Workbook
Name _Hlk69890696: 'ข้อยกเว้น CI 123'!$A$15
Name _Hlk69890696: 'ข้อยกเว้น Roke Rai So Shield'!$A$28
Name _Hlk69890696: 'เงื่อนไขที่สำคัญ ข้อยกเว้น iHU'!$A$34
Name _Hlk69890696: 'เงื่อนไขที่สำคัญ ข้อยกเว้น MEX'!$A$36
Name _Hlk69890696: 'นิยามโรค Roke Rai So Shield'!$B$29
Name _Hlk69890696: 'รายชื่อโรค CI 123'!$A$65
Name _Hlk72091284: 'ผลประโยชน์ โรคร้ายโซชิลด์'!$A$9
Name _Hlk72091284: 'ผลประโยชน์ ไอเฮลท์ตี้ อัลตร้า'!$A$6
Name _Hlk72676939: 'ผลประโยชน์ โรคร้ายโซชิลด์'!$A$54
Name _Hlk72676939: 'ผลประโยชน์ ไอเฮลท์ตี้ อัลตร้า'!$A$63
Name _Hlk72824934: 'ผลประโยชน์ โรคร้ายโซชิลด์'!#REF!
Name _Hlk72824934: 'ผลประโยชน์ ไอเฮลท์ตี้ อัลตร้า'!#REF!
Name _Hlk72839288: 'ผลประโยชน์ โรคร้ายโซชิลด์'!#REF!
Name _Hlk72839288: 'ผลประโยชน์ ไอเฮลท์ตี้ อัลตร้า'!#REF!
Name _Toc98510358: กรอกข้อมูล!$A$85
Name a: '[1]Global Assumption'!$D$13
Name a: '[1]Global Assumption'!$D$13
Name a: '[1]Global Assumption'!$D$13
Name a: '[2]Global Assumption'!$D$13
Name a: '[2]Global Assumption'!$D$13
Name a: '[2]Global Assumption'!$D$13
Name a: '[2]Global Assumption'!$D$13
Name aa: [1]PremiumReport!$A$2
Name aa: [1]PremiumReport!$A$2
Name aa: [1]PremiumReport!$A$2
Name aa: [2]PremiumReport!$A$2
Name aa: [2]PremiumReport!$A$2
Name aa: [2]PremiumReport!$A$2
Name aa: [2]PremiumReport!$A$2
Name age: '[1]Global Assumption'!$D$13
Name age: '[1]Global Assumption'!$D$13
Name age: '[1]Global Assumption'!$D$13
Name age: '[2]Global Assumption'!$D$13
Name age: '[2]Global Assumption'!$D$13
Name age: '[2]Global Assumption'!$D$13
Name age: '[2]Global Assumption'!$D$13
Name BuyOnly: [3]กรอกข้อมูล!#REF!
Name BuyOnly: [4]กรอกข้อมูล!#REF!
Name BuyOnly: [4]กรอกข้อมูล!#REF!
Name BuyOnly: [3]กรอกข้อมูล!#REF!
Name BuyOnly: [3]กรอกข้อมูล!#REF!
Name BuyOnly: [4]กรอกข้อมูล!#REF!
Name BuyOnly: [3]กรอกข้อมูล!#REF!
Name BuyOnly: [4]กรอกข้อมูล!#REF!
Name BuyOnly: กรอกข้อมูล!#REF!
Name CannotBuy: [3]กรอกข้อมูล!#REF!
Name CannotBuy: [4]กรอกข้อมูล!#REF!
Name CannotBuy: [4]กรอกข้อมูล!#REF!
Name CannotBuy: [3]กรอกข้อมูล!#REF!
Name CannotBuy: [3]กรอกข้อมูล!#REF!
Name CannotBuy: [4]กรอกข้อมูล!#REF!
Name CannotBuy: [3]กรอกข้อมูล!#REF!
Name CannotBuy: [4]กรอกข้อมูล!#REF!
Name CannotBuy: กรอกข้อมูล!#REF!
Name CVAge: [5]CVCalculation!$C$2
Name CVAge: [5]CVCalculation!$C$2
Name CVAge: [5]CVCalculation!$C$2
Name CVAge: [6]CVCalculation!$C$2
Name CVAge: [6]CVCalculation!$C$2
Name CVAge: [6]CVCalculation!$C$2

Sheet WPD01
A1: ตารางแสดงอัตราเบี้ยประกันภัย
A2: สัญญาเพิ่มเติมผลประโยชน์ผู้ชำระเบี้ยประกันภัย (WPD01)
A3: ต่อเบี้ยประกันภัย 100 บาท
D5: ระยะเวลายกเว้นเบี้ยประกันภัย (ปี)
A6: age | B6: sex | D6: 10 | E6: 11 | F6: 12 | G6: 13 | H6: 14 | I6: 15 | J6: 16 | K6: 17 | L6: 18 | M6: 19 | N6: 20 | O6: 21 | P6: 22 | Q6: 23 | R6: 24 | S6: 25
A7: 20 | B7: Male | C7: =A7&"-"&LEFT(B7,1) -> 20-M | D7: 1.33 | E7: 1.48 | F7: 1.63 | G7: 1.77 | H7: 1.92 | I7: 2.07 | J7: 2.22 | K7: 2.37 | L7: 2.52 | M7: 2.67 | N7: 2.82 | O7: 2.98 | P7: 3.14 | Q7: 3.3 | R7: 3.47 | S7: 3.63
A8: 21 | B8: Male | C8: =A8&"-"&LEFT(B8,1) -> 21-M | D8: 1.36 | E8: 1.51 | F8: 1.66 | G8: 1.8 | H8: 1.95 | I8: 2.1 | J8: 2.25 | K8: 2.41 | L8: 2.56 | M8: 2.72 | N8: 2.87 | O8: 3.04 | P8: 3.2 | Q8: 3.37 | R8: 3.54 | S8: 3.72
A9: 22 | B9: Male | C9: =A9&"-"&LEFT(B9,1) -> 22-M | D9: 1.37 | E9: 1.52 | F9: 1.67 | G9: 1.83 | H9: 1.98 | I9: 2.13 | J9: 2.28 | K9: 2.44 | L9: 2.6 | M9: 2.76 | N9: 2.92 | O9: 3.09 | P9: 3.26 | Q9: 3.43 | R9: 3.61 | S9: 3.79
A10: 23 | B10: Male | C10: =A10&"-"&LEFT(B10,1) -> 23-M | D10: 1.38 | E10: 1.54 | F10: 1.69 | G10: 1.84 | H10: 1.99 | I10: 2.15 | J10: 2.31 | K10: 2.47 | L10: 2.63 | M10: 2.8 | N10: 2.96 | O10: 3.14 | P10: 3.31 | Q10: 3.5 | R10: 3.68 | S10: 3.88
A11: 24 | B11: Male | C11: =A11&"-"&LEFT(B11,1) -> 24-M | D11: 1.39 | E11: 1.54 | F11: 1.7 | G11: 1.85 | H11: 2.01 | I11: 2.17 | J11: 2.33 | K11: 2.5 | L11: 2.66 | M11: 2.84 | N11: 3.01 | O11: 3.19 | P11: 3.38 | Q11: 3.57 | R11: 3.76 | S11: 3.97
A12: 25 | B12: Male | C12: =A12&"-"&LEFT(B12,1) -> 25-M | D12: 1.4 | E12: 1.55 | F12: 1.71 | G12: 1.87 | H12: 2.03 | I12: 2.19 | J12: 2.36 | K12: 2.53 | L12: 2.71 | M12: 2.88 | N12: 3.07 | O12: 3.26 | P12: 3.45 | Q12: 3.65 | R12: 3.86 | S12: 4.07
A13: 26 | B13: Male | C13: =A13&"-"&LEFT(B13,1) -> 26-M | D13: 1.41 | E13: 1.57 | F13: 1.73 | G13: 1.89 | H13: 2.05 | I13: 2.22 | J13: 2.4 | K13: 2.57 | L13: 2.76 | M13: 2.94 | N13: 3.13 | O13: 3.33 | P13: 3.54 | Q13: 3.74 | R13: 3.96 | S13: 4.18
A14: 27 | B14: Male | C14: =A14&"-"&LEFT(B14,1) -> 27-M | D14: 1.42 | E14: 1.58 | F14: 1.75 | G14: 1.91 | H14: 2.09 | I14: 2.26 | J14: 2.44 | K14: 2.63 | L14: 2.82 | M14: 3.01 | N14: 3.21 | O14: 3.42 | P14: 3.63 | Q14: 3.85 | R14: 4.08 | S14: 4.32
A15: 28 | B15: Male | C15: =A15&"-"&LEFT(B15,1) -> 28-M | D15: 1.44 | E15: 1.6 | F15: 1.77 | G15: 1.95 | H15: 2.13 | I15: 2.31 | J15: 2.5 | K15: 2.69 | L15: 2.89 | M15: 3.1 | N15: 3.31 | O15: 3.53 | P15: 3.75 | Q15: 3.98 | R15: 4.23 | S15: 4.48
A16: 29 | B16: Male | C16: =A16&"-"&LEFT(B16,1) -> 29-M | D16: 1.46 | E16: 1.63 | F16: 1.81 | G16: 1.99 | H16: 2.18 | I16: 2.37 | J16: 2.57 | K16: 2.77 | L16: 2.98 | M16: 3.2 | N16: 3.42 | O16: 3.65 | P16: 3.89 | Q16: 4.13 | R16: 4.39 | S16: 4.66
A17: 30 | B17: Male | C17: =A17&"-"&LEFT(B17,1) -> 30-M | D17: 1.49 | E17: 1.67 | F17: 1.86 | G17: 2.05 | H17: 2.24 | I17: 2.44 | J17: 2.65 | K17: 2.87 | L17: 3.09 | M17: 3.31 | N17: 3.55 | O17: 3.79 | P17: 4.04 | Q17: 4.31 | R17: 4.58 | S17: 4.86
A18: 31 | B18: Male | C18: =A18&"-"&LEFT(B18,1) -> 31-M | D18: 1.53 | E18: 1.72 | F18: 1.92 | G18: 2.11 | H18: 2.32 | I18: 2.53 | J18: 2.75 | K18: 2.98 | L18: 3.21 | M18: 3.45 | N18: 3.7 | O18: 3.96 | P18: 4.22 | Q18: 4.5 | R18: 4.8 | S18: 5.1
... A41: 54 | B41: Male | C41: =A41&"-"&LEFT(B41,1) -> 54-M | D41: 6.79 | E41: 7.81 | F41: 0 | G41: 0 | H41: 0 | I41: 0 | J41: 0 | K41: 0 | L41: 0 | M41: 0 | N41: 0 | O41: 0 | P41: 0 | Q41: 0 | R41: 0 | S41: 0
A42: 55 | B42: Male | C42: =A42&"-"&LEFT(B42,1) -> 55-M | D42: 7.48 | E42: 0 | F42: 0 | G42: 0 | H42: 0 | I42: 0 | J42: 0 | K42: 0
A43: 20 | B43: Female | C43: =A43&"-"&LEFT(B43,1) -> 20-F | D43: 0.44 | E43: 0.49 | F43: 0.54 | G43: 0.59 | H43: 0.65 | I43: 0.7 | J43: 0.75 | K43: 0.81 | L43: 0.86 | M43: 0.92 | N43: 0.98 | O43: 1.04 | P43: 1.1 | Q43: 1.17 | R43: 1.23 | S43: 1.3
A44: 21 | B44: Female | C44: =A44&"-"&LEFT(B44,1) -> 21-F | D44: 0.45 | E44: 0.5 | F44: 0.55 | G44: 0.61 | H44: 0.66 | I44: 0.72 | J44: 0.77 | K44: 0.83 | L44: 0.89 | M44: 0.95 | N44: 1.01 | O44: 1.07 | P44: 1.13 | Q44: 1.2 | R44: 1.27 | S44: 1.34
A45: 22 | B45: Female | C45: =A45&"-"&LEFT(B45,1) -> 22-F | D45: 0.46 | E45: 0.51 | F45: 0.57 | G45: 0.62 | H45: 0.68 | I45: 0.73 | J45: 0.79 | K45: 0.85 | L45: 0.91 | M45: 0.97 | N45: 1.04 | O45: 1.1 | P45: 1.17 | Q45: 1.24 | R45: 1.31 | S45: 1.38
A46: 23 | B46: Female | C46: =A46&"-"&LEFT(B46,1) -> 23-F | D46: 0.47 | E46: 0.52 | F46: 0.58 | G46: 0.63 | H46: 0.69 | I46: 0.75 | J46: 0.81 | K46: 0.87 | L46: 0.94 | M46: 1 | N46: 1.07 | O46: 1.14 | P46: 1.21 | Q46: 1.28 | R46: 1.35 | S46: 1.43
A47: 24 | B47: Female | C47: =A47&"-"&LEFT(B47,1) -> 24-F | D47: 0.48 | E47: 0.53 | F47: 0.59 | G47: 0.65 | H47: 0.71 | I47: 0.77 | J47: 0.84 | K47: 0.9 | L47: 0.97 | M47: 1.03 | N47: 1.1 | O47: 1.18 | P47: 1.25 | Q47: 1.32 | R47: 1.4 | S47: 1.48
A48: 25 | B48: Female | C48: =A48&"-"&LEFT(B48,1) -> 25-F | D48: 0.49 | E48: 0.55 | F48: 0.61 | G48: 0.67 | H48: 0.73 | I48: 0.8 | J48: 0.86 | K48: 0.93 | L48: 1 | M48: 1.07 | N48: 1.14 | O48: 1.22 | P48: 1.29 | Q48: 1.37 | R48: 1.45 | S48: 1.54
A49: 26 | B49: Female | C49: =A49&"-"&LEFT(B49,1) -> 26-F | D49: 0.5 | E49: 0.56 | F49: 0.63 | G49: 0.69 | H49: 0.75 | I49: 0.82 | J49: 0.89 | K49: 0.96 | L49: 1.03 | M49: 1.11 | N49: 1.18 | O49: 1.26 | P49: 1.34 | Q49: 1.43 | R49: 1.51 | S49: 1.6
A50: 27 | B50: Female | C50: =A50&"-"&LEFT(B50,1) -> 27-F | D50: 0.52 | E50: 0.58 | F50: 0.65 | G50: 0.71 | H50: 0.78 | I50: 0.85 | J50: 0.93 | K50: 1 | L50: 1.07 | M50: 1.15 | N50: 1.23 | O50: 1.31 | P50: 1.4 | Q50: 1.49 | R50: 1.58 | S50: 1.68
A51: 28 | B51: Female | C51: =A51&"-"&LEFT(B51,1) -> 28-F | D51: 0.54 | E51: 0.6 | F51: 0.67 | G51: 0.74 | H51: 0.81 | I51: 0.89 | J51: 0.96 | K51: 1.04 | L51: 1.12 | M51: 1.2 | N51: 1.28 | O51: 1.37 | P51: 1.46 | Q51: 1.56 | R51: 1.66 | S51: 1.76
A52: 29 | B52: Female | C52: =A52&"-"&LEFT(B52,1) -> 29-F | D52: 0.56 | E52: 0.63 | F52: 0.7 | G52: 0.77 | H52: 0.85 | I52: 0.93 | J52: 1 | K52: 1.09 | L52: 1.17 | M52: 1.25 | N52: 1.34 | O52: 1.44 | P52: 1.53 | Q52: 1.63 | R52: 1.74 | S52: 1.85
A53: 30 | B53: Female | C53: =A53&"-"&LEFT(B53,1) -> 30-F | D53: 0.58 | E53: 0.66 | F53: 0.73 | G53: 0.81 | H53: 0.89 | I53: 0.97 | J53: 1.05 | K53: 1.14 | L53: 1.22 | M53: 1.31 | N53: 1.41 | O53: 1.51 | P53: 1.61 | Q53: 1.72 | R53: 1.83 | S53: 1.96
A54: 31 | B54: Female | C54: =A54&"-"&LEFT(B54,1) -> 31-F | D54: 0.61 | E54: 0.69 | F54: 0.77 | G54: 0.85 | H54: 0.93 | I54: 1.01 | J54: 1.1 | K54: 1.19 | L54: 1.28 | M54: 1.38 | N54: 1.48 | O54: 1.59 | P54: 1.7 | Q54: 1.82 | R54: 1.94 | S54: 2.07
... A78: 55 | B78: Female | C78: =A78&"-"&LEFT(B78,1) -> 55-F | D78: 4.17 | E78: 0 | F78: 0 | G78: 0 | H78: 0 | I78: 0 | J78: 0 | K78: 0 | L78: 0 | M78: 0 | N78: 0 | O78: 0 | P78: 0 | Q78: 0 | R78: 0 | S78: 0

Sheet WPDD01
A1: ตารางแสดงอัตราเบี้ยประกันภัย
A2: สัญญาเพิ่มเติมผลประโยชน์ผู้ชำระเบี้ยประกันภัย (WPDD01)
A3: ต่อเบี้ยประกันภัย 100 บาท
D5: ระยะเวลายกเว้นเบี้ยประกันภัย (ปี)
A6: age | B6: sex | D6: 10 | E6: 11 | F6: 12 | G6: 13 | H6: 14 | I6: 15 | J6: 16 | K6: 17 | L6: 18 | M6: 19 | N6: 20 | O6: 21 | P6: 22 | Q6: 23 | R6: 24 | S6: 25
A7: 20 | B7: Male | C7: =A7&"-"&LEFT(B7,1) -> 20-M | D7: 1.53 | E7: 1.7 | F7: 1.87 | G7: 2.04 | H7: 2.21 | I7: 2.38 | J7: 2.55 | K7: 2.72 | L7: 2.9 | M7: 3.07 | N7: 3.25 | O7: 3.43 | P7: 3.61 | Q7: 3.8 | R7: 3.99 | S7: 4.18
A8: 21 | B8: Male | C8: =A8&"-"&LEFT(B8,1) -> 21-M | D8: 1.56 | E8: 1.73 | F8: 1.9 | G8: 2.08 | H8: 2.25 | I8: 2.42 | J8: 2.59 | K8: 2.77 | L8: 2.95 | M8: 3.13 | N8: 3.31 | O8: 3.49 | P8: 3.68 | Q8: 3.88 | R8: 4.07 | S8: 4.28
A9: 22 | B9: Male | C9: =A9&"-"&LEFT(B9,1) -> 22-M | D9: 1.58 | E9: 1.75 | F9: 1.93 | G9: 2.1 | H9: 2.27 | I9: 2.45 | J9: 2.63 | K9: 2.81 | L9: 2.99 | M9: 3.17 | N9: 3.36 | O9: 3.55 | P9: 3.75 | Q9: 3.95 | R9: 4.16 | S9: 4.37
A10: 23 | B10: Male | C10: =A10&"-"&LEFT(B10,1) -> 23-M | D10: 1.59 | E10: 1.77 | F10: 1.94 | G10: 2.12 | H10: 2.3 | I10: 2.47 | J10: 2.66 | K10: 2.84 | L10: 3.03 | M10: 3.22 | N10: 3.41 | O10: 3.61 | P10: 3.81 | Q10: 4.02 | R10: 4.24 | S10: 4.46
A11: 24 | B11: Male | C11: =A11&"-"&LEFT(B11,1) -> 24-M | D11: 1.6 | E11: 1.78 | F11: 1.95 | G11: 2.13 | H11: 2.31 | I11: 2.5 | J11: 2.68 | K11: 2.87 | L11: 3.07 | M11: 3.26 | N11: 3.47 | O11: 3.67 | P11: 3.89 | Q11: 4.11 | R11: 4.33 | S11: 4.57
A12: 25 | B12: Male | C12: =A12&"-"&LEFT(B12,1) -> 25-M | D12: 1.61 | E12: 1.79 | F12: 1.97 | G12: 2.15 | H12: 2.34 | I12: 2.52 | J12: 2.72 | K12: 2.91 | L12: 3.11 | M12: 3.32 | N12: 3.53 | O12: 3.75 | P12: 3.97 | Q12: 4.2 | R12: 4.44 | S12: 4.68
A13: 26 | B13: Male | C13: =A13&"-"&LEFT(B13,1) -> 26-M | D13: 1.62 | E13: 1.8 | F13: 1.99 | G13: 2.17 | H13: 2.36 | I13: 2.56 | J13: 2.76 | K13: 2.96 | L13: 3.17 | M13: 3.39 | N13: 3.61 | O13: 3.83 | P13: 4.07 | Q13: 4.31 | R13: 4.56 | S13: 4.82
A14: 27 | B14: Male | C14: =A14&"-"&LEFT(B14,1) -> 27-M | D14: 1.63 | E14: 1.82 | F14: 2.01 | G14: 2.2 | H14: 2.4 | I14: 2.6 | J14: 2.81 | K14: 3.02 | L14: 3.24 | M14: 3.47 | N14: 3.7 | O14: 3.94 | P14: 4.18 | Q14: 4.44 | R14: 4.7 | S14: 4.97
A15: 28 | B15: Male | C15: =A15&"-"&LEFT(B15,1) -> 28-M | D15: 1.65 | E15: 1.85 | F15: 2.04 | G15: 2.24 | H15: 2.45 | I15: 2.66 | J15: 2.87 | K15: 3.1 | L15: 3.33 | M15: 3.56 | N15: 3.81 | O15: 4.06 | P15: 4.32 | Q15: 4.59 | R15: 4.86 | S15: 5.15
A16: 29 | B16: Male | C16: =A16&"-"&LEFT(B16,1) -> 29-M | D16: 1.68 | E16: 1.88 | F16: 2.08 | G16: 2.29 | H16: 2.51 | I16: 2.73 | J16: 2.95 | K16: 3.19 | L16: 3.43 | M16: 3.68 | N16: 3.93 | O16: 4.2 | P16: 4.47 | Q16: 4.76 | R16: 5.05 | S16: 5.36
A17: 30 | B17: Male | C17: =A17&"-"&LEFT(B17,1) -> 30-M | D17: 1.72 | E17: 1.93 | F17: 2.14 | G17: 2.36 | H17: 2.58 | I17: 2.81 | J17: 3.05 | K17: 3.3 | L17: 3.55 | M17: 3.81 | N17: 4.08 | O17: 4.36 | P17: 4.65 | Q17: 4.96 | R17: 5.27 | S17: 5.6
A18: 31 | B18: Male | C18: =A18&"-"&LEFT(B18,1) -> 31-M | D18: 1.77 | E18: 1.98 | F18: 2.2 | G18: 2.43 | H18: 2.67 | I18: 2.91 | J18: 3.17 | K18: 3.42 | L18: 3.69 | M18: 3.97 | N18: 4.25 | O18: 4.55 | P18: 4.86 | Q18: 5.18 | R18: 5.52 | S18: 5.87
... A41: 54 | B41: Male | C41: =A41&"-"&LEFT(B41,1) -> 54-M | D41: 7.81 | E41: 8.99 | F41: 0 | G41: 0 | H41: 0 | I41: 0 | J41: 0 | K41: 0 | L41: 0 | M41: 0 | N41: 0 | O41: 0 | P41: 0 | Q41: 0 | R41: 0 | S41: 0
A42: 55 | B42: Male | C42: =A42&"-"&LEFT(B42,1) -> 55-M | D42: 8.61
A43: 20 | B43: Female | C43: =A43&"-"&LEFT(B43,1) -> 20-F | D43: 0.51 | E43: 0.57 | F43: 0.62 | G43: 0.68 | H43: 0.74 | I43: 0.8 | J43: 0.87 | K43: 0.93 | L43: 0.99 | M43: 1.06 | N43: 1.13 | O43: 1.2 | P43: 1.27 | Q43: 1.34 | R43: 1.41 | S43: 1.49
A44: 21 | B44: Female | C44: =A44&"-"&LEFT(B44,1) -> 21-F | D44: 0.52 | E44: 0.58 | F44: 0.64 | G44: 0.7 | H44: 0.76 | I44: 0.82 | J44: 0.89 | K44: 0.95 | L44: 1.02 | M44: 1.09 | N44: 1.16 | O44: 1.23 | P44: 1.31 | Q44: 1.38 | R44: 1.46 | S44: 1.54
A45: 22 | B45: Female | C45: =A45&"-"&LEFT(B45,1) -> 22-F | D45: 0.53 | E45: 0.59 | F45: 0.65 | G45: 0.71 | H45: 0.78 | I45: 0.84 | J45: 0.91 | K45: 0.98 | L45: 1.05 | M45: 1.12 | N45: 1.19 | O45: 1.27 | P45: 1.35 | Q45: 1.42 | R45: 1.5 | S45: 1.59
A46: 23 | B46: Female | C46: =A46&"-"&LEFT(B46,1) -> 23-F | D46: 0.54 | E46: 0.6 | F46: 0.66 | G46: 0.73 | H46: 0.8 | I46: 0.86 | J46: 0.93 | K46: 1.01 | L46: 1.08 | M46: 1.15 | N46: 1.23 | O46: 1.31 | P46: 1.39 | Q46: 1.47 | R46: 1.56 | S46: 1.64
A47: 24 | B47: Female | C47: =A47&"-"&LEFT(B47,1) -> 24-F | D47: 0.55 | E47: 0.61 | F47: 0.68 | G47: 0.75 | H47: 0.82 | I47: 0.89 | J47: 0.96 | K47: 1.04 | L47: 1.11 | M47: 1.19 | N47: 1.27 | O47: 1.35 | P47: 1.44 | Q47: 1.52 | R47: 1.61 | S47: 1.7
A48: 25 | B48: Female | C48: =A48&"-"&LEFT(B48,1) -> 25-F | D48: 0.56 | E48: 0.63 | F48: 0.7 | G48: 0.77 | H48: 0.84 | I48: 0.92 | J48: 0.99 | K48: 1.07 | L48: 1.15 | M48: 1.23 | N48: 1.31 | O48: 1.4 | P48: 1.49 | Q48: 1.58 | R48: 1.67 | S48: 1.77
A49: 26 | B49: Female | C49: =A49&"-"&LEFT(B49,1) -> 26-F | D49: 0.58 | E49: 0.65 | F49: 0.72 | G49: 0.79 | H49: 0.87 | I49: 0.95 | J49: 1.03 | K49: 1.11 | L49: 1.19 | M49: 1.28 | N49: 1.36 | O49: 1.45 | P49: 1.55 | Q49: 1.64 | R49: 1.74 | S49: 1.84
A50: 27 | B50: Female | C50: =A50&"-"&LEFT(B50,1) -> 27-F | D50: 0.59 | E50: 0.67 | F50: 0.74 | G50: 0.82 | H50: 0.9 | I50: 0.98 | J50: 1.06 | K50: 1.15 | L50: 1.24 | M50: 1.33 | N50: 1.42 | O50: 1.51 | P50: 1.61 | Q50: 1.71 | R50: 1.82 | S50: 1.93
A51: 28 | B51: Female | C51: =A51&"-"&LEFT(B51,1) -> 28-F | D51: 0.62 | E51: 0.69 | F51: 0.77 | G51: 0.85 | H51: 0.94 | I51: 1.02 | J51: 1.11 | K51: 1.2 | L51: 1.29 | M51: 1.38 | N51: 1.48 | O51: 1.58 | P51: 1.68 | Q51: 1.79 | R51: 1.9 | S51: 2.02
A52: 29 | B52: Female | C52: =A52&"-"&LEFT(B52,1) -> 29-F | D52: 0.64 | E52: 0.72 | F52: 0.8 | G52: 0.89 | H52: 0.98 | I52: 1.06 | J52: 1.15 | K52: 1.25 | L52: 1.34 | M52: 1.44 | N52: 1.55 | O52: 1.65 | P52: 1.76 | Q52: 1.88 | R52: 2 | S52: 2.13
A53: 30 | B53: Female | C53: =A53&"-"&LEFT(B53,1) -> 30-F | D53: 0.67 | E53: 0.75 | F53: 0.84 | G53: 0.93 | H53: 1.02 | I53: 1.11 | J53: 1.21 | K53: 1.31 | L53: 1.41 | M53: 1.51 | N53: 1.62 | O53: 1.73 | P53: 1.85 | Q53: 1.98 | R53: 2.11 | S53: 2.25
A54: 31 | B54: Female | C54: =A54&"-"&LEFT(B54,1) -> 31-F | D54: 0.7 | E54: 0.79 | F54: 0.88 | G54: 0.97 | H54: 1.07 | I54: 1.16 | J54: 1.26 | K54: 1.37 | L54: 1.48 | M54: 1.59 | N54: 1.7 | O54: 1.83 | P54: 1.95 | Q54: 2.09 | R54: 2.23 | S54: 2.39
... A78: 55 | B78: Female | C78: =A78&"-"&LEFT(B78,1) -> 55-F | D78: 4.79 | E78: 0 | F78: 0 | G78: 0 | H78: 0 | I78: 0 | J78: 0 | K78: 0 | L78: 0 | M78: 0 | N78: 0 | O78: 0 | P78: 0 | Q78: 0 | R78: 0 | S78: 0

Sheet Rate Rider
A1: MEB | I1: MEA+ | V1: Rate DCI,PLS
J2: ข้อมูล | K2: plan | W2: age | Y2: M | Z2: F | AC2: AP | AD2: ECARE | AG2: ผลประโยชน์ | AH2: 1000 | AI2: 2200 | AJ2: 3200 | AK2: 4200 | AL2: 6200
A3: ผลรวมของ rate | B3: plan | J3: ผลรวมของ Male | O3: ผลรวมของ Female | AB3: 1 | AC3: 3 | AD3: 6.5 | AG3: 6.1 ค่าห้อง ค่าอาหาร และค่าบริการพยาบาลประจำวันในโรงพยาบาลต่อวัน (สูงสุด 75 วัน) | AH3: 1000 | AI3: 2200 | AJ3: 3200 | AK3: 4200 | AL3: 6200
A4: ageMin | B4: 500 | C4: 1000 | D4: 2000 | E4: 3000 | F4: 4000 | G4: 5000 | I4: ageMin | J4: M-1000 | K4: M-2200 | L4: M-3200 | M4: M-4200 | N4: M-6200 | O4: F-1000 | P4: F-2200 | Q4: F-3200 | R4: F-4200 | S4: F-6200 | AB4: 2 | AC4: 4.05 | AD4: 7.5 | AG4: 6.2 ค่าห้อง ไอ ซี ยู ต่อวัน (สูงสุด 20 วัน) โดยจำนวนวันในข้อ (6.1)+(6.2) สูงสุดไม่เกิน 75 วัน | AH4: 2000 | AI4: 4400 | AJ4: 6400 | AK4: 8400 | AL4: 12400
A5: 6 | B5: 475 | C5: 950 | D5: 0 | E5: 0 | F5: 0 | G5: 0 | I5: 0 | J5: 10631 | K5: 16683 | L5: 22437 | M5: 26774 | N5: 34740 | O5: 10631 | P5: 16683 | Q5: 22437 | R5: 26774 | S5: 34740 | AB5: 3 | AC5: 5.1 | AD5: 8.5 | AG5: 6.3 ค่าแพทย์ตรวจรักษาในโรงพยาบาลประจำวันต่อวัน (สูงสุด 75 วัน) | AH5: 600 | AI5: 800 | AJ5: 900 | AK5: 1000 | AL5: 1200
A6: 7 | B6: 475 | C6: 950 | D6: 0 | E6: 0 | F6: 0 | G6: 0 | I6: 1 | J6: 10631 | K6: 16683 | L6: 22437 | M6: 26774 | N6: 34740 | O6: 10631 | P6: 16683 | Q6: 22437 | R6: 26774 | S6: 34740 | AB6: 4 | AC6: 6 | AD6: 10.5 | AG6: 6.4 ค่าปรึกษาแพทย์เฉพาะทางในโรงพยาบาล ต่อการปรึกษาแต่ละครั้ง (1 ครั้งต่อวัน สูงสุด 20 ครั้งต่อปี) | AH6: 900 | AI6: 1200 | AJ6: 1300 | AK6: 1400 | AL6: 1600
A7: 8 | B7: 475 | C7: 950 | D7: 0 | E7: 0 | F7: 0 | G7: 0 | I7: 2 | J7: 10631 | K7: 16683 | L7: 22437 | M7: 26774 | N7: 34740 | O7: 10631 | P7: 16683 | Q7: 22437 | R7: 26774 | S7: 34740 | AG7: 6.5 ค่าแพทย์ผ่าตัดและหัตถการ ต่อการเข้าพักรักษาตัวครั้งใดครั้งหนึ่ง | AH7: 40000 | AI7: 65000 | AJ7: 85000 | AK7: 100000 | AL7: 120000
A8: 9 | B8: 475 | C8: 950 | D8: 0 | E8: 0 | F8: 0 | G8: 0 | I8: 3 | J8: 10631 | K8: 16683 | L8: 22437 | M8: 26774 | N8: 34740 | O8: 10631 | P8: 16683 | Q8: 22437 | R8: 26774 | S8: 34740 | AG8: (เป็นไปตามอัตราที่กำหนดในตารางผลประโยชน์ผ่าตัด/วางยาสลบ แนบท้ายกรมธรรม์)
A9: 10 | B9: 475 | C9: 950 | D9: 0 | E9: 0 | F9: 0 | G9: 0 | I9: 4 | J9: 10631 | K9: 16683 | L9: 22437 | M9: 26774 | N9: 34740 | O9: 10631 | P9: 16683 | Q9: 22437 | R9: 26774 | S9: 34740 | AG9: - รับเพิ่ม 70% ของค่าใช้จ่ายส่วนที่เกินสิทธิ ในอัตราที่กำหนดในตารางผลประโยชน์ผ่าตัด ตามเงื่อนไขของกรมธรรม์ (กรณีค่าใช้จ่ายรวมทั้งหมดไม่เกินผลประโยชน์สูงสุดของแต่ละแผน)
A10: 11 | B10: 475 | C10: 950 | D10: 0 | E10: 0 | F10: 0 | G10: 0 | I10: 5 | J10: 10631 | K10: 16683 | L10: 22437 | M10: 26774 | N10: 34740 | O10: 10631 | P10: 16683 | Q10: 22437 | R10: 26774 | S10: 34740 | AG10: 6.6 ค่าแพทย์วิสัญญี ต่อการเข้าพักรักษาตัวครั้งใดครั้งหนึ่ง (ตามอัตราที่กำหนดในตารางค่าผ่าตัด / วางยาสลบ แนบท้ายกรมธรรม์) | AH10: 6750 | AI10: 9750 | AJ10: 13500 | AK10: 15000 | AL10: 18000
A11: 12 | B11: 475 | C11: 950 | D11: 0 | E11: 0 | F11: 0 | G11: 0 | I11: 6 | J11: 5893 | K11: 9248 | L11: 12438 | M11: 14842 | N11: 19258 | O11: 5893 | P11: 9248 | Q11: 12438 | R11: 14842 | S11: 19258 | AG11: 6.7 ค่าห้องผ่าตัดและอุปกรณ์ในห้องผ่าตัด ต่อการเข้าพักรักษาตัวใดครั้งหนึ่ง | AH11: 13500 | AI11: 19500 | AJ11: 27000 | AK11: 30000 | AL11: 36000
A12: 13 | B12: 475 | C12: 950 | D12: 0 | E12: 0 | F12: 0 | G12: 0 | I12: 7 | J12: 5893 | K12: 9248 | L12: 12438 | M12: 14842 | N12: 19258 | O12: 5893 | P12: 9248 | Q12: 12438 | R12: 14842 | S12: 19258 | AG12: 6.8 ค่ารักษาพยาบาลอื่นๆ ต่อการเข้าพักรักษาตัวครั้งใดครั้งหนึ่ง (รวมค่ายากลับบ้าน ค่ารถพยาบาล และอื่นๆ) | AH12: 15000 | AI12: 20000 | AJ12: 30000 | AK12: 35000 | AL12: 45000
A13: 14 | B13: 475 | C13: 950 | D13: 0 | E13: 0 | F13: 0 | G13: 0 | I13: 8 | J13: 5893 | K13: 9248 | L13: 12438 | M13: 14842 | N13: 19258 | O13: 5893 | P13: 9248 | Q13: 12438 | R13: 14842 | S13: 19258 | AG13: - รับเพิ่ม 70% ของค่าใช้จ่ายส่วนที่เกินสิทธิสำหรับค่ารักษาพยาบาลอื่นๆ ในฐานะผู้ป่วยในตามเงื่อนไขของกรมธรรม์ (กรณีค่าใช้จ่ายรวมทั้งหมดไม่เกินผลประโยชน์สูงสุดของแต่ละแผน)
A14: 15 | B14: 475 | C14: 950 | D14: 0 | E14: 0 | F14: 0 | G14: 0 | I14: 9 | J14: 5893 | K14: 9248 | L14: 12438 | M14: 14842 | N14: 19258 | O14: 5893 | P14: 9248 | Q14: 12438 | R14: 14842 | S14: 19258 | AG14: 6.9 ค่าตรวจวินิจฉัยทางรังสีวิทยาและการตรวจในห้องปฎิบัติการในฐานะผู้ป่วยนอก ต่อการบาดเจ็บหรือเจ็บป่วยแต่ละครั้ง (ซึ่งเกิดขึ้นภายใน 30 วัน ก่อนหรือหลังการเข้ารักษาตัวในโรงพยาบาล) | AH14: 4000 | AI14: 6000 | AJ14: 8000 | AK14: 10000 | AL14: 14000
A15: 16 | B15: 650 | C15: 1300 | D15: 2600 | E15: 3900 | F15: 5200 | G15: 6500 | I15: 10 | J15: 5893 | K15: 9248 | L15: 12438 | M15: 14842 | N15: 19258 | O15: 5893 | P15: 9248 | Q15: 12438 | R15: 14842 | S15: 19258 | AG15: 6.10 ค่ารักษาพยาบาลฉุกเฉินขณะเป็นผู้ป่วยนอก (เนื่องจากอุบัติเหตุ) ต่อการบาดเจ็บแต่ละครั้ง | AH15: 3500 | AI15: 6000 | AJ15: 9000 | AK15: 10000 | AL15: 12000
A16: 17 | B16: 650 | C16: 1300 | D16: 2600 | E16: 3900 | F16: 5200 | G16: 6500 | I16: 11 | J16: 5354 | K16: 8401 | L16: 11299 | M16: 13483 | N16: 17495 | O16: 5354 | P16: 8401 | Q16: 11299 | R16: 13483 | S16: 17495 | AG16: 6.11 ค่ารักษาพยาบาลในฐานะผู้ป่วยนอกต่อเนื่องจากการรักษาพยาบาลในฐานะผู้ป่วยใน โดยเกิดขึ้นภายใน 30 วัน หลังออกจากโรงพยาบาลในฐานะผู้ป่วยใน | AH16: ตามเงื่อนไขของสัญญา | AI16: ตามเงื่อนไขของสัญญา | AJ16: ตามเงื่อนไขของสัญญา | AK16: ตามเงื่อนไขของสัญญา | AL16: ตามเงื่อนไขของสัญญา
A17: 18 | B17: 650 | C17: 1300 | D17: 2600 | E17: 3900 | F17: 5200 | G17: 6500 | I17: 12 | J17: 5354 | K17: 8401 | L17: 11299 | M17: 13483 | N17: 17495 | O17: 5354 | P17: 8401 | Q17: 11299 | R17: 13483 | S17: 17495 | AG17: ผลประโยชน์สูงสุด ต่อการเข้าพักรักษาตัวครั้งใดครั้งหนึ่ง | AH17: 280000 | AI17: 480000 | AJ17: 650000 | AK17: 800000 | AL17: 1100000
A18: 19 | B18: 650 | C18: 1300 | D18: 2600 | E18: 3900 | F18: 5200 | G18: 6500 | I18: 13 | J18: 5354 | K18: 8401 | L18: 11299 | M18: 13483 | N18: 17495 | O18: 5354 | P18: 8401 | Q18: 11299 | R18: 13483 | S18: 17495
A19: 20 | B19: 650 | C19: 1300 | D19: 2600 | E19: 3900 | F19: 5200 | G19: 6500 | I19: 14 | J19: 5354 | K19: 8401 | L19: 11299 | M19: 13483 | N19: 17495 | O19: 5354 | P19: 8401 | Q19: 11299 | R19: 13483 | S19: 17495
A20: 21 | B20: 650 | C20: 1300 | D20: 2600 | E20: 3900 | F20: 5200 | G20: 6500 | I20: 15 | J20: 5354 | K20: 8401 | L20: 11299 | M20: 13483 | N20: 17495 | O20: 5354 | P20: 8401 | Q20: 11299 | R20: 13483 | S20: 17495
A21: 22 | B21: 650 | C21: 1300 | D21: 2600 | E21: 3900 | F21: 5200 | G21: 6500 | I21: 16 | J21: 4237 | K21: 6648 | L21: 8942 | M21: 10670 | N21: 13845 | O21: 4622 | P21: 7253 | Q21: 9755 | R21: 11640 | S21: 15103
A22: 23 | B22: 650 | C22: 1300 | D22: 2600 | E22: 3900 | F22: 5200 | G22: 6500 | I22: 17 | J22: 4237 | K22: 6648 | L22: 8942 | M22: 10670 | N22: 13845 | O22: 4622 | P22: 7253 | Q22: 9755 | R22: 11640 | S22: 15103
A23: 24 | B23: 650 | C23: 1300 | D23: 2600 | E23: 3900 | F23: 5200 | G23: 6500 | I23: 18 | J23: 4237 | K23: 6648 | L23: 8942 | M23: 10670 | N23: 13845 | O23: 4622 | P23: 7253 | Q23: 9755 | R23: 11640 | S23: 15103
A24: 25 | B24: 650 | C24: 1300 | D24: 2600 | E24: 3900 | F24: 5200 | G24: 6500 | I24: 19 | J24: 4237 | K24: 6648 | L24: 8942 | M24: 10670 | N24: 13845 | O24: 4622 | P24: 7253 | Q24: 9755 | R24: 11640 | S24: 15103
A25: 26 | B25: 650 | C25: 1300 | D25: 2600 | E25: 3900 | F25: 5200 | G25: 6500 | I25: 20 | J25: 4237 | K25: 6648 | L25: 8942 | M25: 10670 | N25: 13845 | O25: 4622 | P25: 7253 | Q25: 9755 | R25: 11640 | S25: 15103
A26: 27 | B26: 650 | C26: 1300 | D26: 2600 | E26: 3900 | F26: 5200 | G26: 6500 | I26: 21 | J26: 3852 | K26: 6044 | L26: 8129 | M26: 9700 | N26: 12586 | O26: 5008 | P26: 7857 | Q26: 10568 | R26: 12610 | S26: 16362
A27: 28 | B27: 650 | C27: 1300 | D27: 2600 | E27: 3900 | F27: 5200 | G27: 6500 | I27: 22 | J27: 3852 | K27: 6044 | L27: 8129 | M27: 9700 | N27: 12586 | O27: 5008 | P27: 7857 | Q27: 10568 | R27: 12610 | S27: 16362
A28: 29 | B28: 650 | C28: 1300 | D28: 2600 | E28: 3900 | F28: 5200 | G28: 6500 | I28: 23 | J28: 3852 | K28: 6044 | L28: 8129 | M28: 9700 | N28: 12586 | O28: 5008 | P28: 7857 | Q28: 10568 | R28: 12610 | S28: 16362
A29: 30 | B29: 650 | C29: 1300 | D29: 2600 | E29: 3900 | F29: 5200 | G29: 6500 | I29: 24 | J29: 3852 | K29: 6044 | L29: 8129 | M29: 9700 | N29: 12586 | O29: 5008 | P29: 7857 | Q29: 10568 | R29: 12610 | S29: 16362
... A42: 43 | B42: 750 | C42: 1500 | D42: 3000 | E42: 4500 | F42: 6000 | G42: 7500 | I42: 37 | J42: 4622 | K42: 7253 | L42: 9755 | M42: 11640 | N42: 15103 | O42: 6009 | P42: 9429 | Q42: 12681 | R42: 15132 | S42: 19634
A43: 44 | B43: 750 | C43: 1500 | D43: 3000 | E43: 4500 | F43: 6000 | G43: 7500 | I43: 38 | J43: 4622 | K43: 7253 | L43: 9755 | M43: 11640 | N43: 15103 | O43: 6009 | P43: 9429 | Q43: 12681 | R43: 15132 | S43: 19634 | V43: DCI | W43: 20 | X43: DCI-20 | Y43: 2.35 | Z43: 1.92
A44: 45 | B44: 750 | C44: 1500 | D44: 3000 | E44: 4500 | F44: 6000 | G44: 7500 | I44: 39 | J44: 4622 | K44: 7253 | L44: 9755 | M44: 11640 | N44: 15103 | O44: 6009 | P44: 9429 | Q44: 12681 | R44: 15132 | S44: 19634 | V44: DCI | W44: 21 | X44: DCI-21 | Y44: 2.45 | Z44: 2.01
A45: 46 | B45: 750 | C45: 1500 | D45: 3000 | E45: 4500 | F45: 6000 | G45: 7500 | I45: 40 | J45: 4622 | K45: 7253 | L45: 9755 | M45: 11640 | N45: 15103 | O45: 6009 | P45: 9429 | Q45: 12681 | R45: 15132 | S45: 19634 | V45: DCI | W45: 22 | X45: DCI-22 | Y45: 2.54 | Z45: 2.1
A46: 47 | B46: 750 | C46: 1500 | D46: 3000 | E46: 4500 | F46: 6000 | G46: 7500 | I46: 41 | J46: 5008 | K46: 7857 | L46: 10568 | M46: 12610 | N46: 16362 | O46: 6510 | P46: 10214 | Q46: 13738 | R46: 16393 | S46: 21270 | V46: DCI | W46: 23 | X46: DCI-23 | Y46: 2.61 | Z46: 2.18
A47: 48 | B47: 750 | C47: 1500 | D47: 3000 | E47: 4500 | F47: 6000 | G47: 7500 | I47: 42 | J47: 5008 | K47: 7857 | L47: 10568 | M47: 12610 | N47: 16362 | O47: 6510 | P47: 10214 | Q47: 13738 | R47: 16393 | S47: 21270 | V47: DCI | W47: 24 | X47: DCI-24 | Y47: 2.66 | Z47: 2.24
A48: 49 | B48: 750 | C48: 1500 | D48: 3000 | E48: 4500 | F48: 6000 | G48: 7500 | I48: 43 | J48: 5008 | K48: 7857 | L48: 10568 | M48: 12610 | N48: 16362 | O48: 6510 | P48: 10214 | Q48: 13738 | R48: 16393 | S48: 21270 | V48: DCI | W48: 25 | X48: DCI-25 | Y48: 2.7 | Z48: 2.28
A49: 50 | B49: 750 | C49: 1500 | D49: 3000 | E49: 4500 | F49: 6000 | G49: 7500 | I49: 44 | J49: 5008 | K49: 7857 | L49: 10568 | M49: 12610 | N49: 16362 | O49: 6510 | P49: 10214 | Q49: 13738 | R49: 16393 | S49: 21270 | V49: DCI | W49: 26 | X49: DCI-26 | Y49: 2.77 | Z49: 2.34
A50: 51 | B50: 1000 | C50: 2000 | D50: 4000 | E50: 6000 | F50: 8000 | G50: 10000 | I50: 45 | J50: 5008 | K50: 7857 | L50: 10568 | M50: 12610 | N50: 16362 | O50: 6510 | P50: 10214 | Q50: 13738 | R50: 16393 | S50: 21270 | V50: DCI | W50: 27 | X50: DCI-27 | Y50: 2.85 | Z50: 2.4
A51: 52 | B51: 1000 | C51: 2000 | D51: 4000 | E51: 6000 | F51: 8000 | G51: 10000 | I51: 46 | J51: 5585 | K51: 8764 | L51: 11787 | M51: 14065 | N51: 18250 | O51: 7280 | P51: 11423 | Q51: 15364 | R51: 18333 | S51: 23788 | V51: DCI | W51: 28 | X51: DCI-28 | Y51: 2.97 | Z51: 2.49
A52: 53 | B52: 1000 | C52: 2000 | D52: 4000 | E52: 6000 | F52: 8000 | G52: 10000 | I52: 47 | J52: 5585 | K52: 8764 | L52: 11787 | M52: 14065 | N52: 18250 | O52: 7280 | P52: 11423 | Q52: 15364 | R52: 18333 | S52: 23788 | V52: DCI | W52: 29 | X52: DCI-29 | Y52: 3.09 | Z52: 2.6
A53: 54 | B53: 1000 | C53: 2000 | D53: 4000 | E53: 6000 | F53: 8000 | G53: 10000 | I53: 48 | J53: 5585 | K53: 8764 | L53: 11787 | M53: 14065 | N53: 18250 | O53: 7280 | P53: 11423 | Q53: 15364 | R53: 18333 | S53: 23788 | V53: DCI | W53: 30 | X53: DCI-30 | Y53: 3.22 | Z53: 2.68
A54: 55 | B54: 1000 | C54: 2000 | D54: 4000 | E54: 6000 | F54: 8000 | G54: 10000 | I54: 49 | J54: 5585 | K54: 8764 | L54: 11787 | M54: 14065 | N54: 18250 | O54: 7280 | P54: 11423 | Q54: 15364 | R54: 18333 | S54: 23788 | V54: DCI | W54: 31 | X54: DCI-31 | Y54: 3.35 | Z54: 2.75
... A73: 74 | B73: 3210 | C73: 6420 | D73: 12840 | E73: 19260 | F73: 25680 | G73: 32100 | I73: 68 | J73: 17411 | K73: 27319 | L73: 36743 | M73: 43844 | N73: 56889 | O73: 22688 | P73: 35599 | Q73: 47880 | R73: 57133 | S73: 74132 | V73: DCI | W73: 50 | X73: DCI-50 | Y73: 12.04 | Z73: 9.76
I74: 69 | J74: 18798 | K74: 29495 | L74: 39670 | M74: 47336 | N74: 61420 | O74: 24383 | P74: 38259 | Q74: 51457 | R74: 61401 | S74: 79669 | V74: DCI | W74: 51 | X74: DCI-51 | Y74: 13.1 | Z74: 10.46
I75: 70 | J75: 20107 | K75: 31550 | L75: 42433 | M75: 50634 | N75: 65699 | O75: 26194 | P75: 41099 | Q75: 55277 | R75: 65960 | S75: 85585 | V75: DCI | W75: 52 | X75: DCI-52 | Y75: 14.23 | Z75: 11.22
I76: 71 | J76: 21956 | K76: 34451 | L76: 46335 | M76: 55290 | N76: 71740 | O76: 28543 | P76: 44786 | Q76: 60236 | R76: 71877 | S76: 93262 | V76: DCI | W76: 53 | X76: DCI-53 | Y76: 15.55 | Z76: 12.15
I77: 72 | J77: 23844 | K77: 37412 | L77: 50319 | M77: 60043 | N77: 77907 | O77: 31047 | P77: 48715 | Q77: 65520 | R77: 78182 | S77: 101443 | V77: DCI | W77: 54 | X77: DCI-54 | Y77: 17.16 | Z77: 13.21
I78: 73 | J78: 25770 | K78: 40434 | L78: 54383 | M78: 64893 | N78: 84200 | O78: 33512 | P78: 52583 | Q78: 70722 | R78: 84390 | S78: 109498 | V78: DCI | W78: 55 | X78: DCI-55 | Y78: 19.01 | Z78: 14.37
I79: 74 | J79: 27696 | K79: 43456 | L79: 58448 | M79: 69743 | N79: 90493 | O79: 36016 | P79: 56511 | Q79: 76006 | R79: 90695 | S79: 117679 | V79: DCI | W79: 56 | X79: DCI-56 | Y79: 20.59 | Z79: 15.57
V80: DCI | W80: 57 | X80: DCI-57 | Y80: 22.25 | Z80: 16.88
V81: DCI | W81: 58 | X81: DCI-58 | Y81: 24.02 | Z81: 18.34
V82: DCI | W82: 59 | X82: DCI-59 | Y82: 25.89 | Z82: 19.93
V83: DCI | W83: 60 | X83: DCI-60 | Y83: 28.03 | Z83: 21.67
V84: DCI | W84: 61 | X84: DCI-61 | Y84: 30.11 | Z84: 23.32
V85: DCI | W85: 62 | X85: DCI-62 | Y85: 32.37 | Z85: 25.14
V86: DCI | W86: 63 | X86: DCI-63 | Y86: 35.06 | Z86: 27.39
V87: DCI | W87: 64 | X87: DCI-64 | Y87: 38.01 | Z87: 29.69
V88: DCI | W88: 65 | X88: DCI-65 | Y88: 41.2 | Z88: 32.15
V89: DCI | W89: 66 | X89: DCI-66 | Y89: 43.22 | Z89: 34.49
V90: DCI | W90: 67 | X90: DCI-67 | Y90: 45.33 | Z90: 36.9
V91: DCI | W91: 68 | X91: DCI-68 | Y91: 49.44 | Z91: 40.04
... V257: PLS15 | W257: 59 | X257: PLS15-59 | Y257: 35.66 | Z257: 21.82
V258: CPR | W258: 0 | X258: =V258&"-"&W258 -> CPR-0 | Y258: 0.36 | Z258: 0.32
V259: CPR | W259: 1 | X259: =V259&"-"&W259 -> CPR-1 | Y259: 0.36 | Z259: 0.32
V260: CPR | W260: 2 | X260: =V260&"-"&W260 -> CPR-2 | Y260: 0.36 | Z260: 0.32
V261: CPR | W261: 3 | X261: =V261&"-"&W261 -> CPR-3 | Y261: 0.33 | Z261: 0.29
V262: CPR | W262: 4 | X262: =V262&"-"&W262 -> CPR-4 | Y262: 0.29 | Z262: 0.25
V263: CPR | W263: 5 | X263: =V263&"-"&W263 -> CPR-5 | Y263: 0.24 | Z263: 0.21
V264: CPR | W264: 6 | X264: =V264&"-"&W264 -> CPR-6 | Y264: 0.19 | Z264: 0.16
V265: CPR | W265: 7 | X265: =V265&"-"&W265 -> CPR-7 | Y265: 0.16 | Z265: 0.13
V266: CPR | W266: 8 | X266: =V266&"-"&W266 -> CPR-8 | Y266: 0.13 | Z266: 0.12
V267: CPR | W267: 9 | X267: =V267&"-"&W267 -> CPR-9 | Y267: 0.13 | Z267: 0.12
V268: CPR | W268: 10 | X268: =V268&"-"&W268 -> CPR-10 | Y268: 0.13 | Z268: 0.13
V269: CPR | W269: 11 | X269: =V269&"-"&W269 -> CPR-11 | Y269: 0.15 | Z269: 0.15
... V427: HIC | W427: 84 | X427: =V427&"-"&W427 -> HIC-84 | Y427: 406.07 | Z427: 357.4

Sheet Rate rider_MEX
A1: Rider Plan | B1: MEX1 | C1: MEX2 | D1: MEX3 | E1: MEX4 | F1: MEX5 | G1: MEX1 | H1: MEX2 | I1: MEX3 | J1: MEX4 | K1: MEX5
A2: Rider Class | B2: 1 | C2: 1 | D2: 1 | E2: 1 | F2: 1 | G2: 1 | H2: 1 | I2: 1 | J2: 1 | K2: 1
A3: Gender | B3: F | C3: F | D3: F | E3: F | F3: F | G3: M | H3: M | I3: M | J3: M | K3: M
A4: Rider Eff. | B4: 20210801 | C4: 20210801 | D4: 20210801 | E4: 20210801 | F4: 20210801 | G4: 20210801 | H4: 20210801 | I4: 20210801 | J4: 20210801 | K4: 20210801
B5: F-1200 | C5: F-2200 | D5: F-3200 | E5: F-4200 | F5: F-6200 | G5: M-1200 | H5: M-2200 | I5: M-3200 | J5: M-4200 | K5: M-6200
A6: 0 | B6: 25781 | C6: 40182 | D6: 54257 | E6: 0 | F6: 0 | G6: 31209 | H6: 48642 | I6: 65680 | J6: 0 | K6: 0
A7: 1 | B7: 25781 | C7: 40182 | D7: 54257 | E7: 0 | F7: 0 | G7: 29995 | H7: 46749 | I7: 63125 | J7: 0 | K7: 0
A8: 2 | B8: 25781 | C8: 40182 | D8: 54257 | E8: 0 | F8: 0 | G8: 29995 | H8: 46749 | I8: 63125 | J8: 0 | K8: 0
A9: 3 | B9: 20282 | C9: 31612 | D9: 42684 | E9: 0 | F9: 0 | G9: 23781 | H9: 37066 | I9: 50049 | J9: 0 | K9: 0
A10: 4 | B10: 14926 | C10: 23263 | D10: 31412 | E10: 0 | F10: 0 | G10: 18640 | H10: 29051 | I10: 39228 | J10: 0 | K10: 0
A11: 5 | B11: 12498 | C11: 19479 | D11: 26302 | E11: 0 | F11: 0 | G11: 14569 | H11: 22707 | I11: 30661 | J11: 0 | K11: 0
A12: 6 | B12: 10641 | C12: 16585 | D12: 22394 | E12: 0 | F12: 0 | G12: 12641 | H12: 19702 | I12: 26603 | J12: 0 | K12: 0
A13: 7 | B13: 9427 | C13: 14693 | D13: 19839 | E13: 0 | F13: 0 | G13: 9855 | H13: 15361 | I13: 20741 | J13: 0 | K13: 0
A14: 8 | B14: 7856 | C14: 12244 | D14: 16533 | E14: 0 | F14: 0 | G14: 8141 | H14: 12689 | I14: 17134 | J14: 0 | K14: 0
A15: 9 | B15: 6856 | C15: 10686 | D15: 14429 | E15: 0 | F15: 0 | G15: 6999 | H15: 10908 | I15: 14729 | J15: 0 | K15: 0
A16: 10 | B16: 5713 | C16: 8905 | D16: 12024 | E16: 0 | F16: 0 | G16: 5856 | H16: 9127 | I16: 12324 | J16: 0 | K16: 0
A17: 11 | B17: 7641 | C17: 11910 | D17: 16082 | E17: 19184 | F17: 26299 | G17: 7689 | H17: 11984 | I17: 16182 | J17: 19304 | K17: 26462
... A95: 89 | B95: 81700 | C95: 127336 | D95: 171940 | E95: 205107 | F95: 281174 | G95: 98268 | H95: 153160 | I95: 206809 | J95: 246702 | K95: 338195

Sheet iHealthy Ultra Rate
B1: Check | C1: =กรอกข้อมูล!M29 -> No
B2: Insure Age | C2: =กรอกข้อมูล!$C$5 -> 44 | D2: =IF(C2<11,"J","S") -> S | H2: เอเชีย | I2: A
B3: Gender | C3: =กรอกข้อมูล!$C$6 -> หญิง | D3: =IF(OR(C3="ชาย",C3="Male"),"M","F") -> F | H3: ทั่วโลก | I3: W
B4: แผนไอเฮลท์ตี้ อัลตร้า | C4: =กรอกข้อมูล!$M$27 -> 0 | D4: =กรอกข้อมูล!$R$37 | H4: ประเทศไทย
B5: Coverage | C5: =กรอกข้อมูล!D31 -> 0 | D5: =IFERROR(IF(C5="Full Coverage","",IF(C5="Deductible","D",IF(C5="Co-Payment","C",""))),"")
B6: Cover | C6: =กรอกข้อมูล!$M$28 -> ประเทศไทย | D6: =VLOOKUP($C6,H2:I4,2,FALSE)
B7: Key | D7: =TRIM("MHP"&D5&D4&D2&D6) -> MHPS | E7: =D7&"-"&D3 -> MHPS-F
B8: Premium | D8: =IF(C1="OK",HLOOKUP(E7,$B$9:$BU$111,C2+5,0),0) -> 0
A9: Key | B9: MHP1J-F | C9: MHP1S-F | D9: MHP2J-F | E9: MHP2S-F | F9: MHP3S-F | G9: MHP4S-F | H9: MHP5S-F | I9: MHP5SA-F | J9: MHP5SW-F | K9: MHP6S-F | L9: MHP6SA-F | M9: MHP6SW-F | N9: MHP1J-M | O9: MHP1S-M | P9: MHP2J-M | Q9: MHP2S-M | R9: MHP3S-M | S9: MHP4S-M | T9: MHP5S-M | U9: MHP5SA-M | V9: MHP5SW-M | W9: MHP6S-M | X9: MHP6SA-M | Y9: MHP6SW-M | Z9: MHPC1J-F | AA9: MHPC1S-F | AB9: MHPC2J-F | AC9: MHPC2S-F | AD9: MHPC3S-F | AE9: MHPC4S-F | AF9: MHPC5S-F | AG9: MHPCSA-F | AH9: MHPCSW-F | AI9: MHPC6S-F | AJ9: MHPCSA-F | AK9: MHPCSW-F | AL9: MHPC1J-M | AM9: MHPC1S-M | AN9: MHPC2J-M | AO9: MHPC2S-M | AP9: MHPC3S-M | AQ9: MHPC4S-M | AR9: MHPC5S-M | AS9: MHPCSA-M | AT9: MHPCSW-M | AU9: MHPC6S-M | AV9: MHPCSA-M | AW9: MHPCSW-M | AX9: MHPD1J-F | AY9: MHPD1S-F | AZ9: MHPD2J-F | BA9: MHPD2S-F | BB9: MHPD3S-F | BC9: MHPD4S-F | BD9: MHPD5S-F | BE9: MHPDSA-F | BF9: MHPDSW-F | BG9: MHPD6S-F | BH9: MHPDSA-F | BI9: MHPDSW-F | BJ9: MHPD1J-M | BK9: MHPD1S-M | BL9: MHPD2J-M | BM9: MHPD2S-M | BN9: MHPD3S-M | BO9: MHPD4S-M | BP9: MHPD5S-M | BQ9: MHPDSA-M | BR9: MHPDSW-M | BS9: MHPD6S-M | BT9: MHPDSA-M | BU9: MHPDSW-M
A10: Plan code | B10: MHP1J | C10: MHP1S | D10: MHP2J | E10: MHP2S | F10: MHP3S | G10: MHP4S | H10: MHP5S | I10: MHP5SA | J10: MHP5SW | K10: MHP6S | L10: MHP6SA | M10: MHP6SW | N10: MHP1J | O10: MHP1S | P10: MHP2J | Q10: MHP2S | R10: MHP3S | S10: MHP4S | T10: MHP5S | U10: MHP5SA | V10: MHP5SW | W10: MHP6S | X10: MHP6SA | Y10: MHP6SW | Z10: =LEFT(Z9,6) -> MHPC1J | AA10: =LEFT(AA9,6) -> MHPC1S | AB10: =LEFT(AB9,6) -> MHPC2J | AC10: =LEFT(AC9,6) -> MHPC2S | AD10: =LEFT(AD9,6) -> MHPC3S | AE10: =LEFT(AE9,6) -> MHPC4S | AF10: =LEFT(AF9,6) -> MHPC5S | AG10: =LEFT(AG9,6) -> MHPCSA | ... BU10: =LEFT(BU9,6) -> MHPDSW
A11: Class | B11: 1 | C11: 1 | D11: 1 | E11: 1 | F11: 1 | G11: 1 | H11: 1 | I11: 1 | J11: 1 | K11: 1 | L11: 1 | M11: 1 | N11: 1 | O11: 1 | P11: 1 | Q11: 1 | R11: 1 | S11: 1 | T11: 1 | U11: 1 | V11: 1 | W11: 1 | X11: 1 | Y11: 1 | Z11: 1 | AA11: 1 | AB11: 1 | AC11: 1 | AD11: 1 | AE11: 1 | AF11: 1 | AG11: 1 | AH11: 1 | AI11: 1 | AJ11: 1 | AK11: 1 | AL11: 1 | AM11: 1 | AN11: 1 | AO11: 1 | AP11: 1 | AQ11: 1 | AR11: 1 | AS11: 1 | AT11: 1 | AU11: 1 | AV11: 1 | AW11: 1 | AX11: 1 | AY11: 1 | AZ11: 1 | BA11: 1 | BB11: 1 | BC11: 1 | BD11: 1 | BE11: 1 | BF11: 1 | BG11: 1 | BH11: 1 | BI11: 1 | BJ11: 1 | BK11: 1 | BL11: 1 | BM11: 1 | BN11: 1 | BO11: 1 | BP11: 1 | BQ11: 1 | BR11: 1 | BS11: 1 | BT11: 1 | BU11: 1
A12: Gender | B12: F | C12: F | D12: F | E12: F | F12: F | G12: F | H12: F | I12: F | J12: F | K12: F | L12: F | M12: F | N12: M | O12: M | P12: M | Q12: M | R12: M | S12: M | T12: M | U12: M | V12: M | W12: M | X12: M | Y12: M | Z12: F | AA12: F | AB12: F | AC12: F | AD12: F | AE12: F | AF12: F | AG12: F | AH12: F | AI12: F | AJ12: F | AK12: F | AL12: M | AM12: M | AN12: M | AO12: M | AP12: M | AQ12: M | AR12: M | AS12: M | AT12: M | AU12: M | AV12: M | AW12: M | AX12: F | AY12: F | AZ12: F | BA12: F | BB12: F | BC12: F | BD12: F | BE12: F | BF12: F | BG12: F | BH12: F | BI12: F | BJ12: M | BK12: M | BL12: M | BM12: M | BN12: M | BO12: M | BP12: M | BQ12: M | BR12: M | BS12: M | BT12: M | BU12: M
A13: 0 | B13: 0 | C13: 0 | D13: 0 | E13: 0 | F13: 0 | G13: 0 | H13: 0 | I13: 0 | J13: 0 | K13: 0 | L13: 0 | M13: 0 | N13: 0 | O13: 0 | P13: 0 | Q13: 0 | R13: 0 | S13: 0 | T13: 0 | U13: 0 | V13: 0 | W13: 0 | X13: 0 | Y13: 0 | Z13: 0 | AA13: 0 | AB13: 0 | AC13: 0 | AD13: 0 | AE13: 0 | AF13: 0 | AG13: - | AH13: - | AI13: 0 | AJ13: - | AK13: - | AL13: 0 | AM13: 0 | AN13: 0 | AO13: 0 | AP13: 0 | AQ13: 0 | AR13: 0 | AS13: - | AT13: - | AU13: 0 | AV13: - | AW13: - | AX13: 0 | AY13: 0 | AZ13: 0 | BA13: 0 | BB13: 0 | BC13: 0 | BD13: 0 | BE13: - | BF13: - | BG13: 0 | BH13: - | BI13: - | BJ13: 0 | BK13: 0 | BL13: 0 | BM13: 0 | BN13: 0 | BO13: 0 | BP13: 0 | BQ13: - | BR13: - | BS13: 0 | BT13: - | BU13: -
A14: 1 | B14: 0 | C14: 0 | D14: 0 | E14: 0 | F14: 0 | G14: 0 | H14: 0 | I14: 0 | J14: 0 | K14: 0 | L14: 0 | M14: 0 | N14: 0 | O14: 0 | P14: 0 | Q14: 0 | R14: 0 | S14: 0 | T14: 0 | U14: 0 | V14: 0 | W14: 0 | X14: 0 | Y14: 0 | Z14: 0 | AA14: 0 | AB14: 0 | AC14: 0 | AD14: 0 | AE14: 0 | AF14: 0 | AG14: - | AH14: - | AI14: 0 | AJ14: - | AK14: - | AL14: 0 | AM14: 0 | AN14: 0 | AO14: 0 | AP14: 0 | AQ14: 0 | AR14: 0 | AS14: - | AT14: - | AU14: 0 | AV14: - | AW14: - | AX14: 0 | AY14: 0 | AZ14: 0 | BA14: 0 | BB14: 0 | BC14: 0 | BD14: 0 | BE14: - | BF14: - | BG14: 0 | BH14: - | BI14: - | BJ14: 0 | BK14: 0 | BL14: 0 | BM14: 0 | BN14: 0 | BO14: 0 | BP14: 0 | BQ14: - | BR14: - | BS14: 0 | BT14: - | BU14: -
A15: 2 | B15: 0 | C15: 0 | D15: 0 | E15: 0 | F15: 0 | G15: 0 | H15: 0 | I15: 0 | J15: 0 | K15: 0 | L15: 0 | M15: 0 | N15: 0 | O15: 0 | P15: 0 | Q15: 0 | R15: 0 | S15: 0 | T15: 0 | U15: 0 | V15: 0 | W15: 0 | X15: 0 | Y15: 0 | Z15: 0 | AA15: 0 | AB15: 0 | AC15: 0 | AD15: 0 | AE15: 0 | AF15: 0 | AG15: - | AH15: - | AI15: 0 | AJ15: - | AK15: - | AL15: 0 | AM15: 0 | AN15: 0 | AO15: 0 | AP15: 0 | AQ15: 0 | AR15: 0 | AS15: - | AT15: - | AU15: 0 | AV15: - | AW15: - | AX15: 0 | AY15: 0 | AZ15: 0 | BA15: 0 | BB15: 0 | BC15: 0 | BD15: 0 | BE15: - | BF15: - | BG15: 0 | BH15: - | BI15: - | BJ15: 0 | BK15: 0 | BL15: 0 | BM15: 0 | BN15: 0 | BO15: 0 | BP15: 0 | BQ15: - | BR15: - | BS15: 0 | BT15: - | BU15: -
A16: 3 | B16: 0 | C16: 0 | D16: 0 | E16: 0 | F16: 0 | G16: 0 | H16: 0 | I16: 0 | J16: 0 | K16: 0 | L16: 0 | M16: 0 | N16: 0 | O16: 0 | P16: 0 | Q16: 0 | R16: 0 | S16: 0 | T16: 0 | U16: 0 | V16: 0 | W16: 0 | X16: 0 | Y16: 0 | Z16: 0 | AA16: 0 | AB16: 0 | AC16: 0 | AD16: 0 | AE16: 0 | AF16: 0 | AG16: - | AH16: - | AI16: 0 | AJ16: - | AK16: - | AL16: 0 | AM16: 0 | AN16: 0 | AO16: 0 | AP16: 0 | AQ16: 0 | AR16: 0 | AS16: - | AT16: - | AU16: 0 | AV16: - | AW16: - | AX16: 0 | AY16: 0 | AZ16: 0 | BA16: 0 | BB16: 0 | BC16: 0 | BD16: 0 | BE16: - | BF16: - | BG16: 0 | BH16: - | BI16: - | BJ16: 0 | BK16: 0 | BL16: 0 | BM16: 0 | BN16: 0 | BO16: 0 | BP16: 0 | BQ16: - | BR16: - | BS16: 0 | BT16: - | BU16: -
A17: 4 | B17: 0 | C17: 0 | D17: 0 | E17: 0 | F17: 0 | G17: 0 | H17: 0 | I17: 0 | J17: 0 | K17: 0 | L17: 0 | M17: 0 | N17: 0 | O17: 0 | P17: 0 | Q17: 0 | R17: 0 | S17: 0 | T17: 0 | U17: 0 | V17: 0 | W17: 0 | X17: 0 | Y17: 0 | Z17: 0 | AA17: 0 | AB17: 0 | AC17: 0 | AD17: 0 | AE17: 0 | AF17: 0 | AG17: - | AH17: - | AI17: 0 | AJ17: - | AK17: - | AL17: 0 | AM17: 0 | AN17: 0 | AO17: 0 | AP17: 0 | AQ17: 0 | AR17: 0 | AS17: - | AT17: - | AU17: 0 | AV17: - | AW17: - | AX17: 0 | AY17: 0 | AZ17: 0 | BA17: 0 | BB17: 0 | BC17: 0 | BD17: 0 | BE17: - | BF17: - | BG17: 0 | BH17: - | BI17: - | BJ17: 0 | BK17: 0 | BL17: 0 | BM17: 0 | BN17: 0 | BO17: 0 | BP17: 0 | BQ17: - | BR17: - | BS17: 0 | BT17: - | BU17: -
A18: 5 | B18: 0 | C18: 0 | D18: 0 | E18: 0 | F18: 0 | G18: 0 | H18: 0 | I18: 0 | J18: 0 | K18: 0 | L18: 0 | M18: 0 | N18: 0 | O18: 0 | P18: 0 | Q18: 0 | R18: 0 | S18: 0 | T18: 0 | U18: 0 | V18: 0 | W18: 0 | X18: 0 | Y18: 0 | Z18: 0 | AA18: 0 | AB18: 0 | AC18: 0 | AD18: 0 | AE18: 0 | AF18: 0 | AG18: - | AH18: - | AI18: 0 | AJ18: - | AK18: - | AL18: 0 | AM18: 0 | AN18: 0 | AO18: 0 | AP18: 0 | AQ18: 0 | AR18: 0 | AS18: - | AT18: - | AU18: 0 | AV18: - | AW18: - | AX18: 0 | AY18: 0 | AZ18: 0 | BA18: 0 | BB18: 0 | BC18: 0 | BD18: 0 | BE18: - | BF18: - | BG18: 0 | BH18: - | BI18: - | BJ18: 0 | BK18: 0 | BL18: 0 | BM18: 0 | BN18: 0 | BO18: 0 | BP18: 0 | BQ18: - | BR18: - | BS18: 0 | BT18: - | BU18: -
A19: 6 | B19: 40100 | C19: 0 | D19: 47800 | E19: 0 | F19: 0 | G19: 0 | H19: 0 | I19: 0 | J19: 0 | K19: 0 | L19: 0 | M19: 0 | N19: 46700 | O19: 0 | P19: 55700 | Q19: 0 | R19: 0 | S19: 0 | T19: 0 | U19: 0 | V19: 0 | W19: 0 | X19: 0 | Y19: 0 | Z19: 32000 | AA19: 0 | AB19: 38200 | AC19: 0 | AD19: 0 | AE19: 0 | AF19: 0 | AG19: - | AH19: - | AI19: 0 | AJ19: - | AK19: - | AL19: 37300 | AM19: 0 | AN19: 44500 | AO19: 0 | AP19: 0 | AQ19: 0 | AR19: 0 | AS19: - | AT19: - | AU19: 0 | AV19: - | AW19: - | AX19: 29300 | AY19: 0 | AZ19: 35700 | BA19: 0 | BB19: 0 | BC19: 0 | BD19: 0 | BE19: - | BF19: - | BG19: 0 | BH19: - | BI19: - | BJ19: 34100 | BK19: 0 | BL19: 41600 | BM19: 0 | BN19: 0 | BO19: 0 | BP19: 0 | BQ19: - | BR19: - | BS19: 0 | BT19: - | BU19: -
A20: 7 | B20: 32800 | C20: 0 | D20: 39200 | E20: 0 | F20: 0 | G20: 0 | H20: 0 | I20: 0 | J20: 0 | K20: 0 | L20: 0 | M20: 0 | N20: 38300 | O20: 0 | P20: 45700 | Q20: 0 | R20: 0 | S20: 0 | T20: 0 | U20: 0 | V20: 0 | W20: 0 | X20: 0 | Y20: 0 | Z20: 26200 | AA20: 0 | AB20: 31300 | AC20: 0 | AD20: 0 | AE20: 0 | AF20: 0 | AG20: - | AH20: - | AI20: 0 | AJ20: - | AK20: - | AL20: 30600 | AM20: 0 | AN20: 36500 | AO20: 0 | AP20: 0 | AQ20: 0 | AR20: 0 | AS20: - | AT20: - | AU20: 0 | AV20: - | AW20: - | AX20: 24000 | AY20: 0 | AZ20: 29300 | BA20: 0 | BB20: 0 | BC20: 0 | BD20: 0 | BE20: - | BF20: - | BG20: 0 | BH20: - | BI20: - | BJ20: 28000 | BK20: 0 | BL20: 34100 | BM20: 0 | BN20: 0 | BO20: 0 | BP20: 0 | BQ20: - | BR20: - | BS20: 0 | BT20: - | BU20: -
A21: 8 | B21: 29400 | C21: 0 | D21: 35100 | E21: 0 | F21: 0 | G21: 0 | H21: 0 | I21: 0 | J21: 0 | K21: 0 | L21: 0 | M21: 0 | N21: 32300 | O21: 0 | P21: 38600 | Q21: 0 | R21: 0 | S21: 0 | T21: 0 | U21: 0 | V21: 0 | W21: 0 | X21: 0 | Y21: 0 | Z21: 23500 | AA21: 0 | AB21: 28000 | AC21: 0 | AD21: 0 | AE21: 0 | AF21: 0 | AG21: - | AH21: - | AI21: 0 | AJ21: - | AK21: - | AL21: 25800 | AM21: 0 | AN21: 30800 | AO21: 0 | AP21: 0 | AQ21: 0 | AR21: 0 | AS21: - | AT21: - | AU21: 0 | AV21: - | AW21: - | AX21: 21500 | AY21: 0 | AZ21: 26200 | BA21: 0 | BB21: 0 | BC21: 0 | BD21: 0 | BE21: - | BF21: - | BG21: 0 | BH21: - | BI21: - | BJ21: 23600 | BK21: 0 | BL21: 28800 | BM21: 0 | BN21: 0 | BO21: 0 | BP21: 0 | BQ21: - | BR21: - | BS21: 0 | BT21: - | BU21: -
A22: 9 | B22: 26000 | C22: 0 | D22: 31100 | E22: 0 | F22: 0 | G22: 0 | H22: 0 | I22: 0 | J22: 0 | K22: 0 | L22: 0 | M22: 0 | N22: 26400 | O22: 0 | P22: 31500 | Q22: 0 | R22: 0 | S22: 0 | T22: 0 | U22: 0 | V22: 0 | W22: 0 | X22: 0 | Y22: 0 | Z22: 20800 | AA22: 0 | AB22: 24800 | AC22: 0 | AD22: 0 | AE22: 0 | AF22: 0 | AG22: - | AH22: - | AI22: 0 | AJ22: - | AK22: - | AL22: 21100 | AM22: 0 | AN22: 25200 | AO22: 0 | AP22: 0 | AQ22: 0 | AR22: 0 | AS22: - | AT22: - | AU22: 0 | AV22: - | AW22: - | AX22: 19000 | AY22: 0 | AZ22: 23200 | BA22: 0 | BB22: 0 | BC22: 0 | BD22: 0 | BE22: - | BF22: - | BG22: 0 | BH22: - | BI22: - | BJ22: 19300 | BK22: 0 | BL22: 23600 | BM22: 0 | BN22: 0 | BO22: 0 | BP22: 0 | BQ22: - | BR22: - | BS22: 0 | BT22: - | BU22: -
A23: 10 | B23: 23400 | C23: 0 | D23: 28000 | E23: 0 | F23: 0 | G23: 0 | H23: 0 | I23: 0 | J23: 0 | K23: 0 | L23: 0 | M23: 0 | N23: 23900 | O23: 0 | P23: 28500 | Q23: 0 | R23: 0 | S23: 0 | T23: 0 | U23: 0 | V23: 0 | W23: 0 | X23: 0 | Y23: 0 | Z23: 18700 | AA23: 0 | AB23: 22400 | AC23: 0 | AD23: 0 | AE23: 0 | AF23: 0 | AG23: - | AH23: - | AI23: 0 | AJ23: - | AK23: - | AL23: 19100 | AM23: 0 | AN23: 22800 | AO23: 0 | AP23: 0 | AQ23: 0 | AR23: 0 | AS23: - | AT23: - | AU23: 0 | AV23: - | AW23: - | AX23: 17200 | AY23: 0 | AZ23: 20900 | BA23: 0 | BB23: 0 | BC23: 0 | BD23: 0 | BE23: - | BF23: - | BG23: 0 | BH23: - | BI23: - | BJ23: 17500 | BK23: 0 | BL23: 21300 | BM23: 0 | BN23: 0 | BO23: 0 | BP23: 0 | BQ23: - | BR23: - | BS23: 0 | BT23: - | BU23: -
A24: 11 | B24: 23200 | C24: 23200 | D24: 27600 | E24: 27600 | F24: 39900 | G24: 51300 | H24: 85500 | I24: 152300 | J24: 295600 | K24: 134000 | L24: 222300 | M24: 443000 | N24: 23700 | O24: 23700 | P24: 28300 | Q24: 28300 | R24: 41800 | S24: 53900 | T24: 87800 | U24: 156400 | V24: 303500 | W24: 148300 | X24: 246000 | Y24: 490200 | Z24: 18500 | AA24: 18500 | AB24: 22000 | AC24: 22000 | AD24: 31900 | AE24: 41000 | AF24: 68400 | AG24: - | AH24: - | AI24: 107200 | AJ24: - | AK24: - | AL24: 18900 | AM24: 18900 | AN24: 22600 | AO24: 22600 | AP24: 33400 | AQ24: 43100 | AR24: 70200 | AS24: - | AT24: - | AU24: 118600 | AV24: - | AW24: - | AX24: 17000 | AY24: 17000 | AZ24: 20700 | BA24: 20700 | BB24: 28700 | BC24: 37100 | BD24: 69900 | BE24: - | BF24: - | BG24: 105700 | BH24: - | BI24: - | BJ24: 17400 | BK24: 17400 | BL24: 21200 | BM24: 21200 | BN24: 30300 | BO24: 39400 | BP24: 73000 | BQ24: - | BR24: - | BS24: 120400 | BT24: - | BU24: -
... A102: 89 | B102: 204100 | C102: 204100 | D102: 242600 | E102: 242600 | F102: 325100 | G102: 412900 | H102: 557700 | I102: 993200 | J102: 1926900 | K102: 815800 | L102: 1353500 | M102: 2696700 | N102: 244300 | O102: 244300 | P102: 290400 | Q102: 290400 | R102: 387600 | S102: 491800 | T102: 620700 | U102: 1105400 | V102: 2144600 | W102: 804800 | X102: 1335200 | Y102: 2660400 | Z102: 163200 | AA102: 163200 | AB102: 194000 | AC102: 194000 | AD102: 260000 | AE102: 330300 | AF102: 446100 | AG102: - | AH102: - | AI102: 652600 | AJ102: - | AK102: - | AL102: 195400 | AM102: 195400 | AN102: 232300 | AO102: 232300 | AP102: 310000 | AQ102: 393400 | AR102: 496500 | AS102: - | AT102: - | AU102: 643800 | AV102: - | AW102: - | AX102: 174500 | AY102: 174500 | AZ102: 207600 | BA102: 207600 | BB102: 249800 | BC102: 308400 | BD102: 422800 | BE102: - | BF102: - | BG102: 555500 | BH102: - | BI102: - | BJ102: 208500 | BK102: 208500 | BL102: 247500 | BM102: 247500 | BN102: 295600 | BO102: 362900 | BP102: 455000 | BQ102: - | BR102: - | BS102: 518700 | BT102: - | BU102: -
A103: 90 | B103: 214600 | C103: 214600 | D103: 253800 | E103: 253800 | F103: 337600 | G103: 426900 | H103: 574900 | I103: - | J103: - | K103: 834600 | L103: - | M103: - | N103: 252300 | O103: 252300 | P103: 298200 | Q103: 298200 | R103: 394900 | S103: 498500 | T103: 627200 | U103: - | V103: - | W103: 811100 | X103: - | Y103: - | Z103: 171600 | AA103: 171600 | AB103: 203000 | AC103: 203000 | AD103: 270000 | AE103: 341500 | AF103: 459900 | AG103: - | AH103: - | AI103: 667600 | AJ103: - | AK103: - | AL103: 201800 | AM103: 201800 | AN103: 238500 | AO103: 238500 | AP103: 315900 | AQ103: 398800 | AR103: 501700 | AS103: - | AT103: - | AU103: 648800 | AV103: - | AW103: - | AX103: 178800 | AY103: 178800 | AZ103: 212900 | BA103: 212900 | BB103: 256100 | BC103: 316400 | BD103: 433600 | BE103: - | BF103: - | BG103: 565600 | BH103: - | BI103: - | BJ103: 211500 | BK103: 211500 | BL103: 251200 | BM103: 251200 | BN103: 300000 | BO103: 368500 | BP103: 461400 | BQ103: - | BR103: - | BS103: 524900 | BT103: - | BU103: -
A104: 91 | B104: 225200 | C104: 225200 | D104: 265000 | E104: 265000 | F104: 350200 | G104: 440900 | H104: 592100 | I104: - | J104: - | K104: 853300 | L104: - | M104: - | N104: 260300 | O104: 260300 | P104: 305900 | Q104: 305900 | R104: 402200 | S104: 505300 | T104: 633600 | U104: - | V104: - | W104: 817500 | X104: - | Y104: - | Z104: 180100 | AA104: 180100 | AB104: 212000 | AC104: 212000 | AD104: 280100 | AE104: 352700 | AF104: 473600 | AG104: - | AH104: - | AI104: 682600 | AJ104: - | AK104: - | AL104: 208200 | AM104: 208200 | AN104: 244700 | AO104: 244700 | AP104: 321700 | AQ104: 404200 | AR104: 506800 | AS104: - | AT104: - | AU104: 654000 | AV104: - | AW104: - | AX104: 183100 | AY104: 183100 | AZ104: 218100 | BA104: 218100 | BB104: 262400 | BC104: 324400 | BD104: 444300 | BE104: - | BF104: - | BG104: 575800 | BH104: - | BI104: - | BJ104: 214600 | BK104: 214600 | BL104: 254900 | BM104: 254900 | BN104: 304500 | BO104: 374200 | BP104: 467900 | BQ104: - | BR104: - | BS104: 531100 | BT104: - | BU104: -
A105: 92 | B105: 235900 | C105: 235900 | D105: 276900 | E105: 276900 | F105: 364300 | G105: 457500 | H105: 612800 | I105: - | J105: - | K105: 876400 | L105: - | M105: - | N105: 270900 | O105: 270900 | P105: 317300 | Q105: 317300 | R105: 415100 | S105: 519900 | T105: 650100 | U105: - | V105: - | W105: 835800 | X105: - | Y105: - | Z105: 188700 | AA105: 188700 | AB105: 221500 | AC105: 221500 | AD105: 291400 | AE105: 366000 | AF105: 490200 | AG105: - | AH105: - | AI105: 701100 | AJ105: - | AK105: - | AL105: 216700 | AM105: 216700 | AN105: 253800 | AO105: 253800 | AP105: 332000 | AQ105: 415900 | AR105: 520000 | AS105: - | AT105: - | AU105: 668600 | AV105: - | AW105: - | AX105: 187400 | AY105: 187400 | AZ105: 223400 | BA105: 223400 | BB105: 268800 | BC105: 332400 | BD105: 455100 | BE105: - | BF105: - | BG105: 586000 | BH105: - | BI105: - | BJ105: 217600 | BK105: 217600 | BL105: 258600 | BM105: 258600 | BN105: 309000 | BO105: 379800 | BP105: 474300 | BQ105: - | BR105: - | BS105: 537300 | BT105: - | BU105: -
A106: 93 | B106: 246600 | C106: 246600 | D106: 288800 | E106: 288800 | F106: 378400 | G106: 474100 | H106: 633600 | I106: - | J106: - | K106: 899500 | L106: - | M106: - | N106: 281500 | O106: 281500 | P106: 328700 | Q106: 328700 | R106: 428000 | S106: 534600 | T106: 666600 | U106: - | V106: - | W106: 854000 | X106: - | Y106: - | Z106: 197200 | AA106: 197200 | AB106: 231000 | AC106: 231000 | AD106: 302700 | AE106: 379200 | AF106: 506800 | AG106: - | AH106: - | AI106: 719600 | AJ106: - | AK106: - | AL106: 225200 | AM106: 225200 | AN106: 262900 | AO106: 262900 | AP106: 342400 | AQ106: 427600 | AR106: 533200 | AS106: - | AT106: - | AU106: 683200 | AV106: - | AW106: - | AX106: 191700 | AY106: 191700 | AZ106: 228600 | BA106: 228600 | BB106: 275100 | BC106: 340300 | BD106: 465800 | BE106: - | BF106: - | BG106: 596200 | BH106: - | BI106: - | BJ106: 220600 | BK106: 220600 | BL106: 262300 | BM106: 262300 | BN106: 313400 | BO106: 385400 | BP106: 480800 | BQ106: - | BR106: - | BS106: 543600 | BT106: - | BU106: -
A107: 94 | B107: 254400 | C107: 254400 | D107: 298000 | E107: 298000 | F107: 390500 | G107: 489400 | H107: 654500 | I107: - | J107: - | K107: 923300 | L107: - | M107: - | N107: 287200 | O107: 287200 | P107: 335600 | Q107: 335600 | R107: 437100 | S107: 546200 | T107: 680400 | U107: - | V107: - | W107: 870000 | X107: - | Y107: - | Z107: 203500 | AA107: 203500 | AB107: 238400 | AC107: 238400 | AD107: 312400 | AE107: 391500 | AF107: 523600 | AG107: - | AH107: - | AI107: 738600 | AJ107: - | AK107: - | AL107: 229700 | AM107: 229700 | AN107: 268400 | AO107: 268400 | AP107: 349600 | AQ107: 436900 | AR107: 544300 | AS107: - | AT107: - | AU107: 696000 | AV107: - | AW107: - | AX107: 197300 | AY107: 197300 | AZ107: 235500 | BA107: 235500 | BB107: 283300 | BC107: 350800 | BD107: 480200 | BE107: - | BF107: - | BG107: 609700 | BH107: - | BI107: - | BJ107: 224800 | BK107: 224800 | BL107: 267500 | BM107: 267500 | BN107: 319600 | BO107: 393300 | BP107: 489800 | BQ107: - | BR107: - | BS107: 552200 | BT107: - | BU107: -
A108: 95 | B108: 262100 | C108: 262100 | D108: 307200 | E108: 307200 | F108: 402600 | G108: 504800 | H108: 675400 | I108: - | J108: - | K108: 947100 | L108: - | M108: - | N108: 293000 | O108: 293000 | P108: 342500 | Q108: 342500 | R108: 446200 | S108: 557700 | T108: 694200 | U108: - | V108: - | W108: 885900 | X108: - | Y108: - | Z108: 209600 | AA108: 209600 | AB108: 245700 | AC108: 245700 | AD108: 322000 | AE108: 403800 | AF108: 540300 | AG108: - | AH108: - | AI108: 757600 | AJ108: - | AK108: - | AL108: 234400 | AM108: 234400 | AN108: 274000 | AO108: 274000 | AP108: 356900 | AQ108: 446100 | AR108: 555300 | AS108: - | AT108: - | AU108: 708700 | AV108: - | AW108: - | AX108: 202900 | AY108: 202900 | AZ108: 242400 | BA108: 242400 | BB108: 291600 | BC108: 361200 | BD108: 494500 | BE108: - | BF108: - | BG108: 623300 | BH108: - | BI108: - | BJ108: 229100 | BK108: 229100 | BL108: 272600 | BM108: 272600 | BN108: 325800 | BO108: 401100 | BP108: 498700 | BQ108: - | BR108: - | BS108: 560900 | BT108: - | BU108: -
A109: 96 | B109: 269800 | C109: 269800 | D109: 316400 | E109: 316400 | F109: 414700 | G109: 520200 | H109: 696300 | I109: - | J109: - | K109: 970900 | L109: - | M109: - | N109: 298800 | O109: 298800 | P109: 349400 | Q109: 349400 | R109: 455300 | S109: 569200 | T109: 708000 | U109: - | V109: - | W109: 901800 | X109: - | Y109: - | Z109: 215800 | AA109: 215800 | AB109: 253100 | AC109: 253100 | AD109: 331700 | AE109: 416100 | AF109: 557000 | AG109: - | AH109: - | AI109: 776700 | AJ109: - | AK109: - | AL109: 239000 | AM109: 239000 | AN109: 279500 | AO109: 279500 | AP109: 364200 | AQ109: 455300 | AR109: 566400 | AS109: - | AT109: - | AU109: 721400 | AV109: - | AW109: - | AX109: 208600 | AY109: 208600 | AZ109: 249200 | BA109: 249200 | BB109: 299800 | BC109: 371700 | BD109: 508900 | BE109: - | BF109: - | BG109: 636900 | BH109: - | BI109: - | BJ109: 233300 | BK109: 233300 | BL109: 277800 | BM109: 277800 | BN109: 332000 | BO109: 408900 | BP109: 507700 | BQ109: - | BR109: - | BS109: 569500 | BT109: - | BU109: -
A110: 97 | B110: 277500 | C110: 277500 | D110: 325600 | E110: 325600 | F110: 426800 | G110: 535500 | H110: 717200 | I110: - | J110: - | K110: 994600 | L110: - | M110: - | N110: 304600 | O110: 304600 | P110: 356300 | Q110: 356300 | R110: 464400 | S110: 580700 | T110: 721700 | U110: - | V110: - | W110: 917700 | X110: - | Y110: - | Z110: 222000 | AA110: 222000 | AB110: 260400 | AC110: 260400 | AD110: 341400 | AE110: 428400 | AF110: 573700 | AG110: - | AH110: - | AI110: 795600 | AJ110: - | AK110: - | AL110: 243600 | AM110: 243600 | AN110: 285000 | AO110: 285000 | AP110: 371500 | AQ110: 464500 | AR110: 577300 | AS110: - | AT110: - | AU110: 734100 | AV110: - | AW110: - | AX110: 214200 | AY110: 214200 | AZ110: 256100 | BA110: 256100 | BB110: 308100 | BC110: 382100 | BD110: 523200 | BE110: - | BF110: - | BG110: 650500 | BH110: - | BI110: - | BJ110: 237500 | BK110: 237500 | BL110: 282900 | BM110: 282900 | BN110: 338200 | BO110: 416800 | BP110: 516700 | BQ110: - | BR110: - | BS110: 578200 | BT110: - | BU110: -
A111: 98 | B111: 285200 | C111: 285200 | D111: 334900 | E111: 334900 | F111: 439000 | G111: 550900 | H111: 738100 | I111: - | J111: - | K111: 1018400 | L111: - | M111: - | N111: 310400 | O111: 310400 | P111: 363200 | Q111: 363200 | R111: 473500 | S111: 592300 | T111: 735500 | U111: - | V111: - | W111: 933700 | X111: - | Y111: - | Z111: 228100 | AA111: 228100 | AB111: 267900 | AC111: 267900 | AD111: 351200 | AE111: 440700 | AF111: 590400 | AG111: - | AH111: - | AI111: 814700 | AJ111: - | AK111: - | AL111: 248300 | AM111: 248300 | AN111: 290500 | AO111: 290500 | AP111: 378800 | AQ111: 473800 | AR111: 588400 | AS111: - | AT111: - | AU111: 746900 | AV111: - | AW111: - | AX111: 219800 | AY111: 219800 | AZ111: 263000 | BA111: 263000 | BB111: 316300 | BC111: 392500 | BD111: 537600 | BE111: - | BF111: - | BG111: 664000 | BH111: - | BI111: - | BJ111: 241700 | BK111: 241700 | BL111: 288100 | BM111: 288100 | BN111: 344400 | BO111: 424600 | BP111: 525600 | BQ111: - | BR111: - | BS111: 586900 | BT111: - | BU111: -

Sheet Login
E2: LOGIN
K3: di6'wmp
D4: Username : | F4: =IF(E4="","",IF(#REF!=0,"คุณใส่ User Name ไม่ถูกต้อง",""))
D5: Password : | F5: =IF(E4="","",IF(F4<>"","กรุณาใส่ User Name ให้ถูกต้อง",IF(E5="","กรุณาใส่ Password",IF(#REF!="NO","คุณใส่ Password ไม่ถูกต้อง",""))))
E6: =IF(E10="Login Complete","","กรุณากรอก Username / Password เพื่อเริ่มใช้งาน") -> #REF!
D8: Broker Name : | E8: =IF(AND(F4="",F5=""),VLOOKUP($E4,#REF!,2,FALSE),"N/A") -> #REF!
D9: Password
D10: Check password | E10: =IF(#REF!="YES","Login Complete","") -> #REF!

Sheet Data support
A1: Product Name | B1: WPTPD | C1: WPTPDCI
A2: Official Product Name TH : | B2: สัญญาเพิ่มเติมผลประโยชน์ยกเว้นเบี้ยประกันภัยสัญญาหลัก (คุ้มครองการทุพพลภาพถาวรสิ้นเชิง) | C2: สัญญาเพิ่มเติมผลประโยชน์ยกเว้นเบี้ยประกันภัยสัญญาหลัก (คุ้มครองการทุพพลภาพถาวรสิ้นเชิงและโรคร้ายแรง)
A3: Official Product Name EN : | B3: Waiver of Basic Premium Rider (Cover for Total and permanent disability) | C3: Waiver of Basic Premium Rider (Cover for Total and permanent disability and Critical Illness) | E3: 1.1.1 Plan Code:
A4: Marketing name TH : | B4: N/A | C4: N/A
A5: Marketing name EN : | B5: N/A | C5: N/A | E5: WP Plancode:
A6: Product Type : | B6: Rider | C6: Rider
A7: Par / Non-Par | B7: Non-Par | C7: Non-Par
A8: Product Code : | B8: WPTPD (TBC) | C8: WPTPDCI (TBC) | E8: Product WP | F8: Plan code | G8: System Plan Code
A9: Product Category | B9: Protection | C9: Protection | E9: Waiver of Premium Rider (Total Permanent Disability) | F9: WPTPD | G9: WPTPDxx
A10: Policy term / | B10: Minimum of | C10: Minimum of | E10: Waiver of Premium Rider (Total Permanent Disability and Critical Illness) | F10: WPTPDCI | G10: WPTCIxx
A11: Coverage period: | B11: · PPP(4) of basic plan | C11: · PPP(4) of basic plan
B12: · 80 – issued age | C12: · 80 – issued age | E12: System plan code will be align with the waive periods and premium rate provide in Appendix 2
A13: Premium payment term: | B13: Minimum of | C13: Minimum of | E13: Example plancode:
B14: · PPP(4) of basic plan | C14: · PPP(4) of basic plan | E14: WPTPD02, WPTPD03, … , WPTPD25, WPTPD55, WPTPD60, WPTPD85, WPTPD99
B15: · 80 – issued age | C15: · 80 – issued age | E15: WPTCI02, WPTCI03, … , WPTCI25, WPTCI55, WPTCI60, WPTCI85, WPTCI99
A16: Period to waive premium | B16: Until end of PPP of basic plan | C16: Until end of PPP of basic plan
A17: Type of product development: | B17: Restyling Product | C17: Restyling Product
A18: (New product / Restyling / Repricing)
A31: Product Specification for PB Rider (PBFP, PBBP, PBFS, PBBS)
B53: Period to waive premium | C53: Until end of PPP of basic plan | D53: WP เอาใช้ดุระยะเวลา waive เบี้ย

Sheet Rate CI 123
A1: RLPLAN | B1: Plancode | C1: RLOCLS | D1: RLCLS | E1: RLSEX | F1: KEY | G1: RLL00 | H1: RLL01 | I1: RLL02 | J1: RLL03 | K1: RLL04 | L1: RLL05 | M1: RLL06 | N1: RLL07 | O1: RLL08 | P1: RLL09 | Q1: RLL10 | R1: RLL11 | S1: RLL12 | T1: RLL13 | U1: RLL14 | V1: RLL15 | W1: RLL16 | X1: RLL17 | Y1: RLL18 | Z1: RLL19 | AA1: RLL20 | AB1: RLL21 | AC1: RLL22 | AD1: RLL23 | AE1: RLL24 | AF1: RLL25 | AG1: RLL26 | AH1: RLL27 | AI1: RLL28 | AJ1: RLL29 | AK1: RLL30 | AL1: RLL31 | AM1: RLL32 | AN1: RLL33 | AO1: RLL34 | AP1: RLL35 | AQ1: RLL36 | AR1: RLL37 | AS1: RLL38 | AT1: RLL39 | AU1: RLL40 | AV1: RLL41 | AW1: RLL42 | AX1: RLL43 | AY1: RLL44 | AZ1: RLL45 | BA1: RLL46 | BB1: RLL47 | BC1: RLL48 | BD1: RLL49 | BE1: RLL50 | BF1: RLL51 | BG1: RLL52 | BH1: RLL53 | BI1: RLL54 | BJ1: RLL55 | BK1: RLL56 | BL1: RLL57 | BM1: RLL58 | BN1: RLL59 | BO1: RLL60 | BP1: RLL61 | BQ1: RLL62 | BR1: RLL63 | BS1: RLL64 | BT1: RLL65 | BU1: RLL66 | BV1: RLL67 | BW1: RLL68 | BX1: RLL69 | BY1: RLL70 | BZ1: RLL71 | CA1: RLL72 | CB1: RLL73 | CC1: RLL74 | CD1: RLL75 | CE1: RLL76 | CF1: RLL77 | CG1: RLL78 | CH1: RLL79 | CI1: RLL80 | CJ1: RLL81 | CK1: RLL82 | CL1: RLL83 | CM1: RLL84 | CN1: RLL85 | CO1: RLL86 | CP1: RLL87 | CQ1: RLL88 | CR1: RLL89 | CS1: RLL90 | CT1: RLL91 | CU1: RLL92 | CV1: RLL93 | CW1: RLL94 | CX1: RLL95 | CY1: RLL96 | CZ1: RLL97 | DA1: RLL98 | DB1: RLL99 | DC1: RLW00 | DD1: RLW01 | DE1: RLW02 | DF1: RLW03 | DG1: RLW04 | DH1: RLW05 | DI1: RLW06 | DJ1: RLW07 | DK1: RLW08 | DL1: RLW09 | DM1: RLW10 | DN1: RLW11 | DO1: RLW12 | DP1: RLW13 | DQ1: RLW14 | DR1: RLW15 | DS1: RLW16 | DT1: RLW17 | DU1: RLW18 | DV1: RLW19 | DW1: RLW20 | DX1: RLW21 | DY1: RLW22 | DZ1: RLW23 | EA1: RLW24 | EB1: RLW25 | EC1: RLW26 | ED1: RLW27 | EE1: RLW28 | EF1: RLW29 | EG1: RLW30 | EH1: RLW31 | EI1: RLW32 | EJ1: RLW33 | EK1: RLW34 | EL1: RLW35 | EM1: RLW36 | EN1: RLW37 | EO1: RLW38 | EP1: RLW39 | EQ1: RLW40 | ER1: RLW41 | ES1: RLW42 | ET1: RLW43 | EU1: RLW44 | EV1: RLW45 | EW1: RLW46 | EX1: RLW47 | EY1: RLW48 | EZ1: RLW49 | FA1: RLW50 | FB1: RLW51 | FC1: RLW52 | FD1: RLW53 | FE1: RLW54 | FF1: RLW55 | FG1: RLW56 | FH1: RLW57 | FI1: RLW58 | FJ1: RLW59 | FK1: RLW60 | FL1: RLW61 | FM1: RLW62 | FN1: RLW63 | FO1: RLW64 | FP1: RLW65 | FQ1: RLW66 | FR1: RLW67 | FS1: RLW68 | FT1: RLW69 | FU1: RLW70 | FV1: RLW71 | FW1: RLW72 | FX1: RLW73 | FY1: RLW74 | FZ1: RLW75 | GA1: RLW76 | GB1: RLW77 | GC1: RLW78 | GD1: RLW79 | GE1: RLW80 | GF1: RLW81 | GG1: RLW82 | GH1: RLW83 | GI1: RLW84 | GJ1: RLW85 | GK1: RLW86 | GL1: RLW87 | GM1: RLW88 | GN1: RLW89 | GO1: RLW90 | GP1: RLW91 | GQ1: RLW92 | GR1: RLW93 | GS1: RLW94 | GT1: RLW95 | GU1: RLW96 | GV1: RLW97 | GW1: RLW98 | GX1: RLW99
A2: Major CI | B2: CIES3 | D2: 1 | E2: F | F2: =A2&"-"&E2 -> Major CI-F | G2: 1.41 | H2: 1.38 | I2: 1.37 | J2: 1.35 | K2: 1.34 | L2: 1.32 | M2: 1.3 | N2: 1.28 | O2: 1.26 | P2: 1.29 | Q2: 1.41 | R2: 1.61 | S2: 1.77 | T2: 1.65 | U2: 1.53 | V2: 1.43 | W2: 1.4 | X2: 1.37 | Y2: 1.4 | Z2: 1.43 | AA2: 1.6 | AB2: 1.69 | AC2: 1.78 | AD2: 1.88 | AE2: 1.97 | AF2: 1.97 | AG2: 2 | AH2: 2.1 | AI2: 2.48 | AJ2: 2.53 | AK2: 2.55 | AL2: 2.58 | AM2: 2.61 | AN2: 3.03 | AO2: 3.51 | AP2: 3.2 | AQ2: 3.62 | AR2: 4.07 | AS2: 4.55 | AT2: 5.05 | AU2: 5.02 | AV2: 5.64 | AW2: 6.32 | AX2: 7.04 | AY2: 7.17 | AZ2: 7.58 | BA2: 8.22 | BB2: 8.93 | BC2: 9.71 | BD2: 10.01 | BE2: 10.62 | BF2: 12.62 | BG2: 13.25 | BH2: 14.31 | BI2: 15.45 | BJ2: 17.66 | BK2: 20.52 | BL2: 22.64 | BM2: 24.47 | BN2: 25.2 | BO2: 25.93 | BP2: 26.66 | BQ2: 27.39 | BR2: 29.42 | BS2: 31.77 | BT2: 32.5 | BU2: 34.74 | BV2: 37.21 | BW2: 39.33 | BX2: 41.68 | BY2: 41.93 | BZ2: 44.4 | CA2: 47.05 | CB2: 50.1 | CC2: 53.39 | CD2: 62.25 | CE2: 67.27 | CF2: 72.97 | CG2: 78.6 | CH2: 84.76 | CI2: 91.49 | CJ2: 98.86 | CK2: 106.92 | CL2: 115.26 | CM2: 124.32 | CN2: 134.21 | CO2: 143.89 | CP2: 155.29 | CQ2: 168.13 | CR2: 182.29 | CS2: 197.93 | CT2: 214.28 | CU2: 232.53 | CV2: 252.34 | CW2: 273.69 | CX2: 297.04 | CY2: 322.46 | CZ2: 350.07 | DA2: 552.62 | DB2: 0
A3: Major CI | B3: CIES3 | D3: 1 | E3: M | F3: =A3&"-"&E3 -> Major CI-M | G3: 1.77 | H3: 1.71 | I3: 1.69 | J3: 1.67 | K3: 1.64 | L3: 1.6 | M3: 1.6 | N3: 1.58 | O3: 1.56 | P3: 1.54 | Q3: 1.47 | R3: 1.46 | S3: 1.44 | T3: 1.42 | U3: 1.4 | V3: 1.39 | W3: 1.37 | X3: 1.35 | Y3: 1.33 | Z3: 1.34 | AA3: 1.39 | AB3: 1.42 | AC3: 1.44 | AD3: 1.47 | AE3: 1.5 | AF3: 1.51 | AG3: 1.51 | AH3: 1.61 | AI3: 1.66 | AJ3: 1.7 | AK3: 1.89 | AL3: 1.92 | AM3: 2.16 | AN3: 2.44 | AO3: 2.75 | AP3: 3.34 | AQ3: 3.75 | AR3: 4.18 | AS3: 4.76 | AT3: 5.42 | AU3: 5.29 | AV3: 5.29 | AW3: 5.98 | AX3: 6.74 | AY3: 7.58 | AZ3: 9.21 | BA3: 10.14 | BB3: 11.25 | BC3: 12.43 | BD3: 13.72 | BE3: 15.01 | BF3: 15.01 | BG3: 16.62 | BH3: 18.42 | BI3: 20.38 | BJ3: 21.13 | BK3: 23.02 | BL3: 25.11 | BM3: 27.41 | BN3: 30.03 | BO3: 34.45 | BP3: 37.75 | BQ3: 41.01 | BR3: 44.55 | BS3: 47.08 | BT3: 49.62 | BU3: 52.16 | BV3: 54.69 | BW3: 59.18 | BX3: 61.87 | BY3: 64.57 | BZ3: 67.27 | CA3: 69.97 | CB3: 75.18 | CC3: 80.85 | CD3: 85.7 | CE3: 92.11 | CF3: 99.33 | CG3: 104.67 | CH3: 110.5 | CI3: 116.82 | CJ3: 123.68 | CK3: 131.06 | CL3: 137.73 | CM3: 144.9 | CN3: 153.46 | CO3: 161.58 | CP3: 170.94 | CQ3: 182.08 | CR3: 194.3 | CS3: 207.69 | CT3: 221.95 | CU3: 237.64 | CV3: 254.4 | CW3: 272.16 | CX3: 291.36 | CY3: 311.94 | CZ3: 334.09 | DA3: 503.75 | DB3: 0
A4: Major CI | B4: CIES4 | D4: 1 | E4: F | F4: =A4&"-"&E4 -> Major CI-F | G4: 1.41 | H4: 1.38 | I4: 1.37 | J4: 1.35 | K4: 1.34 | L4: 1.32 | M4: 1.3 | N4: 1.28 | O4: 1.26 | P4: 1.29 | Q4: 1.41 | R4: 1.61 | S4: 1.77 | T4: 1.65 | U4: 1.53 | V4: 1.43 | W4: 1.4 | X4: 1.37 | Y4: 1.4 | Z4: 1.43 | AA4: 1.6 | AB4: 1.69 | AC4: 1.78 | AD4: 1.88 | AE4: 1.97 | AF4: 1.97 | AG4: 2 | AH4: 2.1 | AI4: 2.48 | AJ4: 2.53 | AK4: 2.55 | AL4: 2.58 | AM4: 2.61 | AN4: 3.03 | AO4: 3.51 | AP4: 3.2 | AQ4: 3.62 | AR4: 4.07 | AS4: 4.55 | AT4: 5.05 | AU4: 5.02 | AV4: 5.64 | AW4: 6.32 | AX4: 7.04 | AY4: 7.17 | AZ4: 7.58 | BA4: 8.22 | BB4: 8.93 | BC4: 9.71 | BD4: 10.01 | BE4: 10.62 | BF4: 12.62 | BG4: 13.25 | BH4: 14.31 | BI4: 15.45 | BJ4: 17.66 | BK4: 20.52 | BL4: 22.64 | BM4: 24.47 | BN4: 25.2 | BO4: 25.93 | BP4: 26.66 | BQ4: 27.39 | BR4: 29.42 | BS4: 31.77 | BT4: 32.5 | BU4: 34.74 | BV4: 37.21 | BW4: 39.33 | BX4: 41.68 | BY4: 41.93 | BZ4: 44.4 | CA4: 47.05 | CB4: 50.1 | CC4: 53.39 | CD4: 62.25 | CE4: 67.27 | CF4: 72.97 | CG4: 78.6 | CH4: 84.76 | CI4: 91.49 | CJ4: 98.86 | CK4: 106.92 | CL4: 115.26 | CM4: 124.32 | CN4: 134.21 | CO4: 143.89 | CP4: 155.29 | CQ4: 168.13 | CR4: 182.29 | CS4: 197.93 | CT4: 214.28 | CU4: 232.53 | CV4: 252.34 | CW4: 273.69 | CX4: 297.04 | CY4: 322.46 | CZ4: 350.07 | DA4: 552.62 | DB4: 0
A5: Major CI | B5: CIES4 | D5: 1 | E5: M | F5: =A5&"-"&E5 -> Major CI-M | G5: 1.77 | H5: 1.71 | I5: 1.69 | J5: 1.67 | K5: 1.64 | L5: 1.6 | M5: 1.6 | N5: 1.58 | O5: 1.56 | P5: 1.54 | Q5: 1.47 | R5: 1.46 | S5: 1.44 | T5: 1.42 | U5: 1.4 | V5: 1.39 | W5: 1.37 | X5: 1.35 | Y5: 1.33 | Z5: 1.34 | AA5: 1.39 | AB5: 1.42 | AC5: 1.44 | AD5: 1.47 | AE5: 1.5 | AF5: 1.51 | AG5: 1.51 | AH5: 1.61 | AI5: 1.66 | AJ5: 1.7 | AK5: 1.89 | AL5: 1.92 | AM5: 2.16 | AN5: 2.44 | AO5: 2.75 | AP5: 3.34 | AQ5: 3.75 | AR5: 4.18 | AS5: 4.76 | AT5: 5.42 | AU5: 5.29 | AV5: 5.29 | AW5: 5.98 | AX5: 6.74 | AY5: 7.58 | AZ5: 9.21 | BA5: 10.14 | BB5: 11.25 | BC5: 12.43 | BD5: 13.72 | BE5: 15.01 | BF5: 15.01 | BG5: 16.62 | BH5: 18.42 | BI5: 20.38 | BJ5: 21.13 | BK5: 23.02 | BL5: 25.11 | BM5: 27.41 | BN5: 30.03 | BO5: 34.45 | BP5: 37.75 | BQ5: 41.01 | BR5: 44.55 | BS5: 47.08 | BT5: 49.62 | BU5: 52.16 | BV5: 54.69 | BW5: 59.18 | BX5: 61.87 | BY5: 64.57 | BZ5: 67.27 | CA5: 69.97 | CB5: 75.18 | CC5: 80.85 | CD5: 85.7 | CE5: 92.11 | CF5: 99.33 | CG5: 104.67 | CH5: 110.5 | CI5: 116.82 | CJ5: 123.68 | CK5: 131.06 | CL5: 137.73 | CM5: 144.9 | CN5: 153.46 | CO5: 161.58 | CP5: 170.94 | CQ5: 182.08 | CR5: 194.3 | CS5: 207.69 | CT5: 221.95 | CU5: 237.64 | CV5: 254.4 | CW5: 272.16 | CX5: 291.36 | CY5: 311.94 | CZ5: 334.09 | DA5: 503.75 | DB5: 0
A6: Critical Care Benefit | B6: CIESCB | D6: 1 | E6: F | F6: =A6&"-"&E6 -> Critical Care Benefit-F | G6: 1.87 | H6: 1.47 | I6: 1.46 | J6: 1.46 | K6: 1.26 | L6: 1.06 | M6: 0.86 | N6: 0.66 | O6: 0.46 | P6: 0.45 | Q6: 0.44 | R6: 0.43 | S6: 0.42 | T6: 0.41 | U6: 0.49 | V6: 0.57 | W6: 0.68 | X6: 0.76 | Y6: 0.84 | Z6: 0.82 | AA6: 0.71 | AB6: 0.7 | AC6: 0.69 | AD6: 0.67 | AE6: 0.72 | AF6: 0.77 | AG6: 0.82 | AH6: 0.86 | AI6: 0.91 | AJ6: 0.94 | AK6: 0.96 | AL6: 0.98 | AM6: 1 | AN6: 1.01 | AO6: 1.02 | AP6: 1.04 | AQ6: 1.05 | AR6: 1.07 | AS6: 1.09 | AT6: 1.18 | AU6: 1.17 | AV6: 1.25 | AW6: 1.32 | AX6: 1.4 | AY6: 1.44 | AZ6: 1.49 | BA6: 1.54 | BB6: 1.6 | BC6: 1.66 | BD6: 1.85 | BE6: 2.04 | BF6: 2.24 | BG6: 2.45 | BH6: 2.67 | BI6: 2.87 | BJ6: 3.08 | BK6: 3.31 | BL6: 3.56 | BM6: 3.84 | BN6: 4.41 | BO6: 5.01 | BP6: 6.22 | BQ6: 6.98 | BR6: 7.79 | BS6: 9.09 | BT6: 10.46 | BU6: 12.11 | BV6: 13.93 | BW6: 15.97 | BX6: 18.27 | BY6: 21.04 | BZ6: 24.34 | CA6: 28.13 | CB6: 32.48 | CC6: 37.41 | CD6: 41.9 | CE6: 47.93 | CF6: 54.65 | CG6: 62.1 | CH6: 70.34 | CI6: 79.45 | CJ6: 88.56 | CK6: 98.47 | CL6: 109.26 | CM6: 121.01 | CN6: 133.81 | CO6: 151.51 | CP6: 176.27 | CQ6: 205.02 | CR6: 238.38 | CS6: 277.11 | CT6: 322.13 | CU6: 373.21 | CV6: 430.95 | CW6: 496 | CX6: 569.08 | CY6: 651.06 | CZ6: 742.97 | DA6: 846.09 | DB6: 0
A7: Critical Care Benefit | B7: CIESCB | D7: 1 | E7: M | F7: =A7&"-"&E7 -> Critical Care Benefit-M | G7: 2.45 | H7: 1.97 | I7: 1.96 | J7: 1.96 | K7: 1.67 | L7: 1.38 | M7: 1.08 | N7: 0.8 | O7: 0.5 | P7: 0.59 | Q7: 0.69 | R7: 0.82 | S7: 0.96 | T7: 1.1 | U7: 1.23 | V7: 1.35 | W7: 1.49 | X7: 1.61 | Y7: 1.73 | Z7: 1.74 | AA7: 1.54 | AB7: 1.54 | AC7: 1.53 | AD7: 1.52 | AE7: 1.52 | AF7: 1.52 | AG7: 1.52 | AH7: 1.52 | AI7: 1.52 | AJ7: 1.58 | AK7: 1.64 | AL7: 1.7 | AM7: 1.78 | AN7: 1.85 | AO7: 1.9 | AP7: 1.95 | AQ7: 2.01 | AR7: 2.07 | AS7: 2.13 | AT7: 2.27 | AU7: 2.25 | AV7: 2.38 | AW7: 2.52 | AX7: 2.67 | AY7: 2.81 | AZ7: 2.96 | BA7: 3.12 | BB7: 3.29 | BC7: 3.47 | BD7: 3.75 | BE7: 4.05 | BF7: 4.36 | BG7: 4.69 | BH7: 5.04 | BI7: 5.42 | BJ7: 5.82 | BK7: 6.24 | BL7: 6.68 | BM7: 7.15 | BN7: 7.89 | BO7: 8.67 | BP7: 10.45 | BQ7: 11.39 | BR7: 12.38 | BS7: 15.21 | BT7: 18.13 | BU7: 21.14 | BV7: 24.27 | BW7: 27.52 | BX7: 30.45 | BY7: 37.63 | BZ7: 42.66 | CA7: 48.35 | CB7: 54.77 | CC7: 62 | CD7: 68.65 | CE7: 77.4 | CF7: 87.08 | CG7: 97.73 | CH7: 109.4 | CI7: 122.13 | CJ7: 134.82 | CK7: 148.43 | CL7: 163.05 | CM7: 178.78 | CN7: 195.72 | CO7: 218.02 | CP7: 253.03 | CQ7: 293.72 | CR7: 341.06 | CS7: 396.18 | CT7: 460.43 | CU7: 534.49 | CV7: 619.85 | CW7: 718.26 | CX7: 831.78 | CY7: 876.03 | CZ7: 911.35 | DA7: 947.5 | DB7: 0
A8: Early to Intermediate CI | B8: CIESEI | D8: 1 | E8: F | F8: =A8&"-"&E8 -> Early to Intermediate CI-F | G8: 1.09 | H8: 0.96 | I8: 0.84 | J8: 0.75 | K8: 0.66 | L8: 0.57 | M8: 0.48 | N8: 0.41 | O8: 0.38 | P8: 0.36 | Q8: 0.34 | R8: 0.32 | S8: 0.31 | T8: 0.34 | U8: 0.38 | V8: 0.43 | W8: 0.47 | X8: 0.53 | Y8: 0.54 | Z8: 0.56 | AA8: 0.53 | AB8: 0.58 | AC8: 0.64 | AD8: 0.7 | AE8: 0.76 | AF8: 0.92 | AG8: 1.03 | AH8: 1.2 | AI8: 1.34 | AJ8: 1.52 | AK8: 1.71 | AL8: 1.97 | AM8: 2.27 | AN8: 2.4 | AO8: 2.53 | AP8: 2.59 | AQ8: 2.69 | AR8: 2.79 | AS8: 2.97 | AT8: 3.18 | AU8: 3.19 | AV8: 3.42 | AW8: 3.67 | AX8: 3.86 | AY8: 4.07 | AZ8: 4.29 | BA8: 4.52 | BB8: 4.75 | BC8: 4.85 | BD8: 4.95 | BE8: 5.01 | BF8: 5.01 | BG8: 5.14 | BH8: 5.21 | BI8: 5.3 | BJ8: 5.41 | BK8: 5.79 | BL8: 6.19 | BM8: 6.74 | BN8: 7.36 | BO8: 7.79 | BP8: 8.47 | BQ8: 9.19 | BR8: 10.1 | BS8: 11.1 | BT8: 12.07 | BU8: 13.15 | BV8: 13.97 | BW8: 14.41 | BX8: 14.95 | BY8: 15.39 | BZ8: 16.14 | CA8: 16.91 | CB8: 17.63 | CC8: 18.39 | CD8: 19.53 | CE8: 19.82 | CF8: 20.18 | CG8: 20.19 | CH8: 20.22 | CI8: 20.31 | CJ8: 20.43 | CK8: 20.61 | CL8: 20.66 | CM8: 20.76 | CN8: 20.96 | CO8: 21.19 | CP8: 21.52 | CQ8: 22 | CR8: 22.64 | CS8: 23.49 | CT8: 24.79 | CU8: 25.27 | CV8: 21.93 | CW8: 19.69 | CX8: 18.22 | CY8: 17.27 | CZ8: 16.68 | DA8: 18.57 | DB8: 0
A9: Early to Intermediate CI | B9: CIESEI | D9: 1 | E9: M | F9: =A9&"-"&E9 -> Early to Intermediate CI-M | G9: 0.93 | H9: 0.84 | I9: 0.76 | J9: 0.69 | K9: 0.63 | L9: 0.57 | M9: 0.51 | N9: 0.46 | O9: 0.42 | P9: 0.39 | Q9: 0.35 | R9: 0.32 | S9: 0.3 | T9: 0.29 | U9: 0.29 | V9: 0.29 | W9: 0.3 | X9: 0.33 | Y9: 0.37 | Z9: 0.43 | AA9: 0.44 | AB9: 0.5 | AC9: 0.56 | AD9: 0.53 | AE9: 0.51 | AF9: 0.52 | AG9: 0.51 | AH9: 0.52 | AI9: 0.59 | AJ9: 0.67 | AK9: 0.74 | AL9: 0.84 | AM9: 0.94 | AN9: 1.04 | AO9: 1.14 | AP9: 1.28 | AQ9: 1.48 | AR9: 1.69 | AS9: 1.95 | AT9: 2.23 | AU9: 2.15 | AV9: 2.42 | AW9: 2.7 | AX9: 3.09 | AY9: 3.52 | AZ9: 4.15 | BA9: 4.57 | BB9: 5.01 | BC9: 5.41 | BD9: 5.84 | BE9: 6 | BF9: 6.46 | BG9: 6.96 | BH9: 7.61 | BI9: 8.3 | BJ9: 8.82 | BK9: 10.2 | BL9: 11.72 | BM9: 13.52 | BN9: 15.52 | BO9: 18.06 | BP9: 20.61 | BQ9: 23.43 | BR9: 26.51 | BS9: 30.1 | BT9: 31.88 | BU9: 34.64 | BV9: 36.98 | BW9: 39.58 | BX9: 42.37 | BY9: 42.87 | BZ9: 46.78 | CA9: 50.17 | CB9: 52.48 | CC9: 54.91 | CD9: 57.32 | CE9: 57.29 | CF9: 57.49 | CG9: 56.34 | CH9: 55.36 | CI9: 54.55 | CJ9: 53.9 | CK9: 53.41 | CL9: 52.55 | CM9: 51.79 | CN9: 51.29 | CO9: 50.6 | CP9: 50.08 | CQ9: 49.78 | CR9: 49.67 | CS9: 49.76 | CT9: 50.65 | CU9: 51.12 | CV9: 45.28 | CW9: 41.36 | CX9: 38.75 | CY9: 37.06 | CZ9: 35.96 | DA9: 40.98 | DB9: 0
A10: Pre-Early CI | B10: CIESPE | D10: 1 | E10: F | F10: =A10&"-"&E10 -> Pre-Early CI-F | G10: 0.38 | H10: 0.39 | I10: 0.4 | J10: 0.42 | K10: 0.45 | L10: 0.47 | M10: 0.51 | N10: 0.51 | O10: 0.53 | P10: 0.54 | Q10: 0.55 | R10: 0.56 | S10: 0.54 | T10: 0.54 | U10: 0.54 | V10: 0.54 | W10: 0.54 | X10: 0.53 | Y10: 0.51 | Z10: 0.48 | AA10: 0.4 | AB10: 0.38 | AC10: 0.42 | AD10: 0.47 | AE10: 0.54 | AF10: 0.63 | AG10: 0.74 | AH10: 0.73 | AI10: 0.72 | AJ10: 0.71 | AK10: 0.72 | AL10: 0.72 | AM10: 0.71 | AN10: 0.71 | AO10: 0.71 | AP10: 0.71 | AQ10: 0.71 | AR10: 0.78 | AS10: 0.84 | AT10: 0.92 | AU10: 0.93 | AV10: 1.01 | AW10: 1.1 | AX10: 1.21 | AY10: 1.32 | AZ10: 1.44 | BA10: 1.58 | BB10: 1.67 | BC10: 1.76 | BD10: 6.2 | BE10: 6.73 | BF10: 7.27 | BG10: 7.85 | BH10: 8.44 | BI10: 9.04 | BJ10: 9.66 | BK10: 10.27 | BL10: 10.79 | BM10: 11.31 | BN10: 12.26 | BO10: 13.22 | BP10: 14.61 | BQ10: 16.88 | BR10: 20.89 | BS10: 28.36 | BT10: 28.9 | BU10: 29.49 | BV10: 29.96 | BW10: 30.36 | BX10: 30.76 | BY10: 33.75 | BZ10: 47.99 | CA10: 62.05 | CB10: 64.76 | CC10: 67.43 | CD10: 50.36 | CE10: 60.86 | CF10: 71.11 | CG10: 72.55 | CH10: 73.93 | CI10: 77.72 | CJ10: 83.45 | CK10: 91.29 | CL10: 99.24 | CM10: 107.25 | CN10: 115.27 | CO10: 123.27 | CP10: 131.16 | CQ10: 138.87 | CR10: 146.3 | CS10: 164.21 | CT10: 181.67 | CU10: 198.54 | CV10: 214.69 | CW10: 230.05 | CX10: 246.19 | CY10: 263.29 | CZ10: 281.49 | DA10: 365.19 | DB10: 0
A11: Pre-Early CI | B11: CIESPE | D11: 1 | E11: M | F11: =A11&"-"&E11 -> Pre-Early CI-M | G11: 0.43 | H11: 0.42 | I11: 0.41 | J11: 0.41 | K11: 0.41 | L11: 0.41 | M11: 0.42 | N11: 0.43 | O11: 0.45 | P11: 0.47 | Q11: 0.5 | R11: 0.52 | S11: 0.5 | T11: 0.48 | U11: 0.47 | V11: 0.45 | W11: 0.44 | X11: 0.43 | Y11: 0.43 | Z11: 0.43 | AA11: 0.38 | AB11: 0.37 | AC11: 0.42 | AD11: 0.46 | AE11: 0.52 | AF11: 0.58 | AG11: 0.65 | AH11: 0.64 | AI11: 0.63 | AJ11: 0.62 | AK11: 0.62 | AL11: 0.62 | AM11: 0.61 | AN11: 0.61 | AO11: 0.61 | AP11: 0.6 | AQ11: 0.6 | AR11: 0.67 | AS11: 0.76 | AT11: 0.86 | AU11: 0.9 | AV11: 1.02 | AW11: 1.12 | AX11: 1.23 | AY11: 1.36 | AZ11: 1.5 | BA11: 1.69 | BB11: 1.78 | BC11: 1.87 | BD11: 6.31 | BE11: 6.84 | BF11: 7.39 | BG11: 8 | BH11: 8.64 | BI11: 9.29 | BJ11: 9.96 | BK11: 10.65 | BL11: 11.2 | BM11: 11.76 | BN11: 12.76 | BO11: 13.75 | BP11: 15.19 | BQ11: 17.5 | BR11: 21.54 | BS11: 29.06 | BT11: 29.64 | BU11: 30.27 | BV11: 30.76 | BW11: 31.19 | BX11: 31.63 | BY11: 34.66 | BZ11: 48.95 | CA11: 63.05 | CB11: 65.77 | CC11: 68.46 | CD11: 51.05 | CE11: 61.56 | CF11: 71.83 | CG11: 73.29 | CH11: 74.68 | CI11: 78.48 | CJ11: 84.22 | CK11: 92.07 | CL11: 100.01 | CM11: 108.02 | CN11: 116.05 | CO11: 124.04 | CP11: 131.94 | CQ11: 139.65 | CR11: 147.08 | CS11: 164.99 | CT11: 182.43 | CU11: 199.29 | CV11: 215.44 | CW11: 230.77 | CX11: 246.92 | CY11: 264.02 | CZ11: 282.23 | DA11: 365.92 | DB11: 0
A12: Juvenile CI | B12: CIESJN | D12: 1 | E12: F | F12: =A12&"-"&E12 -> Juvenile CI-F | G12: 0.97 | H12: 0.99 | I12: 1 | J12: 1.06 | K12: 1.3 | L12: 1.4 | M12: 1.66 | N12: 2.89 | O12: 3.03 | P12: 2.99 | Q12: 2.99 | R12: 2.84 | S12: 2.97 | T12: 3.03 | U12: 3.14 | V12: 3.29 | W12: 3.39 | X12: 3.48 | Y12: 3.57 | Z12: 0 | AA12: 0 | AB12: 0 | AC12: 0 | AD12: 0 | AE12: 0 | AF12: 0 | AG12: 0 | AH12: 0 | AI12: 0 | AJ12: 0 | AK12: 0 | AL12: 0 | AM12: 0 | AN12: 0 | AO12: 0 | AP12: 0 | AQ12: 0 | AR12: 0 | AS12: 0 | AT12: 0 | AU12: 0 | AV12: 0 | AW12: 0 | AX12: 0 | AY12: 0 | AZ12: 0 | BA12: 0 | BB12: 0 | BC12: 0 | BD12: 0 | BE12: 0 | BF12: 0 | BG12: 0 | BH12: 0 | BI12: 0 | BJ12: 0 | BK12: 0 | BL12: 0 | BM12: 0 | BN12: 0 | BO12: 0 | BP12: 0 | BQ12: 0 | BR12: 0 | BS12: 0 | BT12: 0 | BU12: 0 | BV12: 0 | BW12: 0 | BX12: 0 | BY12: 0 | BZ12: 0 | CA12: 0 | CB12: 0 | CC12: 0 | CD12: 0 | CE12: 0 | CF12: 0 | CG12: 0 | CH12: 0 | CI12: 0 | CJ12: 0 | CK12: 0 | CL12: 0 | CM12: 0 | CN12: 0 | CO12: 0 | CP12: 0 | CQ12: 0 | CR12: 0 | CS12: 0 | CT12: 0 | CU12: 0 | CV12: 0 | CW12: 0 | CX12: 0 | CY12: 0 | CZ12: 0 | DA12: 0 | DB12: 0
A13: Juvenile CI | B13: CIESJN | D13: 1 | E13: M | F13: =A13&"-"&E13 -> Juvenile CI-M | G13: 1.04 | H13: 1.03 | I13: 1.02 | J13: 1.06 | K13: 1.28 | L13: 1.84 | M13: 2.1 | N13: 3.32 | O13: 3.29 | P13: 2.95 | Q13: 2.55 | R13: 2.64 | S13: 2.75 | T13: 2.77 | U13: 2.85 | V13: 2.83 | W13: 2.82 | X13: 2.79 | Y13: 2.81 | Z13: 0 | AA13: 0 | AB13: 0 | AC13: 0 | AD13: 0 | AE13: 0 | AF13: 0 | AG13: 0 | AH13: 0 | AI13: 0 | AJ13: 0 | AK13: 0 | AL13: 0 | AM13: 0 | AN13: 0 | AO13: 0 | AP13: 0 | AQ13: 0 | AR13: 0 | AS13: 0 | AT13: 0 | AU13: 0 | AV13: 0 | AW13: 0 | AX13: 0 | AY13: 0 | AZ13: 0 | BA13: 0 | BB13: 0 | BC13: 0 | BD13: 0 | BE13: 0 | BF13: 0 | BG13: 0 | BH13: 0 | BI13: 0 | BJ13: 0 | BK13: 0 | BL13: 0 | BM13: 0 | BN13: 0 | BO13: 0 | BP13: 0 | BQ13: 0 | BR13: 0 | BS13: 0 | BT13: 0 | BU13: 0 | BV13: 0 | BW13: 0 | BX13: 0 | BY13: 0 | BZ13: 0 | CA13: 0 | CB13: 0 | CC13: 0 | CD13: 0 | CE13: 0 | CF13: 0 | CG13: 0 | CH13: 0 | CI13: 0 | CJ13: 0 | CK13: 0 | CL13: 0 | CM13: 0 | CN13: 0 | CO13: 0 | CP13: 0 | CQ13: 0 | CR13: 0 | CS13: 0 | CT13: 0 | CU13: 0 | CV13: 0 | CW13: 0 | CX13: 0 | CY13: 0 | CZ13: 0 | DA13: 0 | DB13: 0
... A15: Special Conditions | B15: CIESSC | D15: 1 | E15: M | F15: =A15&"-"&E15 -> Special Conditions-M | G15: 2.28 | H15: 2.57 | I15: 2.88 | J15: 2.44 | K15: 2.02 | L15: 1.59 | M15: 1.16 | N15: 0.74 | O15: 0.7 | P15: 0.66 | Q15: 0.62 | R15: 0.58 | S15: 0.55 | T15: 0.59 | U15: 0.64 | V15: 0.7 | W15: 0.76 | X15: 0.84 | Y15: 0.99 | Z15: 1.14 | AA15: 1.14 | AB15: 1.28 | AC15: 1.43 | AD15: 1.27 | AE15: 1.11 | AF15: 0.95 | AG15: 0.8 | AH15: 0.65 | AI15: 0.7 | AJ15: 0.76 | AK15: 0.83 | AL15: 0.9 | AM15: 0.98 | AN15: 1.06 | AO15: 1.15 | AP15: 1.24 | AQ15: 1.34 | AR15: 1.45 | AS15: 1.57 | AT15: 1.69 | AU15: 1.7 | AV15: 1.84 | AW15: 1.98 | AX15: 2.22 | AY15: 2.46 | AZ15: 2.73 | BA15: 3.02 | BB15: 3.33 | BC15: 3.67 | BD15: 4.05 | BE15: 4.45 | BF15: 4.9 | BG15: 5.41 | BH15: 5.95 | BI15: 6.54 | BJ15: 7.17 | BK15: 8.24 | BL15: 9.46 | BM15: 10.83 | BN15: 12.42 | BO15: 14.34 | BP15: 16.21 | BQ15: 18.31 | BR15: 20.6 | BS15: 23.19 | BT15: 25.55 | BU15: 28.56 | BV15: 31.22 | BW15: 33.81 | BX15: 36.7 | BY15: 38.69 | BZ15: 42.78 | CA15: 46.42 | CB15: 49.08 | CC15: 51.93 | CD15: 54.96 | CE15: 57.98 | CF15: 61.38 | CG15: 63.22 | CH15: 65.48 | CI15: 68.15 | CJ15: 71.24 | CK15: 74.75 | CL15: 77.97 | CM15: 81.57 | CN15: 85.58 | CO15: 90.17 | CP15: 95.55 | CQ15: 102.62 | CR15: 110.55 | CS15: 119.46 | CT15: 127.83 | CU15: 136.71 | CV15: 139.88 | CW15: 146 | CX15: 154.68 | CY15: 165.64 | CZ15: 178.58 | DA15: 263.03 | DB15: 0

Sheet วิธีการใช้งาน
A1: =กรอกข้อมูล!G64
A2: =IF(A1="Expire",กรอกข้อมูล!$A$1,"วิธีการใช้งาน") -> วิธีการใช้งาน
B4: ขั้นที่ 1 กรอกข้อมูลใน sheet "กรอกข้อมูล" | P4: di6'wmp
B5: ขั้นที่ 2 ใส่ข้อมูลผู้ขอเอาประกันภัยในช่องสีเขียว
B6: ขั้นที่ 3 เลือกกำหนดวิธีการคำนวน จาก จำนวนเงินเอาประกันภัย หรือ เบี้ยประกันภัย
B7: ขั้นที่ 3 ใส่ จำนวนเงินเอาประกันภัย ตามที่ต้องการ
B8: ขั้นที่ 4 การเลือกซื้อสัญญาเพิ่มเติม
B9: - กรณีที่ต้องการซื้อ WP หรือ PB ให้คลิกเลือก "ซื้อ" โดยไม่ต้องกรอกจำนวนเงินเอาประกันภัย
B10: - สำหรับสัญญาเพิ่มเติมอื่นๆ ที่ต้องการซื้อให้ใส่จำนวนเงินเอาประกันภัยในช่องของ "จำนวนเงินเอาประกันภัยที่ต้องการ"
B11: - เลือกขั้นอาชีพสำหรับสัญญาเพิ่มเติม
B13: หมายเหตุ - จำนวนเงินเอาประกันภัยที่สามารถซื้อได้ขั้นต่ำ และสูงสุดสามารถดูได้ในช่อง "ขั้นต่ำ" และ "สูงสุด"
B14: - หากสัญญาเพิ่มเติมใดที่ไม่สามารถซื้อได้ จะขึ้นข้อความว่า "ไม่สามารถซื้อได้"
B15: - ในกรณีที่ไม่ต้องการซื้อสัญญาเพิ่มเติม จะไม่สามารถใส่เลข "0" ในช่องของจำนวนเงินเอาประกันภัยได้ ท่านจะต้องกดปุ่ม "delete" เท่านั้น เพื่อเป็นช่องว่าง

Sheet กรอกข้อมูล
A1: =IF(G64="Expire","โปรแกรมข้อเสนอ หมดอายุตั้งแต่วันที่ "&TEXT(G63,"dd/MM/YYYY")," โปรแกรมข้อเสนอ แบบประกัน "&E65&" เวอร์ชั่น "&E64) -> โปรแกรมข้อเสนอ แบบประกัน ไอสมาร์ท 80/6 (ไม่มีเงินปันผล) เวอร์ชั่น A2026-1
A2: กรุณากรอกข้อมูล
A3: ข้อมูลลูกค้า | F3: ข้อมูลผู้เสนอขาย
A4: ชื่อผู้เอาประกันภัย | C4: คุณคนพิเศษ | F4: ชื่อผู้เสนอขาย | G4: KAL
A5: อายุผู้เอาประกันภัย | C5: 44 | D5: ปี | F5: หน่วย/สาขา | G5: KAL
A6: เพศ | C6: หญิง | E6: =IF(C6="ชาย","M","F") -> F | F6: เลขที่ใบอนุญาต | G6: 0123
A7: งวดการชำระเบี้ยประกันภัย | C7: รายปี | D7: =IF(OR(C7="รายเดือน",C7="Monthly"),"(กรณีเลือกหมวดการชำระเบี้ยรายเดือน เบี้ยประกันภัย (สัญญาหลัก+สัญญาเพิ่มเติม) ต่อเดือน ต้องไม่ต่ำกว่า 1,000 บาท)","") | F7: เบอร์โทรศัพท์ | G7: 999999999
A10: ข้อมูลผู้ชำระเบี้ย
A11: อายุ (ผู้ชำระเบี้ย) | D11: =IF(I14>=5,"","อายุผู้ชำระเบี้ยระหว่าง 20-70 ปี") -> อายุผู้ชำระเบี้ยระหว่าง 20-70 ปี
A12: เพศ (ผู้ชำระเบี้ย)
I13: Group | J13: Payment Term | K13: Payment Year
A14: เลือกแบบประกัน | C14: ชำระเบี้ย 6 ปี | I14: =VLOOKUP($C14,$A$78:$E$83,5,FALSE) -> 1 | J14: =VLOOKUP($C14,$A$78:$G$83,7,FALSE) -> 6 ปี | K14: =VLOOKUP($C14,$A$78:$H$83,8,FALSE) -> 6
A17: ผลิตภัณฑ์ | B17: จำนวนเงินเอาประกันภัย | E17: ขั้นอาชีพ | F17: ="เบี้ยประกันภัย ("&C7&")" -> เบี้ยประกันภัย (รายปี) | G17: อายุรับประกัน
B18: ขั้นต่ำ | C18: สูงสุด | D18: ที่ต้องการ | I18: เบี้ยต่อปี | J18: จำนวนงวดต่อปี
A19: ไอสมาร์ท 80/6 (W80F06) | B19: =IF(I14>=5,50000,150000) -> 150000 | C19: =IF(I14>=5,50000,"") | D19: 1000000 | F19: =IF(AND(I14>=5,D19<>50000),"ระบุจำนวนเงินเอาประกันภัยไม่ถูกต้อง",IF(AND(I14<5,D19<B19,D19<>0),"ระบุจำนวนเงินเอาประกันภัยไม่ถูกต้อง",IF(J22="no","ระบุแบบประกันไม่ถูกต้อง",IF(D19=0,0,Cal!H13)))) -> 287000 | G19: 25 ปี - 65 ปี | H19: =IF(OR(F19=0,LEFT(F19,4)="ระบุ"),"ไม่คุ้มครอง","") | I19: =IFERROR(F19*J19,0) -> 287000 | J19: =VLOOKUP($C7,$E$66:$G$69,3,FALSE) -> 1 | K19: Rider Name | L19: Rider Plancode | M19: Rider Plancode
A20: PB Beyond | B20: =IF(C5>70,"ไม่สามารถซื้อได้",IF(OR(D20="",D20="ไม่ซื้อ",I14>=5),"",IF(AND(C5<=70,C11=0,D20="ซื้อ"),"กรอกอายุผู้ชำระเบี้ย",IF(OR(C11<20,C11>70),"อายุผู้ชำระเบี้ยไม่อยู่ในเกณฑ์",IF(AND(C5<=70,C12="",D20="ซื้อ"),"กรอกเพศผู้ชำระเบี้ย",""))))) | C20: =IF(B20="","",B20) | E20: 1 | F20: =IFERROR(IF(I14>=5,"PB ไม่ขายกับ Package นี้",IF(OR(D20="",D20="ไม่ซื้อ",$H$19="ไม่คุ้มครอง"),0,IF(AND(H19="",D19>30000000),"กรุณาลดทุนประกันเหลือ 30 ลบ.",IF(AND(C5>=16,C11>=20,C12<>"",D20="ซื้อ",D21="ซื้อ"),"กรุณาเลือก WP หรือ PB อย่างใดอย่างหนึ่ง",Cal!H14)))),0) -> 0 | G20: 20 ปี - 70 ปี | H20: =IF(OR(C11<20,C11>70,D20="ไม่ซื้อ",D20="",I14>=5,LEFT(F20,5)="กรุณา"),"ไม่คุ้มครอง","") -> ไม่คุ้มครอง | I20: Plancode PB >> | J20: =IF($C$5<=15,VLOOKUP($A20,$E$86:$K$87,7,FALSE),VLOOKUP($A$20,$E$88:$K$89,7,FALSE)) -> PBSDDCI | K20: =IF($C$5<=15,VLOOKUP($A20,$E$86:$Z$87,5,FALSE),VLOOKUP($A$20,$E$88:$Z$89,5,FALSE)) -> สัญญาเพิ่มเติมพีบี บียอนด์ | L20: =J20&Cal!$B$6 -> PBSDDCI6 | M20: =K20&" ("&J20&")" -> สัญญาเพิ่มเติมพีบี บียอนด์ (PBSDDCI)
A21: WP Fit | B21: =IF(OR(C5<16,C5>70),"ไม่สามารถซื้อได้","") | C21: =IF(B21="","",B21) | E21: 1 | F21: =IF(I14>=5,"WP ไม่ขายกับ Package นี้",IF(OR(D21="ไม่ซื้อ",D21="",$H$19="ไม่คุ้มครอง"),0,IF(AND(H19="",D19>30000000),"กรุณาลดทุนประกันเหลือ 30 ลบ.",IF(AND(C5>=16,C11>=20,C12<>"",D20="ซื้อ",D21="ซื้อ"),"กรุณาเลือก WP หรือ PB อย่างใดอย่างหนึ่ง",Cal!H15)))) -> 0 | G21: 16 ปี - 70 ปี | H21: =IF(OR(C5<16,C5>70,D21="ไม่ซื้อ",D21="",I14>=5,LEFT(F21,5)="กรุณา"),"ไม่คุ้มครอง","") -> ไม่คุ้มครอง | I21: Plancode WP >> | J21: =IF($C$5<=15,"",VLOOKUP($A21,$E$92:$I$93,5,FALSE)) -> WPTPD | K21: =IF($C$5<=15,"",VLOOKUP($A21,$E$92:$Z$93,3,FALSE)) -> สัญญาเพิ่มเติมดับบลิวพี ฟิต | L21: =IF(J21="","",J21&Cal!$B$6) -> WPTPD6 | M21: =K21&" ("&J21&")" -> สัญญาเพิ่มเติมดับบลิวพี ฟิต (WPTPD)
A22: AP | B22: =IF(C5>60,"ไม่สามารถซื้อได้",100000) -> 100000 | C22: =IF(C5>60,"ไม่สามารถซื้อได้",IF(C5<16,MIN(3000000,2*D19),MIN(5*D19,10000000))) -> 5000000 | E22: 1 | F22: =IF($D$22+$D$23>MIN(5*$D$19,10000000),"AP+ECARE เกินกว่าที่กำหนด",IF(AND(C5<16,D22>C22),"AP เกินกว่าที่กำหนด",Cal!H16)) -> 0 | G22: 1 เดือน - 60 ปี | H22: =IF(OR(LEFT(F22,2)="AP",F22=0),"ไม่คุ้มครอง","") -> ไม่คุ้มครอง | I22: Check plan >> | J22: =IF(C15<>"","no","Yes") -> Yes
A23: =IF(I14>=5,"","ECARE") -> ECARE | B23: =IF(A23="","",IF(OR(C5<16,C5>60),"ไม่สามารถซื้อได้",100000)) -> 100000 | C23: =IF(A23="","",IF(OR(C5<16,C5>60),"ไม่สามารถซื้อได้",MIN(10000000,5*D19))) -> 5000000 | E23: 1 | F23: =IF(A23="",0,IF($D$22+$D$23>MIN(5*$D$19,10000000),"AP+ECARE เกินกว่าที่กำหนด",Cal!H17)) -> 0 | G23: 16 ปี - 60 ปี | H23: =IF(OR(LEFT(F23,2)="AP",F23=0),"ไม่คุ้มครอง","") -> ไม่คุ้มครอง | I23: Final Select | J23: =IF(AND(F20>0,H20=""),J20,IF(AND(F21>0,H21=""),J21,""))
A24: =IF(I14=5,"","MEX") -> MEX | B24: =IF(A24="","",IF(C5>70,"ไม่สามารถซื้อได้",1200)) -> 1200 | C24: =IF(A24="","",IF(C5>70,"ไม่สามารถซื้อได้",IF(C5<=10,3200,6200))) -> 6200 | E24: 1 | F24: =IF(AND(I14=5,R37>=1),"MEA Extra ไม่ขายกับ package นี้",IF(AND(I14=6,OR(D24="",D24="ไม่ซื้อ")),"กรุณาเลือกแผน MEA Extra",IF(OR(A24="",F19=0,D24="",D24="ไม่ซื้อ"),0,IF(D24>C24,A24&" เกินกว่าที่กำหนด",Cal!H22)))) -> 0 | G24: 1 เดือน - 70 ปี | H24: =IF(OR(I14=5,F19=0,D24="",D24="ไม่ซื้อ",D24>C24),"ไม่คุ้มครอง","") -> ไม่คุ้มครอง | AI24: =IF(C5>75,"ไม่สามารถซื้อได้","แผน S") -> แผน S | AJ24: =IF(C5>75,"ไม่สามารถซื้อได้","แผน M") -> แผน M | AK24: แผน M
A25: MEB | B25: =IF(OR(C5<6,C5>65),"ไม่สามารถซื้อได้",500) -> 500 | C25: =IF(OR(C5<6,C5>65),"ไม่สามารถซื้อได้",IF(C5<11,500,IF(C5<16,1000,5000))) -> 5000 | D25: 500 | E25: 1 | F25: =IF(OR(F19=0,D25="",D25="ไม่ซื้อ"),0,IF(D25>C25,A25&" เกินกว่าที่กำหนด",Cal!H19)) -> 750 | G25: 6 ปี - 65 ปี | H25: =IF(OR(,C25="ไม่สามารถซื้อได้",D25="",D25="ไม่ซื้อ",D25>C25,F25=0),"ไม่คุ้มครอง","")
A26: DCI | B26: =IF(OR(C5<20,C5>65),"ไม่สามารถซื้อได้",200000) -> 200000 | C26: =IF(AND(I14>=5,C5>=20,C5<=65),200000,IF(OR(C5<20,C5>65),"ไม่สามารถซื้อได้",10000000)) -> 10000000 | F26: =IF(AND(I14>=5,D26>200000),"ต้องระบุทุน DCI 2 แสนบาทเท่านั้น",IF(D26>C26,A26&" เกินกว่าที่กำหนด",IF($D$28+$D$26>10000000,"DCI+CPR เกินกว่าที่กำหนด",Cal!H20))) -> 0 | G26: 20 ปี - 65 ปี | H26: =IF(OR(D26="",D26>C26,C26="ไม่สามารถซื้อได้",F26=0),"ไม่คุ้มครอง","") -> ไม่คุ้มครอง | N26: แผน | O26: ความคุ้มครอง | R26: MHP | S26: Plan_Eng | T26: Plan Code | U26: TH Product Name | V26: แผน | X26: แผน | Y26: Plancode | AI26: Easy Ci | AK26: =IF(C6="ชาย","M",IF(C6="หญิง","F","-")) -> F | AL26: =C5 -> 44
A27: PLS10 | B27: =IF(I14>=5,"",IF(OR(C5<20,C5>59),"ไม่สามารถซื้อได้",300000)) -> 300000 | C27: =IF(B27="","",IF(OR(C5<20,C5>59),"ไม่สามารถซื้อได้",5*D19)) -> 5000000 | F27: =IF(I14>=5,"PLS ไม่ขายกับ package นี้",IF(B27="ไม่สามารถซื้อได้",0,IF(D27>C27,A27&" เกินกว่าที่กำหนด",Cal!H21))) -> 0 | G27: 20 ปี - 59 ปี | H27: =IF(OR(D27="",D27>C27,C27="ไม่สามารถซื้อได้",F27=0,I14>=5),"ไม่คุ้มครอง","") -> ไม่คุ้มครอง | L27: Select >> | M27: =D30 -> 0 | N27: PLATINUM | O27: ทั่วโลก | P27: เอเชีย | Q27: ประเทศไทย | R27: 6 | S27: Platinum | T27: MHP1J | U27: ไอเฮลท์ตี้ อัลตร้า (แผนสมาร์ท) | V27: สมาร์ท | X27: =IF(C5>65,"","แผน S") -> แผน S | Y27: MCI1 | Z27: 1 | AG27: แผน S | AH27: =AK24 -> แผน M | AI27: Benefit Component | AJ27: SA | AK27: Key | AL27: Rate | AM27: Premium | AN27: Premium (Mode) | AO27: Premium ANN
A28: =IF(I14>=5,"","CPR") -> CPR | B28: =IF(A28="","",IF(C5>65,"ไม่สามารถซื้อได้",IF(D26>0,"ไม่สามารถซื้อคู่กับ DCI ได้",300000))) -> 300000 | C28: =IF(A28="","",IF(C5>65,"ไม่สามารถซื้อได้",IF(D26>0,"ไม่สามารถซื้อคู่กับ DCI ได้",MIN(5000000,D19*5)))) -> 5000000 | F28: =IF(A28="",0,IF(D28>C28,A28&" เกินกว่าที่กำหนด",IF($D$28+$D$26>10000000,"DCI+CPR เกินกว่าที่กำหนด",Cal!H37))) -> 0 | G28: 1 เดือน - 65 ปี | H28: =IF(OR(D28="",D28>C28,LEFT(C28,3)="ไม่",F28=0),"ไม่คุ้มครอง","") -> ไม่คุ้มครอง | M28: =D37 -> ประเทศไทย | N28: DIAMOND | O28: ทั่วโลก | P28: เอเชีย | Q28: ประเทศไทย | R28: 5 | S28: Diamond | T28: MHP1S | U28: ไอเฮลท์ตี้ อัลตร้า (แผนสมาร์ท) | V28: สมาร์ท | X28: =IF(C5>65,"","แผน M") -> แผน M | Y28: MCI2 | Z28: 2 | AG28: แผน M | AH28: =IF(AH27="แผน S",SUM(AN28:AN30),SUM(AN28:AN33)) -> 44789.5 | AI28: Major CI | AJ28: =D33 -> 5000000 | AK28: =AI28&"-"&$AK$26 -> Major CI-F | AL28: =IF(C5<76,(VLOOKUP(AK28,'Rate CI 123'!$F$4:$DB$15,$C$5+2,FALSE)),0) -> 7.17 | AM28: =TRUNC(AL28*TRUNC(AJ28/1000,3),2) -> 35850 | AN28: =TRUNC(AM28*$AL$36,2) -> 35850
A29: =IF(I14>=5,"","HIC") -> HIC | B29: =IF(A29="","",IF(H24="","ไม่สามารถซื้อคู่กับ MEX",IF(H30="","ไม่สามารถซื้อคู่กับ iHealthy Ultra",IF(H25="","ไม่สามารถซื้อคู่กับ MEB",IF(F28=0,"ต้องซื้อคู่กับ CPR",1000))))) -> ไม่สามารถซื้อคู่กับ MEB | C29: =IF(A29="","",IF(OR(LEFT(B29,3)="ไม่",F28=0),B29,10000)) -> ไม่สามารถซื้อคู่กับ MEB | F29: =IF(A28="",0,Cal!H38) -> 0 | G29: 1 เดือน - 65 ปี | H29: =IF(OR(D29="",H28="ไม่คุ้มครอง",LEFT(C29,3)="ไม่"),"ไม่คุ้มครอง","") -> ไม่คุ้มครอง | L29: Check select plan correct? | M29: =IF(OR(I14=6,M27="ไม่ซื้อ",M27=""),"No",IF(AND(C5<11,OR(M27="Smart",M27="Bronze"),M28="ประเทศไทย"),"OK",IF(AND(C5>=11,OR(M27="Smart",M27="Bronze",M27="Silver",M27="Gold"),M28="ประเทศไทย"),"OK",IF(AND(C5>=11,OR(M27="Diamond",M27="Platinum"),OR(M28="ประเทศไทย",M28="เอเชีย",M28="ทั่วโลก")),"OK","No")))) -> No | N29: GOLD | O29: ประเทศไทย | R29: 4 | S29: Gold | T29: MHP2J | U29: ไอเฮลท์ตี้ อัลตร้า (แผนบรอนซ์) | V29: บรอนซ์ | X29: =IF(OR(C5<11,C5>65),"","แผน L") -> แผน L | Y29: MCI3 | Z29: 3 | AI29: Critical Care Benefit | AJ29: =AJ28*25% -> 1250000 | AK29: =AI29&"-"&$AK$26 -> Critical Care Benefit-F | AL29: =IF(C5<76,(VLOOKUP(AK29,'Rate CI 123'!$F$4:$DB$15,$C$5+2,FALSE)),0) -> 1.44 | AM29: =TRUNC(AL29*TRUNC(AJ29/1000,3),2) -> 1800 | AN29: =TRUNC(AM29*$AL$36,2) -> 1800
A30: =IF(I14=6,"","iHealthy Ultra") -> iHealthy Ultra | B30: =IF(A30="","",IF(OR(C5<6,C5>80),"ไม่สามารถซื้อได้","แผน Smart")) -> แผน Smart | C30: =IF(A30="","",IF(OR(C5<6,C5>80),"ไม่สามารถซื้อได้",IF(C5<=10,"แผน Bronze","แผน Platinum"))) -> แผน Platinum | E30: 1 | F30: =IF(C5<=5,"ไม่สามารถซื้อ iHealthy Ultra ได้",IF(AND(I14=6,R37<>""),"iHealthy Ultra ไม่ขายกับ package นี้",IF(AND(I14=5,OR(D30="",D30="ไม่ซื้อ")),"กรุณาเลือกแผน iHealthy Ultra",IF(OR(A30="",D30="ไม่ซื้อ",D30=""),0,IF(AND(C5<11,R37>2),"แผน iHealthy Ultra ไม่ถูกต้อง",Cal!H23))))) -> 0 | G30: 6 ปี - 80 ปี | H30: =IF(OR(I14=6,F19=0,D30="",F30=0,LEFT(C30,3)="ไม่",D30="ไม่ซื้อ"),"ไม่คุ้มครอง","") -> ไม่คุ้มครอง | M30: Full Coverage | N30: SILVER | O30: ประเทศไทย | R30: 3 | S30: Silver | T30: MHP2S | U30: ไอเฮลท์ตี้ อัลตร้า (แผนบรอนซ์) | V30: บรอนซ์ | X30: =IF(OR(C5<11,C5>65),"","แผน XL") -> แผน XL | Y30: MCI4 | Z30: 4 | AI30: Juvenile CI | AJ30: =AJ28*25% -> 1250000 | AK30: =AI30&"-"&$AK$26 -> Juvenile CI-F | AL30: =IF(C5>18,0,VLOOKUP(AK30,'Rate CI 123'!$F$4:$DB$15,$C$5+2,FALSE)) -> 0 | AM30: =TRUNC(AL30*TRUNC(AJ30/1000,3),2) -> 0 | AN30: =TRUNC(AM30*$AL$36,2) -> 0
B31: =IF($D$30="","","โปรดเลือกลักษณะความคุ้มครอง") | M31: Deductible | N31: BRONZE | O31: ประเทศไทย | R31: 2 | S31: Bronze | T31: MHP3S | U31: ไอเฮลท์ตี้ อัลตร้า (แผนซิลเวอร์) | V31: ซิลเวอร์ | X31: ที่เลือก | AI31: Pre-Early CI | AJ31: =MIN(AJ28*20%,100000) -> 100000 | AK31: =AI31&"-"&$AK$26 -> Pre-Early CI-F | AL31: =IF(C5<76,(VLOOKUP(AK31,'Rate CI 123'!$F$4:$DB$15,$C$5+2,FALSE)),0) -> 1.32 | AM31: =TRUNC(AL31*TRUNC(AJ31/1000,3),2) -> 132 | AN31: =TRUNC(AM31*$AL$36,2) -> 132
A32: Roke Rai So Shield | B32: =IF(C5>65,"ไม่สามารถซื้อได้","แผน S") -> แผน S | C32: =IF(C5>65,"ไม่สามารถซื้อได้",IF(AND(C5<66,C5>11),"แผน XL","แผน M")) -> แผน XL | E32: 1 | F32: =IFERROR(IF(D32="",0,Cal!H24),"-") -> 0 | G32: 1 เดือน - 65 ปี | H32: =IF(D32="","ไม่คุ้มครอง","") -> ไม่คุ้มครอง | N32: SMART | O32: ประเทศไทย | R32: 1 | S32: Smart | T32: MHP4S | U32: ไอเฮลท์ตี้ อัลตร้า (แผนโกลด์) | V32: โกลด์ | X32: =D32 -> 0 | Y32: =IFERROR(VLOOKUP(X32,$X$27:$Y$30,2,FALSE),"") | Z32: =IFERROR(VLOOKUP(X32,$X$27:$Z$30,3,FALSE),"") | AI32: Early to Intermediate CI | AJ32: =AJ28*25% -> 1250000 | AK32: =AI32&"-"&$AK$26 -> Early to Intermediate CI-F | AL32: =IF(C5<76,(VLOOKUP(AK32,'Rate CI 123'!$F$4:$DB$15,$C$5+2,FALSE)),0) -> 4.07 | AM32: =TRUNC(AL32*TRUNC(AJ32/1000,3),2) -> 5087.5 | AN32: =TRUNC(AM32*$AL$36,2) -> 5087.5
A33: สัญญาเพิ่มเติมคุ้มครองโรคร้ายแรง (CI 123) | B33: =IF(C5>75,"ไม่สามารถซื้อได้",100000) -> 100000 | C33: =IF(C5>75,"ไม่สามารถซื้อได้",10000000) -> 10000000 | D33: 5000000 | F33: =IF(D33="",0,IF(C5>75,"อายุผู้เอาประกันไม่ถูกต้อง",IF(AO34="NO","เบี้ยประกันภัยรวมรายปีของสัญญาเพิ่มเติมคุ้มครองโรคร้ายแรงและบันทึกฯต้องมากกว่าหรือเท่ากับ 1,000 บาท",SUM(AN28:AN30)))) -> 37650 | G33: 1 เดือน - 75 ปี | AI33: Special conditions | AJ33: =AJ28*10% -> 500000 | AK33: =AI33&"-"&$AK$26 -> Special conditions-F | AL33: =IF(C5<76,(VLOOKUP(AK33,'Rate CI 123'!$F$4:$DB$15,$C$5+2,FALSE)),0) -> 3.84 | AM33: =TRUNC(AL33*TRUNC(AJ33/1000,3),2) -> 1920 | AN33: =TRUNC(AM33*$AL$36,2) -> 1920
A34: บันทึกฯ โรคร้ายแรงระยะก่อนเริ่มต้น (CI 123) | B34: บังคับซื้อแนบสัญญาเพิ่มเติม CI 123 | D34: =IF(D33="","",MIN(AJ28*20%,100000)) -> 100000 | F34: =IF(D33="",0,IF(C5>75,"อายุผู้เอาประกันไม่ถูกต้อง",IF(AO34="NO","เบี้ยประกันภัยรวมรายปีของสัญญาเพิ่มเติมคุ้มครองโรคร้ายแรงและบันทึกฯต้องมากกว่าหรือเท่ากับ 1,000 บาท",AN31))) -> 132 | AM34: =SUM(AM28:AM33) -> 44789.5 | AN34: =SUM(AN28:AN33)*AL37 -> 44789.5 | AO34: =IF(AN34<1000,"NO","")
A35: บันทึกฯ โรคร้ายแรงระยะเริ่มต้นถึงปานกลาง (CI 123) | B35: บังคับซื้อแนบสัญญาเพิ่มเติม CI 123 | D35: =IF(D33="","",AJ28*25%) -> 1250000 | F35: =IF(D33="",0,IF(C5>75,"อายุผู้เอาประกันไม่ถูกต้อง",IF(AO34="NO","เบี้ยประกันภัยรวมรายปีของสัญญาเพิ่มเติมคุ้มครองโรคร้ายแรงและบันทึกฯต้องมากกว่าหรือเท่ากับ 1,000 บาท",AN32))) -> 5087.5 | AI35: รายปี | AJ35: 1 | AK35: 1 | AL35: =C7 -> รายปี
A36: บันทึกฯ โรคร้ายแรงภายใต้เงื่อนไขพิเศษ (CI 123) | B36: บังคับซื้อแนบสัญญาเพิ่มเติม CI 123 | D36: =IF(D33="","",AJ28*10%) -> 500000 | F36: =IF(D33="",0,IF(C5>75,"อายุผู้เอาประกันไม่ถูกต้อง",IF(AO34="NO","เบี้ยประกันภัยรวมรายปีของสัญญาเพิ่มเติมคุ้มครองโรคร้ายแรงและบันทึกฯต้องมากกว่าหรือเท่ากับ 1,000 บาท",AN33))) -> 1920 | AI36: ราย 6 เดือน | AJ36: 0.52 | AK36: 2 | AL36: =VLOOKUP(AL35,$AI$35:$AJ$38,2,FALSE) -> 1
D37: ประเทศไทย | E37: รวมงวดละ | F37: =IF(OR(H19="ไม่คุ้มครอง",AND(I14=5,H30="ไม่คุ้มครอง"),AND(I14=6,H24="ไม่คุ้มครอง")),0,SUM(F19:F36)) -> 332539.5 | N37: for Drop Down List >> | O37: =IFERROR(VLOOKUP($M27,$N$27:$R$32,2,FALSE),"") | P37: =IFERROR(VLOOKUP($M27,$N$27:$R$32,3,FALSE),"") | Q37: =IFERROR(VLOOKUP($M27,$N$27:$R$32,4,FALSE),"") | R37: =IFERROR(VLOOKUP($M27,$N$27:$R$32,5,FALSE),"") | T37: MHP5S | U37: ไอเฮลท์ตี้ อัลตร้า (แผนไดมอนด์) | V37: ไดมอนด์ | AI37: ราย 3 เดือน | AJ37: 0.27 | AK37: 4 | AL37: =VLOOKUP(AL35,$AI$35:$AK$38,3,FALSE) -> 1
A38: =IF(C7="รายเดือน","การชำระเบี้ยประกันภัยรายเดือนครั้งแรก ผู้เอาประกันภัยต้องชำระเบี้ยประกันภัยเป็นจำนวน 2 งวด","") | T38: MHP5SA | U38: ไอเฮลท์ตี้ อัลตร้า (แผนไดมอนด์) เอเชีย | V38: ไดมอนด์ | AI38: รายเดือน | AJ38: 0.09 | AK38: 12
A39: ="เบี้ยประกันภัยรวมงวดแรก ("&C7&") และจำนวนเงินเอาประกันภัย" -> เบี้ยประกันภัยรวมงวดแรก (รายปี) และจำนวนเงินเอาประกันภัย | T39: MHP5SW | U39: ไอเฮลท์ตี้ อัลตร้า (แผนไดมอนด์) ทั่วโลก | V39: ไดมอนด์
A40: ="จำนวนเงินเอาประกันภัยของ "&A19 -> จำนวนเงินเอาประกันภัยของ ไอสมาร์ท 80/6 (W80F06) | C40: =IF(H19="ไม่คุ้มครอง",0,D19) -> 1000000 | E40: บาท | T40: MHP6S | U40: ไอเฮลท์ตี้ อัลตร้า (แผนแพลทินั่ม) | V40: แพลทินั่ม
A41: ="เบี้ยประกันภัยรวมงวดแรก ("&C7&")" -> เบี้ยประกันภัยรวมงวดแรก (รายปี) | C41: =IF(AND(C7="รายเดือน",F37<1000),"เบี้ยรายเดือนน้อยกว่า 1,000 บาท",IF(E70="no",0,F37)) -> 332539.5 | E41: บาท | T41: MHP6SA | U41: ไอเฮลท์ตี้ อัลตร้า (แผนแพลทินั่ม) เอเชีย | V41: แพลทินั่ม
T42: MHP6SW | U42: ไอเฮลท์ตี้ อัลตร้า (แผนแพลทินั่ม) ทั่วโลก | V42: แพลทินั่ม
A44: เอกสารประกอบการเสนอขายนี้เป็นข้อมูลเบื้องต้นของแบบประกันภัย ผลประโยชน์ ความคุ้มครองและข้อยกเว้น เป็นไปตามที่กำหนดในกรมธรรม์ ผู้ซื้อควรทำความเข้าใจรายละเอียด ความคุ้มครองและเงื่อนไขก่อนตัดสินใจทำประกันภัยทุกครั้ง
A45: =ตารางแสดงผลประโยชน์!B76 -> โปรแกรมใบข้อเสนอนี้ใช้สำหรับแบบประกัน ไอสมาร์ท 80/6 (ไม่มีเงินปันผล) ที่เสนอขายตั้งแต่ 1 มกราคม 2569 ถึง 31 มีนาคม 2570 หรือตามประกาศยกเลิกการใช้จากบริษัทฯ (แล้วแต่ระยะเวลาใดจะเกิดขึ้นก่อน)
G46: =ตารางแสดงผลประโยชน์!I77 -> ไอสมาร์ท 80/6 (ไม่มีเงินปันผล) เวอร์ชั่น A2026-1
A50: MEB | C50: iHealthy Ultra | D50: MEX | E50: PLS Rider | F50: HIC
A51: ไม่ซื้อ | C51: ไม่ซื้อ | D51: ไม่ซื้อ | E51: PLS05 | F51: 1000
A52: =IF($B$25="ไม่สามารถซื้อได้",$B$25,500) -> 500 | C52: =IF($B$30="ไม่สามารถซื้อได้",$B$30,IF($C$5<11,"BRONZE","PLATINUM")) -> PLATINUM | D52: =IF($B$24="ไม่สามารถซื้อได้",$B$24,1200) -> 1200 | E52: PLS10 | F52: 2000
A53: =IF($B$25="ไม่สามารถซื้อได้",$B$25,IF($C$5<=10,"",1000)) -> 1000 | C53: =IF($B$30="ไม่สามารถซื้อได้",$B$30,IF($C$5<11,"SMART","DIAMOND")) -> DIAMOND | D53: =IF($B$24="ไม่สามารถซื้อได้",$B$24,2200) -> 2200 | E53: PLS12 | F53: 3000
A54: =IF($B$25="ไม่สามารถซื้อได้",$B$25,IF($C$5<=15,"",2000)) -> 2000 | C54: =IF($B$30="ไม่สามารถซื้อได้",$B$30,IF($C$5<11,"","GOLD")) -> GOLD | D54: =IF($B$24="ไม่สามารถซื้อได้",$B$24,3200) -> 3200 | E54: PLS15 | F54: 4000
A55: =IF($B$25="ไม่สามารถซื้อได้",$B$25,IF($C$5<=15,"",3000)) -> 3000 | C55: =IF($B$30="ไม่สามารถซื้อได้",$B$30,IF($C$5<11,"","SILVER")) -> SILVER | D55: =IF($B$24="ไม่สามารถซื้อได้",$B$24,IF($C$5<=10,"",4200)) -> 4200 | F55: 5000
A56: =IF($B$25="ไม่สามารถซื้อได้",$B$25,IF($C$5<=15,"",4000)) -> 4000 | C56: =IF($B$30="ไม่สามารถซื้อได้",$B$30,IF($C$5<11,"","BRONZE")) -> BRONZE | D56: =IF($B$24="ไม่สามารถซื้อได้",$B$24,IF($C$5<=10,"",6200)) -> 6200 | F56: 6000
A57: =IF($B$25="ไม่สามารถซื้อได้",$B$25,IF($C$5<=15,"",5000)) -> 5000 | C57: =IF($B$30="ไม่สามารถซื้อได้",$B$30,IF($C$5<11,"","SMART")) -> SMART | D57: MEX Rule (Effective Jan'2022) | F57: 7000
A58: MEB Rule (Effective Jan'2022) | D58: 0-10 : 1200 2200 3200 | F58: 8000
A59: 6-10 : 500 | D59: 11 up : 1200 2200 3200 4200 6200 | F59: 9000
A60: 11-15 : 500 1000 | F60: 10000
A61: 16 up : 500 1000 2000 3000 4000 5000
G62: Expire of Sales proposal
D63: Effective Date | E63: 1 มกราคม 2569 ถึง 31 มีนาคม 2570 | G63: 46477
D64: version | E64: A2026-1 | G64: =IF(TODAY()>G63,"Expire","")
D65: ชื่อไทย | E65: ไอสมาร์ท 80/6 (ไม่มีเงินปันผล)
D66: งวดการชำระ | E66: รายปี | F66: รายปี | G66: 1
E67: ราย 6 เดือน | F67: ราย 6 เดือน | G67: 2
E68: ราย 3 เดือน | F68: รายเดือน | G68: 4
E69: รายเดือน | G69: 12
D70: ถ้าเบี้ยรวมเท่ากับศูนย์ หรือ เบี้ยรายเดือนน้อยกว่า 1,000 จะ = no | E70: =IF(OR(F37=0,AND(C7="รายเดือน",F37<1000)),"no","yes") -> yes
D73: ไลฟ์เรดดี้ (ไม่มีเงินปันผล)
D74: LifeReady (Non-Participating)
A77: Premium Payment Term | B77: Premium Payment Term | C77: Issue age Min | D77: Issue age Max | E77: Seq. | F77: Plan Code | G77: Payment Term | H77: Payment Year | I77: Plan Code SA<300,000 | J77: Plan Code SA>=300,000
A78: ชำระเบี้ย 6 ปี | B78: 6 Pay | C78: 25 | D78: 65 | E78: 1 | F78: W80F06 | G78: 6 ปี | H78: 6
H79: 12
H80: 18 | I80: W99FU18 | J80: W99FH18
H81: =99-$C$5 -> 55 | I81: W99FU99 | J81: W99FH99
H82: =99-$C$5 -> 55
H83: =99-$C$5 -> 55
A85: Product PB | B85: Issue Age Min | C85: Issue Age Max | D85: Payer Type | E85: Group | F85: RLS Plan Code | G85: Payor Age Min | H85: Payor Age Max | I85: Official Product Name TH | J85: Official Product Name EN | K85: Plancode (PIP & Commu)
A86: Payor Benefit Rider for Parent (Cover for Death and Total Permanent Disability) | B86: 0 | C86: 15 | D86: Parent | E86: PB Fit | F86: PBPDD | G86: 20 | H86: 70 | I86: สัญญาเพิ่มเติมพีบี ฟิต | J86: PB Fit Rider | K86: PBPDD
A87: Payor Benefit Rider for Parent (Cover for Death, Total Permanent Disability and Critical Illness | B87: 0 | C87: 15 | D87: Parent | E87: PB Beyond | F87: PBPDC | G87: 20 | H87: 70 | I87: สัญญาเพิ่มเติมพีบี บียอนด์ | J87: PB Beyond Rider | K87: PBPDDCI
A88: Payor Benefit Rider for Spouse (Cover for Death and Total Permanent Disability) | B88: 16 | C88: 70 | D88: Spouse | E88: PB Fit | F88: PBSDD | G88: 20 | H88: 70 | I88: สัญญาเพิ่มเติมพีบี ฟิต | J88: PB Fit Rider | K88: PBSDD
A89: Payor Benefit Rider for Spouse (Cover for Death, Total Permanent Disability and Critical Illness | B89: 16 | C89: 70 | D89: Spouse | E89: PB Beyond | F89: PBSDC | G89: 20 | H89: 70 | I89: สัญญาเพิ่มเติมพีบี บียอนด์ | J89: PB Beyond Rider | K89: PBSDDCI
A91: Product WP | B91: Plan code | C91: System Plan Code | D91: Payer Type | E91: Group | F91: System Plan Code | G91: Official Product Name TH | H91: Official Product Name EN | I91: Plancode (PIP & Commu)
A92: Waiver of Premium Rider (Total Permanent Disability) | B92: 16 | C92: 70 | D92: Insure | E92: WP Fit | F92: WPTPD | G92: สัญญาเพิ่มเติมดับบลิวพี ฟิต | H92: WP Fit Rider | I92: WPTPD
A93: Waiver of Premium Rider (Total Permanent Disability and Critical Illness) | B93: 16 | C93: 70 | D93: Insure | E93: WP Beyond | F93: WPTCI | G93: สัญญาเพิ่มเติมดับบลิวพี บียอนด์ | H93: WP Beyond Rider | I93: WPTPDCI

Sheet ตารางแสดงผลประโยชน์
A1: =กรอกข้อมูล!G64 | M1: di
D2: =IF(A1="Expire",กรอกข้อมูล!$A$1,"ตารางแสดงผลประโยชน์แบบ "&กรอกข้อมูล!E65) -> ตารางแสดงผลประโยชน์แบบ ไอสมาร์ท 80/6 (ไม่มีเงินปันผล)
C5: ="ลูกค้าคนพิเศษ "&กรอกข้อมูล!$C$4&" " -> ลูกค้าคนพิเศษ คุณคนพิเศษ | F5: ="เพศ "&กรอกข้อมูล!$C$6&" อายุ "&กรอกข้อมูล!$C$5&" ปี"&" " -> เพศ หญิง อายุ 44 ปี | I5: ="ระยะเวลาชำระเบี้ยประกันภัย "&กรอกข้อมูล!$J$14 -> ระยะเวลาชำระเบี้ยประกันภัย 6 ปี | M5: check select plan Basic | N5: =กรอกข้อมูล!J22 -> Yes
C6: ="จำนวนเงินเอาประกันภัย "&TEXT(กรอกข้อมูล!$C$40,"0,000")&" บาท " -> จำนวนเงินเอาประกันภัย 1,000,000 บาท | F6: ="เบี้ยประกันภัยหลักงวดแรก ("&กรอกข้อมูล!$C$7&")"&" "&TEXT(กรอกข้อมูล!F19,"#,#00.00")&" บาท "&"" -> เบี้ยประกันภัยหลักงวดแรก (รายปี) 287,000.00 บาท | I6: ระยะเวลาคุ้มครอง ครบอายุ 80 ปี | M6: Gender | N6: =IF(กรอกข้อมูล!$C$6="ชาย","Male",IF(กรอกข้อมูล!$C$6="หญิง","Female","")) -> Female | O6: =LEFT(N6,1) -> F
M7: Issue Age | N7: =กรอกข้อมูล!$C$5 -> 44
B8: ="ตัวอย่าง ตารางแสดงผลประโยชน์ที่ได้รับจากแบบประกัน "&กรอกข้อมูล!E65 -> ตัวอย่าง ตารางแสดงผลประโยชน์ที่ได้รับจากแบบประกัน ไอสมาร์ท 80/6 (ไม่มีเงินปันผล) | M8: SA | N8: =กรอกข้อมูล!$C$40 -> 1000000
B9: ="จำนวนเงินเอาประกันภัย "&TEXT(กรอกข้อมูล!C40,"0,000")&" บาท สำหรับผู้ขอเอาประกันภัย เพศ "&กรอกข้อมูล!C6&" อายุ "&กรอกข้อมูล!C5&" ปี" -> จำนวนเงินเอาประกันภัย 1,000,000 บาท สำหรับผู้ขอเอาประกันภัย เพศ หญิง อายุ 44 ปี | M9: Payment Year | N9: =กรอกข้อมูล!K14 -> 6
B11: อายุ | C11: ปี กรมธรรม์ ที่ | D11: เบี้ยประกันภัยสัญญาหลัก | F11: เงินจ่ายคืนตามกรมธรรม์ประกันภัย และเงินครบกำหนดสัญญา (ณ สิ้นปีกรมธรรม์) | H11: ความคุ้มครอง กรณีเสียชีวิต | I11: ผลประโยชน์กรณีเสียชีวิตรวมเงินจ่ายคืนระหว่างสัญญาที่จ่ายไปแล้ว | J11: เงินค่าเวนคืน กรมธรรม์ประกันภัย (ณ สิ้นปีกรมธรรม์) | M11: Plancode | N11: =Cal!B13 -> 06F | O11: =+N11&N7 -> 06F44
D12: ต่อปี | E12: สะสม | F12: กรณีรับเงินจ่ายคืน | G12: กรณีสะสมไว้กับบริษัทฯ ด้วยอัตราดอกเบี้ยขั้นต่ำ 0.5% ต่อปี | M12: มูลค่าเวนคืน กรมธรรม์ของสัญญาหลัก | N12: Coupon rate | O12: Max(200%SA,101%Acc Prem,CV
Q13: =IF(กรอกข้อมูล!$A$19="i-Protect05",#REF!,IF(กรอกข้อมูล!$A$19="i-Protect10",#REF!,IF(กรอกข้อมูล!$A$19="i-Protect85",#REF!))) -> FALSE
B14: =กรอกข้อมูล!$C$5 -> 44 | C14: 1 | D14: =IF(กรอกข้อมูล!$E$70="no",0,IF(B14="","",IF(C14<=$N$9,กรอกข้อมูล!$I$19,0))) -> 287000 | E14: =D14 -> 287000 | F14: =(IF(C14="","",IF(N14=2,ROUND(MAX(101%*E14,2*$N$8,H14),0),ROUND($N$8*N14,0)))) -> 10000 | G14: =F14 -> 10000 | H14: =IF(C14="","",MAX(2*$N$8,101%*E14,J14)) -> 2000000 | I14: =H14 -> 2000000 | J14: =IF(D14="","",IF($N$5<>"Yes",0,ROUND((M14*$N$8)/1000,0))) -> 45000 | M14: =IF(B14="","",IF($O$6="M",VLOOKUP($O$11,'TABCV(Male)'!$A$2:$CZ$431,ตารางแสดงผลประโยชน์!C14+4,FALSE),IF($O$6="F",VLOOKUP($O$11,'TABCV(Female)'!$A$2:$CZ$431,ตารางแสดงผลประโยชน์!C14+4,FALSE)))) -> 45 | N14: =IF(C14<=5,0.01,IF(AND(C14>5,B14<79),0.02,IF(B14=79,2,""))) -> 0.01
B15: =IF(B14="","",IF(กรอกข้อมูล!$C$5+C14>79,"",กรอกข้อมูล!$C$5+C14)) -> 45 | C15: =IF(B15="","",C14+1) -> 2 | D15: =IF(กรอกข้อมูล!$E$70="no",0,IF(B15="","",IF(C15<=$N$9,กรอกข้อมูล!$I$19,0))) -> 287000 | E15: =IF(C15="","",E14+D15) -> 574000 | F15: =(IF(C15="","",IF(N15=2,ROUND(MAX(101%*E15,2*$N$8,H15),0),ROUND($N$8*N15,0)))) -> 10000 | G15: =IF(C15="","",IF(F15=0,0,F15+(1+0.5%)*G14)) -> 20050 | H15: =IF(C15="","",MAX(2*$N$8,101%*E15,J15)) -> 2000000 | I15: =IF(C15="","",SUM($F$14:F14,H15)) -> 2010000 | J15: =IF(D15="","",IF($N$5<>"Yes",0,ROUND((M15*$N$8)/1000,0))) -> 182000 | M15: =IF(B15="","",IF($O$6="M",VLOOKUP($O$11,'TABCV(Male)'!$A$2:$CZ$431,ตารางแสดงผลประโยชน์!C15+4,FALSE),IF($O$6="F",VLOOKUP($O$11,'TABCV(Female)'!$A$2:$CZ$431,ตารางแสดงผลประโยชน์!C15+4,FALSE)))) -> 182 | N15: =IF(C15<=5,0.01,IF(AND(C15>5,B15<79),0.02,IF(B15=79,2,""))) -> 0.01
B16: =IF(B15="","",IF(กรอกข้อมูล!$C$5+C15>79,"",กรอกข้อมูล!$C$5+C15)) -> 46 | C16: =IF(B16="","",C15+1) -> 3 | D16: =IF(กรอกข้อมูล!$E$70="no",0,IF(B16="","",IF(C16<=$N$9,กรอกข้อมูล!$I$19,0))) -> 287000 | E16: =IF(C16="","",E15+D16) -> 861000 | F16: =(IF(C16="","",IF(N16=2,ROUND(MAX(101%*E16,2*$N$8,H16),0),ROUND($N$8*N16,0)))) -> 10000 | G16: =IF(C16="","",IF(F16=0,0,F16+(1+0.5%)*G15)) -> 30150.25 | H16: =IF(C16="","",MAX(2*$N$8,101%*E16,J16)) -> 2000000 | I16: =IF(C16="","",SUM($F$14:F15,H16)) -> 2020000 | J16: =IF(D16="","",IF($N$5<>"Yes",0,ROUND((M16*$N$8)/1000,0))) -> 467000 | M16: =IF(B16="","",IF($O$6="M",VLOOKUP($O$11,'TABCV(Male)'!$A$2:$CZ$431,ตารางแสดงผลประโยชน์!C16+4,FALSE),IF($O$6="F",VLOOKUP($O$11,'TABCV(Female)'!$A$2:$CZ$431,ตารางแสดงผลประโยชน์!C16+4,FALSE)))) -> 467 | N16: =IF(C16<=5,0.01,IF(AND(C16>5,B16<79),0.02,IF(B16=79,2,""))) -> 0.01
B17: =IF(B16="","",IF(กรอกข้อมูล!$C$5+C16>79,"",กรอกข้อมูล!$C$5+C16)) -> 47 | C17: =IF(B17="","",C16+1) -> 4 | D17: =IF(กรอกข้อมูล!$E$70="no",0,IF(B17="","",IF(C17<=$N$9,กรอกข้อมูล!$I$19,0))) -> 287000 | E17: =IF(C17="","",E16+D17) -> 1148000 | F17: =(IF(C17="","",IF(N17=2,ROUND(MAX(101%*E17,2*$N$8,H17),0),ROUND($N$8*N17,0)))) -> 10000 | G17: =IF(C17="","",IF(F17=0,0,F17+(1+0.5%)*G16)) -> 40301.001 | H17: =IF(C17="","",MAX(2*$N$8,101%*E17,J17)) -> 2000000 | I17: =IF(C17="","",SUM($F$14:F16,H17)) -> 2030000 | J17: =IF(D17="","",IF($N$5<>"Yes",0,ROUND((M17*$N$8)/1000,0))) -> 729000 | M17: =IF(B17="","",IF($O$6="M",VLOOKUP($O$11,'TABCV(Male)'!$A$2:$CZ$431,ตารางแสดงผลประโยชน์!C17+4,FALSE),IF($O$6="F",VLOOKUP($O$11,'TABCV(Female)'!$A$2:$CZ$431,ตารางแสดงผลประโยชน์!C17+4,FALSE)))) -> 729 | N17: =IF(C17<=5,0.01,IF(AND(C17>5,B17<79),0.02,IF(B17=79,2,""))) -> 0.01
B18: =IF(B17="","",IF(กรอกข้อมูล!$C$5+C17>79,"",กรอกข้อมูล!$C$5+C17)) -> 48 | C18: =IF(B18="","",C17+1) -> 5 | D18: =IF(กรอกข้อมูล!$E$70="no",0,IF(B18="","",IF(C18<=$N$9,กรอกข้อมูล!$I$19,0))) -> 287000 | E18: =IF(C18="","",E17+D18) -> 1435000 | F18: =(IF(C18="","",IF(N18=2,ROUND(MAX(101%*E18,2*$N$8,H18),0),ROUND($N$8*N18,0)))) -> 10000 | G18: =IF(C18="","",IF(F18=0,0,F18+(1+0.5%)*G17)) -> 50502.506 | H18: =IF(C18="","",MAX(2*$N$8,101%*E18,J18)) -> 2000000 | I18: =IF(C18="","",SUM($F$14:F17,H18)) -> 2040000 | J18: =IF(D18="","",IF($N$5<>"Yes",0,ROUND((M18*$N$8)/1000,0))) -> 1043000 | M18: =IF(B18="","",IF($O$6="M",VLOOKUP($O$11,'TABCV(Male)'!$A$2:$CZ$431,ตารางแสดงผลประโยชน์!C18+4,FALSE),IF($O$6="F",VLOOKUP($O$11,'TABCV(Female)'!$A$2:$CZ$431,ตารางแสดงผลประโยชน์!C18+4,FALSE)))) -> 1043 | N18: =IF(C18<=5,0.01,IF(AND(C18>5,B18<79),0.02,IF(B18=79,2,""))) -> 0.01
B19: =IF(B18="","",IF(กรอกข้อมูล!$C$5+C18>79,"",กรอกข้อมูล!$C$5+C18)) -> 49 | C19: =IF(B19="","",C18+1) -> 6 | D19: =IF(กรอกข้อมูล!$E$70="no",0,IF(B19="","",IF(C19<=$N$9,กรอกข้อมูล!$I$19,0))) -> 287000 | E19: =IF(C19="","",E18+D19) -> 1722000 | F19: =(IF(C19="","",IF(N19=2,ROUND(MAX(101%*E19,2*$N$8,H19),0),ROUND($N$8*N19,0)))) -> 20000 | G19: =IF(C19="","",IF(F19=0,0,F19+(1+0.5%)*G18)) -> 70755.019 | H19: =IF(C19="","",MAX(2*$N$8,101%*E19,J19)) -> 2000000 | I19: =IF(C19="","",SUM($F$14:F18,H19)) -> 2050000 | J19: =IF(D19="","",IF($N$5<>"Yes",0,ROUND((M19*$N$8)/1000,0))) -> 1273000 | M19: =IF(B19="","",IF($O$6="M",VLOOKUP($O$11,'TABCV(Male)'!$A$2:$CZ$431,ตารางแสดงผลประโยชน์!C19+4,FALSE),IF($O$6="F",VLOOKUP($O$11,'TABCV(Female)'!$A$2:$CZ$431,ตารางแสดงผลประโยชน์!C19+4,FALSE)))) -> 1273 | N19: =IF(C19<=5,0.01,IF(AND(C19>5,B19<79),0.02,IF(B19=79,2,""))) -> 0.02
B20: =IF(B19="","",IF(กรอกข้อมูล!$C$5+C19>79,"",กรอกข้อมูล!$C$5+C19)) -> 50 | C20: =IF(B20="","",C19+1) -> 7 | D20: =IF(กรอกข้อมูล!$E$70="no",0,IF(B20="","",IF(C20<=$N$9,กรอกข้อมูล!$I$19,0))) -> 0 | E20: =IF(C20="","",E19+D20) -> 1722000 | F20: =(IF(C20="","",IF(N20=2,ROUND(MAX(101%*E20,2*$N$8,H20),0),ROUND($N$8*N20,0)))) -> 20000 | G20: =IF(C20="","",IF(F20=0,0,F20+(1+0.5%)*G19)) -> 91108.794 | H20: =IF(C20="","",MAX(2*$N$8,101%*E20,J20)) -> 2000000 | I20: =IF(C20="","",SUM($F$14:F19,H20)) -> 2070000 | J20: =IF(D20="","",IF($N$5<>"Yes",0,ROUND((M20*$N$8)/1000,0))) -> 1290000 | M20: =IF(B20="","",IF($O$6="M",VLOOKUP($O$11,'TABCV(Male)'!$A$2:$CZ$431,ตารางแสดงผลประโยชน์!C20+4,FALSE),IF($O$6="F",VLOOKUP($O$11,'TABCV(Female)'!$A$2:$CZ$431,ตารางแสดงผลประโยชน์!C20+4,FALSE)))) -> 1290 | N20: =IF(C20<=5,0.01,IF(AND(C20>5,B20<79),0.02,IF(B20=79,2,""))) -> 0.02
B21: =IF(B20="","",IF(กรอกข้อมูล!$C$5+C20>79,"",กรอกข้อมูล!$C$5+C20)) -> 51 | C21: =IF(B21="","",C20+1) -> 8 | D21: =IF(กรอกข้อมูล!$E$70="no",0,IF(B21="","",IF(C21<=$N$9,กรอกข้อมูล!$I$19,0))) -> 0 | E21: =IF(C21="","",E20+D21) -> 1722000 | F21: =(IF(C21="","",IF(N21=2,ROUND(MAX(101%*E21,2*$N$8,H21),0),ROUND($N$8*N21,0)))) -> 20000 | G21: =IF(C21="","",IF(F21=0,0,F21+(1+0.5%)*G20)) -> 111564.34 | H21: =IF(C21="","",MAX(2*$N$8,101%*E21,J21)) -> 2000000 | I21: =IF(C21="","",SUM($F$14:F20,H21)) -> 2090000 | J21: =IF(D21="","",IF($N$5<>"Yes",0,ROUND((M21*$N$8)/1000,0))) -> 1307000 | M21: =IF(B21="","",IF($O$6="M",VLOOKUP($O$11,'TABCV(Male)'!$A$2:$CZ$431,ตารางแสดงผลประโยชน์!C21+4,FALSE),IF($O$6="F",VLOOKUP($O$11,'TABCV(Female)'!$A$2:$CZ$431,ตารางแสดงผลประโยชน์!C21+4,FALSE)))) -> 1307 | N21: =IF(C21<=5,0.01,IF(AND(C21>5,B21<79),0.02,IF(B21=79,2,""))) -> 0.02
B22: =IF(B21="","",IF(กรอกข้อมูล!$C$5+C21>79,"",กรอกข้อมูล!$C$5+C21)) -> 52 | C22: =IF(B22="","",C21+1) -> 9 | D22: =IF(กรอกข้อมูล!$E$70="no",0,IF(B22="","",IF(C22<=$N$9,กรอกข้อมูล!$I$19,0))) -> 0 | E22: =IF(C22="","",E21+D22) -> 1722000 | F22: =(IF(C22="","",IF(N22=2,ROUND(MAX(101%*E22,2*$N$8,H22),0),ROUND($N$8*N22,0)))) -> 20000 | G22: =IF(C22="","",IF(F22=0,0,F22+(1+0.5%)*G21)) -> 132122.16 | H22: =IF(C22="","",MAX(2*$N$8,101%*E22,J22)) -> 2000000 | I22: =IF(C22="","",SUM($F$14:F21,H22)) -> 2110000 | J22: =IF(D22="","",IF($N$5<>"Yes",0,ROUND((M22*$N$8)/1000,0))) -> 1324000 | M22: =IF(B22="","",IF($O$6="M",VLOOKUP($O$11,'TABCV(Male)'!$A$2:$CZ$431,ตารางแสดงผลประโยชน์!C22+4,FALSE),IF($O$6="F",VLOOKUP($O$11,'TABCV(Female)'!$A$2:$CZ$431,ตารางแสดงผลประโยชน์!C22+4,FALSE)))) -> 1324 | N22: =IF(C22<=5,0.01,IF(AND(C22>5,B22<79),0.02,IF(B22=79,2,""))) -> 0.02
B23: =IF(B22="","",IF(กรอกข้อมูล!$C$5+C22>79,"",กรอกข้อมูล!$C$5+C22)) -> 53 | C23: =IF(B23="","",C22+1) -> 10 | D23: =IF(กรอกข้อมูล!$E$70="no",0,IF(B23="","",IF(C23<=$N$9,กรอกข้อมูล!$I$19,0))) -> 0 | E23: =IF(C23="","",E22+D23) -> 1722000 | F23: =(IF(C23="","",IF(N23=2,ROUND(MAX(101%*E23,2*$N$8,H23),0),ROUND($N$8*N23,0)))) -> 20000 | G23: =IF(C23="","",IF(F23=0,0,F23+(1+0.5%)*G22)) -> 152782.77 | H23: =IF(C23="","",MAX(2*$N$8,101%*E23,J23)) -> 2000000 | I23: =IF(C23="","",SUM($F$14:F22,H23)) -> 2130000 | J23: =IF(D23="","",IF($N$5<>"Yes",0,ROUND((M23*$N$8)/1000,0))) -> 1342000 | M23: =IF(B23="","",IF($O$6="M",VLOOKUP($O$11,'TABCV(Male)'!$A$2:$CZ$431,ตารางแสดงผลประโยชน์!C23+4,FALSE),IF($O$6="F",VLOOKUP($O$11,'TABCV(Female)'!$A$2:$CZ$431,ตารางแสดงผลประโยชน์!C23+4,FALSE)))) -> 1342 | N23: =IF(C23<=5,0.01,IF(AND(C23>5,B23<79),0.02,IF(B23=79,2,""))) -> 0.02
B24: =IF(B23="","",IF(กรอกข้อมูล!$C$5+C23>79,"",กรอกข้อมูล!$C$5+C23)) -> 54 | C24: =IF(B24="","",C23+1) -> 11 | D24: =IF(กรอกข้อมูล!$E$70="no",0,IF(B24="","",IF(C24<=$N$9,กรอกข้อมูล!$I$19,0))) -> 0 | E24: =IF(C24="","",E23+D24) -> 1722000 | F24: =(IF(C24="","",IF(N24=2,ROUND(MAX(101%*E24,2*$N$8,H24),0),ROUND($N$8*N24,0)))) -> 20000 | G24: =IF(C24="","",IF(F24=0,0,F24+(1+0.5%)*G23)) -> 173546.68 | H24: =IF(C24="","",MAX(2*$N$8,101%*E24,J24)) -> 2000000 | I24: =IF(C24="","",SUM($F$14:F23,H24)) -> 2150000 | J24: =IF(D24="","",IF($N$5<>"Yes",0,ROUND((M24*$N$8)/1000,0))) -> 1360000 | M24: =IF(B24="","",IF($O$6="M",VLOOKUP($O$11,'TABCV(Male)'!$A$2:$CZ$431,ตารางแสดงผลประโยชน์!C24+4,FALSE),IF($O$6="F",VLOOKUP($O$11,'TABCV(Female)'!$A$2:$CZ$431,ตารางแสดงผลประโยชน์!C24+4,FALSE)))) -> 1360 | N24: =IF(C24<=5,0.01,IF(AND(C24>5,B24<79),0.02,IF(B24=79,2,""))) -> 0.02
B25: =IF(B24="","",IF(กรอกข้อมูล!$C$5+C24>79,"",กรอกข้อมูล!$C$5+C24)) -> 55 | C25: =IF(B25="","",C24+1) -> 12 | D25: =IF(กรอกข้อมูล!$E$70="no",0,IF(B25="","",IF(C25<=$N$9,กรอกข้อมูล!$I$19,0))) -> 0 | E25: =IF(C25="","",E24+D25) -> 1722000 | F25: =(IF(C25="","",IF(N25=2,ROUND(MAX(101%*E25,2*$N$8,H25),0),ROUND($N$8*N25,0)))) -> 20000 | G25: =IF(C25="","",IF(F25=0,0,F25+(1+0.5%)*G24)) -> 194414.42 | H25: =IF(C25="","",MAX(2*$N$8,101%*E25,J25)) -> 2000000 | I25: =IF(C25="","",SUM($F$14:F24,H25)) -> 2170000 | J25: =IF(D25="","",IF($N$5<>"Yes",0,ROUND((M25*$N$8)/1000,0))) -> 1379000 | M25: =IF(B25="","",IF($O$6="M",VLOOKUP($O$11,'TABCV(Male)'!$A$2:$CZ$431,ตารางแสดงผลประโยชน์!C25+4,FALSE),IF($O$6="F",VLOOKUP($O$11,'TABCV(Female)'!$A$2:$CZ$431,ตารางแสดงผลประโยชน์!C25+4,FALSE)))) -> 1379 | N25: =IF(C25<=5,0.01,IF(AND(C25>5,B25<79),0.02,IF(B25=79,2,""))) -> 0.02
B26: =IF(B25="","",IF(กรอกข้อมูล!$C$5+C25>79,"",กรอกข้อมูล!$C$5+C25)) -> 56 | C26: =IF(B26="","",C25+1) -> 13 | D26: =IF(กรอกข้อมูล!$E$70="no",0,IF(B26="","",IF(C26<=$N$9,กรอกข้อมูล!$I$19,0))) -> 0 | E26: =IF(C26="","",E25+D26) -> 1722000 | F26: =(IF(C26="","",IF(N26=2,ROUND(MAX(101%*E26,2*$N$8,H26),0),ROUND($N$8*N26,0)))) -> 20000 | G26: =IF(C26="","",IF(F26=0,0,F26+(1+0.5%)*G25)) -> 215386.49 | H26: =IF(C26="","",MAX(2*$N$8,101%*E26,J26)) -> 2000000 | I26: =IF(C26="","",SUM($F$14:F25,H26)) -> 2190000 | J26: =IF(D26="","",IF($N$5<>"Yes",0,ROUND((M26*$N$8)/1000,0))) -> 1398000 | M26: =IF(B26="","",IF($O$6="M",VLOOKUP($O$11,'TABCV(Male)'!$A$2:$CZ$431,ตารางแสดงผลประโยชน์!C26+4,FALSE),IF($O$6="F",VLOOKUP($O$11,'TABCV(Female)'!$A$2:$CZ$431,ตารางแสดงผลประโยชน์!C26+4,FALSE)))) -> 1398 | N26: =IF(C26<=5,0.01,IF(AND(C26>5,B26<79),0.02,IF(B26=79,2,""))) -> 0.02
... B68: =IF(B67="","",IF(กรอกข้อมูล!$C$5+C67>79,"",กรอกข้อมูล!$C$5+C67)) | C68: =IF(B68="","",C67+1) | D68: =IF(กรอกข้อมูล!$E$70="no",0,IF(B68="","",IF(C68<=$N$9,กรอกข้อมูล!$I$19,0))) | E68: =IF(C68="","",E67+D68) | F68: =(IF(C68="","",IF(N68=2,ROUND(MAX(101%*E68,2*$N$8,H68),0),ROUND($N$8*N68,0)))) | G68: =IF(C68="","",IF(F68=0,0,F68+(1+0.5%)*G67)) | H68: =IF(C68="","",MAX(2*$N$8,101%*E68,J68)) | I68: =IF(C68="","",SUM($F$14:F67,H68)) | J68: =IF(D68="","",IF($N$5<>"Yes",0,ROUND((M68*$N$8)/1000,0))) | M68: =IF(B68="","",IF($O$6="M",VLOOKUP($O$11,'TABCV(Male)'!$A$2:$CZ$431,ตารางแสดงผลประโยชน์!C68+4,FALSE),IF($O$6="F",VLOOKUP($O$11,'TABCV(Female)'!$A$2:$CZ$431,ตารางแสดงผลประโยชน์!C68+4,FALSE)))) | N68: =IF(C68<=5,0.01,IF(AND(C68>5,B68<79),0.02,IF(B68=79,2,"")))
D69: รวมเงินจ่ายคืนและเงินครบกำหนดสัญญา ทั้งสิ้น | F69: =SUM($F$14:$F$68) -> 2650000 | G69: =MAX($G$14:$G$68) -> 2707775.2
B71: หมายเหตุ : | D71: 1. เงินค่าเวนคืนกรมธรรม์ประกันภัยข้างต้นเป็นจำนวนเงินก่อนหักหนี้สินใดๆ
D72: 2. เงินค่าเวนคืนกรมธรรม์ประกันภัยที่แสดงไว้ในตารางเป็นจำนวนเงินที่หักเงินจ่ายคืน (ถ้ามี) ออกแล้ว
D73: 3. กรณีเสียชีวิต บริษัทจะจ่ายร้อยละ 200 ของจำนวนเงินเอาประกันภัย หรือเงินค่าเวนคืนกรมธรรม์ประกันภัย
D74: หรือร้อยละ 101 ของเบี้ยประกันภัยของกรมธรรม์หลักที่ชำระมาแล้วทั้งหมด แล้วแต่จำนวนใดจะมากกว่า
B75: เอกสารประกอบการเสนอขายนี้เป็นข้อมูลเบื้องต้นของแบบประกันภัย ผลประโยชน์ ความคุ้มครองและข้อยกเว้น เป็นไปตามที่กำหนดในกรมธรรม์ ผู้ซื้อควรทำความเข้าใจรายละเอียด ความคุ้มครองและเงื่อนไขก่อนตัดสินใจทำประกันภัยทุกครั้ง
B76: ="โปรแกรมใบข้อเสนอนี้ใช้สำหรับแบบประกัน "&กรอกข้อมูล!E65&" ที่เสนอขายตั้งแต่ "&กรอกข้อมูล!E63&" หรือตามประกาศยกเลิกการใช้จากบริษัทฯ (แล้วแต่ระยะเวลาใดจะเกิดขึ้นก่อน)" -> โปรแกรมใบข้อเสนอนี้ใช้สำหรับแบบประกัน ไอสมาร์ท 80/6 (ไม่มีเงินปันผล) ที่เสนอขายตั้งแต่ 1 มกราคม 2569 ถึง 31 มีนาคม 2570 หรือตามประกาศยกเลิกการใช้จากบริษัทฯ (แล้วแต่ระยะเวลาใดจะเกิดขึ้นก่อน)
I77: =กรอกข้อมูล!E65&" เวอร์ชั่น "&กรอกข้อมูล!E64 -> ไอสมาร์ท 80/6 (ไม่มีเงินปันผล) เวอร์ชั่น A2026-1

Sheet ตารางมูลค่า
A1: =กรอกข้อมูล!G64
D2: =IF(A1="Expire",กรอกข้อมูล!$A$1,"ตารางมูลค่ากรมธรรม์ประกันภัยแบบ "&กรอกข้อมูล!E65) -> ตารางมูลค่ากรมธรรม์ประกันภัยแบบ ไอสมาร์ท 80/6 (ไม่มีเงินปันผล)
C5: ="ลูกค้าคนพิเศษ "&กรอกข้อมูล!$C$4&" " -> ลูกค้าคนพิเศษ คุณคนพิเศษ | H5: ="เพศ "&กรอกข้อมูล!$C$6&" อายุ "&กรอกข้อมูล!$C$5&" ปี"&" " -> เพศ หญิง อายุ 44 ปี | N5: ="ระยะเวลาชำระเบี้ยประกันภัย "&กรอกข้อมูล!$J$14 -> ระยะเวลาชำระเบี้ยประกันภัย 6 ปี | U5: check select plan Basic | V5: =กรอกข้อมูล!J22 -> Yes
C6: ="จำนวนเงินเอาประกันภัย "&TEXT(กรอกข้อมูล!$C$40,"0,000")&" บาท " -> จำนวนเงินเอาประกันภัย 1,000,000 บาท | H6: ="เบี้ยประกันภัยหลักงวดแรก ("&กรอกข้อมูล!$C$7&")"&" "&TEXT(กรอกข้อมูล!F19,"#,#00.00")&" บาท "&"" -> เบี้ยประกันภัยหลักงวดแรก (รายปี) 287,000.00 บาท | N6: ระยะเวลาคุ้มครอง ครบอายุ 80 ปี | U6: Gender | V6: =IF(กรอกข้อมูล!$C$6="ชาย","Male",IF(กรอกข้อมูล!$C$6="หญิง","Female","")) -> Female | W6: =LEFT(V6,1) -> F
U7: Issue Age | V7: =กรอกข้อมูล!$C$5 -> 44
B8: ="ตัวอย่าง ตารางมูลค่ากรมธรรม์ประกันภัยแบบ "&กรอกข้อมูล!E65 -> ตัวอย่าง ตารางมูลค่ากรมธรรม์ประกันภัยแบบ ไอสมาร์ท 80/6 (ไม่มีเงินปันผล) | U8: SA | V8: =กรอกข้อมูล!$C$40 -> 1000000
B9: ="จำนวนเงินเอาประกันภัย "&TEXT(กรอกข้อมูล!C40,"0,000")&" บาท สำหรับผู้ขอเอาประกันภัย เพศ "&กรอกข้อมูล!C6&" อายุ "&กรอกข้อมูล!C5&" ปี" -> จำนวนเงินเอาประกันภัย 1,000,000 บาท สำหรับผู้ขอเอาประกันภัย เพศ หญิง อายุ 44 ปี | U9: Payment Year | V9: =กรอกข้อมูล!K14 -> 6 | W9: =+V11&V7 -> 06F44 | AA9: Plan | AB9: CVPLAN | AC9: =กรอกข้อมูล!A19 -> ไอสมาร์ท 80/6 (W80F06)
AA10: Sex | AB10: CVSEX | AC10: =W6 -> F
G11: อายุ | H11: สิ้นปี กรมธรรม์ ที่ | I11: กรมธรรม์ใช้เงินสำเร็จ | K11: กรมธรรม์แบบขยายเวลา | U11: Plancode | V11: =Cal!B13 -> 06F | W11: กรมธรรม์แบบขยายเวลา | AA11: Age | AB11: CVAGE | AC11: =V7 -> 44
I12: เงินจ่ายคืนทันที | J12: มูลค่าใช้เงินสำเร็จ | K12: ระยะเวลาที่ขยาย | M12: เงินจ่ายคืนทันที | N12: เงินครบกำหนด | U12: RPU | W12: ระยะเวลาที่ขยาย | Y12: จำนวนเงินจ่ายคืนทันที | Z12: เงินครบกำหนด | AA12: Key | AC12: =AC9&AC10&AC11 -> ไอสมาร์ท 80/6 (W80F06)F44
K13: ปี | L13: วัน | U13: เงินจ่ายคืนทันที | V13: มูลค่าใช้เงินสำเร็จ | W13: ปี | X13: วัน | AA13: RPU Year 0 | AB13: PVL00 | AC13: =IFERROR(IF($W$6="M",VLOOKUP($W$9,'TABCV(Male)'!$A$2:$QQ$431,H13+105,FALSE),VLOOKUP($W$9,'TABCV(Female)'!$A$2:$QQ$431,H13+105,FALSE)),0) -> 0 | AE13: ETI Year 0 | AF13: ETA00 | AG13: =IFERROR(IF($W$6="M",VLOOKUP($W$9,'TABCV(Male)'!$A$2:$QQ$431,H13+206,FALSE),VLOOKUP($W$9,'TABCV(Female)'!$A$2:$QQ$431,H13+206,FALSE)),0) -> 0 | AI13: PEN Year 0 | AJ13: PEN00 | AK13: =IFERROR(IF($W$6="M",VLOOKUP($W$9,'TABCV(Male)'!$A$2:$QQ$431,H13+307,FALSE),VLOOKUP($W$9,'TABCV(Female)'!$A$2:$QQ$431,H13+307,FALSE)),0) -> 0
G14: =กรอกข้อมูล!$C$5 -> 44 | H14: 1 | I14: =IF(H14="","",(U14*$V$8)/1000) -> 0 | J14: =IF(H14="","",(V14*$V$8)/1000) -> 112000 | K14: =IF(H14="","",IF(W14="","-",W14)) -> 15 | L14: =IF(I14="","",IF(X14=0,"-",X14)) -> 219 | M14: =IF(H14="","",(Y14*$V$8)/1000) -> 0 | N14: =IF(H14="","",(Z14*$V$8)/1000) -> 0 | U14: =IF(AC14-1000<0,0,AC14-1000) -> 0 | V14: =IF(AC14=0,0,IF(AC14>1000,1000,AC14)) -> 112 | W14: =IF(AG14=0,0,IF(LEN(AG14)<4,0,LEFT(AG14,(LEN(AG14)-3)))) -> 15 | X14: =IF(AG14=0,0,RIGHT(AG14,3)+0) -> 219 | Y14: =IF(AK14-1000<0,0,AK14-1000) -> 0 | Z14: =IF(AK14=0,0,IF(AK14>1000,1000,AK14)) -> 0 | AA14: RPU Year 1 | AB14: PVL01 | AC14: =IFERROR(IF($W$6="M",VLOOKUP($W$9,'TABCV(Male)'!$A$2:$QQ$431,H14+105,FALSE),VLOOKUP($W$9,'TABCV(Female)'!$A$2:$QQ$431,H14+105,FALSE)),0) -> 112 | AE14: ETI Year 1 | AF14: ETA01 | AG14: =IFERROR(IF($W$6="M",VLOOKUP($W$9,'TABCV(Male)'!$A$2:$QQ$431,H14+206,FALSE),VLOOKUP($W$9,'TABCV(Female)'!$A$2:$QQ$431,H14+206,FALSE)),0) -> 15219 | AI14: PEN Year 1 | AJ14: PEN01 | AK14: =IFERROR(IF($W$6="M",VLOOKUP($W$9,'TABCV(Male)'!$A$2:$QQ$431,H14+307,FALSE),VLOOKUP($W$9,'TABCV(Female)'!$A$2:$QQ$431,H14+307,FALSE)),0) -> 0
G15: =IF(G14="","",IF(กรอกข้อมูล!$C$5+H14>79,"",กรอกข้อมูล!$C$5+H14)) -> 45 | H15: =IF(G15="","",H14+1) -> 2 | I15: =IF(H15="","",(U15*$V$8)/1000) -> 0 | J15: =IF(H15="","",(V15*$V$8)/1000) -> 440000 | K15: =IF(H15="","",IF(W15="","-",W15)) -> 29 | L15: =IF(I15="","",IF(X15=0,"-",X15)) -> 235 | M15: =IF(H15="","",(Y15*$V$8)/1000) -> 0 | N15: =IF(H15="","",(Z15*$V$8)/1000) -> 0 | U15: =IF(AC15-1000<0,0,AC15-1000) -> 0 | V15: =IF(AC15=0,0,IF(AC15>1000,1000,AC15)) -> 440 | W15: =IF(AG15=0,0,IF(LEN(AG15)<4,0,LEFT(AG15,(LEN(AG15)-3)))) -> 29 | X15: =IF(AG15=0,0,RIGHT(AG15,3)+0) -> 235 | Y15: =IF(AK15-1000<0,0,AK15-1000) -> 0 | Z15: =IF(AK15=0,0,IF(AK15>1000,1000,AK15)) -> 0 | AA15: RPU Year 2 | AB15: PVL02 | AC15: =IFERROR(IF($W$6="M",VLOOKUP($W$9,'TABCV(Male)'!$A$2:$QQ$431,H15+105,FALSE),VLOOKUP($W$9,'TABCV(Female)'!$A$2:$QQ$431,H15+105,FALSE)),0) -> 440 | AE15: ETI Year 2 | AF15: ETA02 | AG15: =IFERROR(IF($W$6="M",VLOOKUP($W$9,'TABCV(Male)'!$A$2:$QQ$431,H15+206,FALSE),VLOOKUP($W$9,'TABCV(Female)'!$A$2:$QQ$431,H15+206,FALSE)),0) -> 29235 | AI15: PEN Year 2 | AJ15: PEN02 | AK15: =IFERROR(IF($W$6="M",VLOOKUP($W$9,'TABCV(Male)'!$A$2:$QQ$431,H15+307,FALSE),VLOOKUP($W$9,'TABCV(Female)'!$A$2:$QQ$431,H15+307,FALSE)),0) -> 0
G16: =IF(G15="","",IF(กรอกข้อมูล!$C$5+H15>79,"",กรอกข้อมูล!$C$5+H15)) -> 46 | H16: =IF(G16="","",H15+1) -> 3 | I16: =IF(H16="","",(U16*$V$8)/1000) -> 41000 | J16: =IF(H16="","",(V16*$V$8)/1000) -> 1000000 | K16: =IF(H16="","",IF(W16="","-",W16)) -> 33 | L16: =IF(I16="","",IF(X16=0,"-",X16)) -> - | M16: =IF(H16="","",(Y16*$V$8)/1000) -> 29000 | N16: =IF(H16="","",(Z16*$V$8)/1000) -> 1000000 | U16: =IF(AC16-1000<0,0,AC16-1000) -> 41 | V16: =IF(AC16=0,0,IF(AC16>1000,1000,AC16)) -> 1000 | W16: =IF(AG16=0,0,IF(LEN(AG16)<4,0,LEFT(AG16,(LEN(AG16)-3)))) -> 33 | X16: =IF(AG16=0,0,RIGHT(AG16,3)+0) -> 0 | Y16: =IF(AK16-1000<0,0,AK16-1000) -> 29 | Z16: =IF(AK16=0,0,IF(AK16>1000,1000,AK16)) -> 1000 | AA16: RPU Year 3 | AB16: PVL03 | AC16: =IFERROR(IF($W$6="M",VLOOKUP($W$9,'TABCV(Male)'!$A$2:$QQ$431,H16+105,FALSE),VLOOKUP($W$9,'TABCV(Female)'!$A$2:$QQ$431,H16+105,FALSE)),0) -> 1041 | AE16: ETI Year 3 | AF16: ETA03 | AG16: =IFERROR(IF($W$6="M",VLOOKUP($W$9,'TABCV(Male)'!$A$2:$QQ$431,H16+206,FALSE),VLOOKUP($W$9,'TABCV(Female)'!$A$2:$QQ$431,H16+206,FALSE)),0) -> 33000 | AI16: PEN Year 3 | AJ16: PEN03 | AK16: =IFERROR(IF($W$6="M",VLOOKUP($W$9,'TABCV(Male)'!$A$2:$QQ$431,H16+307,FALSE),VLOOKUP($W$9,'TABCV(Female)'!$A$2:$QQ$431,H16+307,FALSE)),0) -> 1029
G17: =IF(G16="","",IF(กรอกข้อมูล!$C$5+H16>79,"",กรอกข้อมูล!$C$5+H16)) -> 47 | H17: =IF(G17="","",H16+1) -> 4 | I17: =IF(H17="","",(U17*$V$8)/1000) -> 292000 | J17: =IF(H17="","",(V17*$V$8)/1000) -> 1000000 | K17: =IF(H17="","",IF(W17="","-",W17)) -> 32 | L17: =IF(I17="","",IF(X17=0,"-",X17)) -> - | M17: =IF(H17="","",(Y17*$V$8)/1000) -> 279000 | N17: =IF(H17="","",(Z17*$V$8)/1000) -> 1000000 | U17: =IF(AC17-1000<0,0,AC17-1000) -> 292 | V17: =IF(AC17=0,0,IF(AC17>1000,1000,AC17)) -> 1000 | W17: =IF(AG17=0,0,IF(LEN(AG17)<4,0,LEFT(AG17,(LEN(AG17)-3)))) -> 32 | X17: =IF(AG17=0,0,RIGHT(AG17,3)+0) -> 0 | Y17: =IF(AK17-1000<0,0,AK17-1000) -> 279 | Z17: =IF(AK17=0,0,IF(AK17>1000,1000,AK17)) -> 1000 | AA17: RPU Year 4 | AB17: PVL04 | AC17: =IFERROR(IF($W$6="M",VLOOKUP($W$9,'TABCV(Male)'!$A$2:$QQ$431,H17+105,FALSE),VLOOKUP($W$9,'TABCV(Female)'!$A$2:$QQ$431,H17+105,FALSE)),0) -> 1292 | AE17: ETI Year 4 | AF17: ETA04 | AG17: =IFERROR(IF($W$6="M",VLOOKUP($W$9,'TABCV(Male)'!$A$2:$QQ$431,H17+206,FALSE),VLOOKUP($W$9,'TABCV(Female)'!$A$2:$QQ$431,H17+206,FALSE)),0) -> 32000 | AI17: PEN Year 4 | AJ17: PEN04 | AK17: =IFERROR(IF($W$6="M",VLOOKUP($W$9,'TABCV(Male)'!$A$2:$QQ$431,H17+307,FALSE),VLOOKUP($W$9,'TABCV(Female)'!$A$2:$QQ$431,H17+307,FALSE)),0) -> 1279
G18: =IF(G17="","",IF(กรอกข้อมูล!$C$5+H17>79,"",กรอกข้อมูล!$C$5+H17)) -> 48 | H18: =IF(G18="","",H17+1) -> 5 | I18: =IF(H18="","",(U18*$V$8)/1000) -> 594000 | J18: =IF(H18="","",(V18*$V$8)/1000) -> 1000000 | K18: =IF(H18="","",IF(W18="","-",W18)) -> 31 | L18: =IF(I18="","",IF(X18=0,"-",X18)) -> - | M18: =IF(H18="","",(Y18*$V$8)/1000) -> 581000 | N18: =IF(H18="","",(Z18*$V$8)/1000) -> 1000000 | U18: =IF(AC18-1000<0,0,AC18-1000) -> 594 | V18: =IF(AC18=0,0,IF(AC18>1000,1000,AC18)) -> 1000 | W18: =IF(AG18=0,0,IF(LEN(AG18)<4,0,LEFT(AG18,(LEN(AG18)-3)))) -> 31 | X18: =IF(AG18=0,0,RIGHT(AG18,3)+0) -> 0 | Y18: =IF(AK18-1000<0,0,AK18-1000) -> 581 | Z18: =IF(AK18=0,0,IF(AK18>1000,1000,AK18)) -> 1000 | AA18: RPU Year 5 | AB18: PVL05 | AC18: =IFERROR(IF($W$6="M",VLOOKUP($W$9,'TABCV(Male)'!$A$2:$QQ$431,H18+105,FALSE),VLOOKUP($W$9,'TABCV(Female)'!$A$2:$QQ$431,H18+105,FALSE)),0) -> 1594 | AE18: ETI Year 5 | AF18: ETA05 | AG18: =IFERROR(IF($W$6="M",VLOOKUP($W$9,'TABCV(Male)'!$A$2:$QQ$431,H18+206,FALSE),VLOOKUP($W$9,'TABCV(Female)'!$A$2:$QQ$431,H18+206,FALSE)),0) -> 31000 | AI18: PEN Year 5 | AJ18: PEN05 | AK18: =IFERROR(IF($W$6="M",VLOOKUP($W$9,'TABCV(Male)'!$A$2:$QQ$431,H18+307,FALSE),VLOOKUP($W$9,'TABCV(Female)'!$A$2:$QQ$431,H18+307,FALSE)),0) -> 1581
G19: =IF(G18="","",IF(กรอกข้อมูล!$C$5+H18>79,"",กรอกข้อมูล!$C$5+H18)) -> 49 | H19: =IF(G19="","",H18+1) -> 6 | I19: =IF(H19="","",(U19*$V$8)/1000) -> 0 | J19: =IF(H19="","",(V19*$V$8)/1000) -> 0 | K19: =IF(H19="","",IF(W19="","-",W19)) -> 0 | L19: =IF(I19="","",IF(X19=0,"-",X19)) -> - | M19: =IF(H19="","",(Y19*$V$8)/1000) -> 0 | N19: =IF(H19="","",(Z19*$V$8)/1000) -> 0 | U19: =IF(AC19-1000<0,0,AC19-1000) -> 0 | V19: =IF(AC19=0,0,IF(AC19>1000,1000,AC19)) -> 0 | W19: =IF(AG19=0,0,IF(LEN(AG19)<4,0,LEFT(AG19,(LEN(AG19)-3)))) -> 0 | X19: =IF(AG19=0,0,RIGHT(AG19,3)+0) -> 0 | Y19: =IF(AK19-1000<0,0,AK19-1000) -> 0 | Z19: =IF(AK19=0,0,IF(AK19>1000,1000,AK19)) -> 0 | AA19: RPU Year 6 | AB19: PVL06 | AC19: =IFERROR(IF($W$6="M",VLOOKUP($W$9,'TABCV(Male)'!$A$2:$QQ$431,H19+105,FALSE),VLOOKUP($W$9,'TABCV(Female)'!$A$2:$QQ$431,H19+105,FALSE)),0) -> 0 | AE19: ETI Year 6 | AF19: ETA06 | AG19: =IFERROR(IF($W$6="M",VLOOKUP($W$9,'TABCV(Male)'!$A$2:$QQ$431,H19+206,FALSE),VLOOKUP($W$9,'TABCV(Female)'!$A$2:$QQ$431,H19+206,FALSE)),0) -> 0 | AI19: PEN Year 6 | AJ19: PEN06 | AK19: =IFERROR(IF($W$6="M",VLOOKUP($W$9,'TABCV(Male)'!$A$2:$QQ$431,H19+307,FALSE),VLOOKUP($W$9,'TABCV(Female)'!$A$2:$QQ$431,H19+307,FALSE)),0) -> 0
G20: =IF(G19="","",IF(กรอกข้อมูล!$C$5+H19>79,"",กรอกข้อมูล!$C$5+H19)) -> 50 | H20: =IF(G20="","",H19+1) -> 7 | I20: =IF(H20="","",(U20*$V$8)/1000) -> 0 | J20: =IF(H20="","",(V20*$V$8)/1000) -> 0 | K20: =IF(H20="","",IF(W20="","-",W20)) -> 0 | L20: =IF(I20="","",IF(X20=0,"-",X20)) -> - | M20: =IF(H20="","",(Y20*$V$8)/1000) -> 0 | N20: =IF(H20="","",(Z20*$V$8)/1000) -> 0 | U20: =IF(AC20-1000<0,0,AC20-1000) -> 0 | V20: =IF(AC20=0,0,IF(AC20>1000,1000,AC20)) -> 0 | W20: =IF(AG20=0,0,IF(LEN(AG20)<4,0,LEFT(AG20,(LEN(AG20)-3)))) -> 0 | X20: =IF(AG20=0,0,RIGHT(AG20,3)+0) -> 0 | Y20: =IF(AK20-1000<0,0,AK20-1000) -> 0 | Z20: =IF(AK20=0,0,IF(AK20>1000,1000,AK20)) -> 0 | AA20: RPU Year 7 | AB20: PVL07 | AC20: =IFERROR(IF($W$6="M",VLOOKUP($W$9,'TABCV(Male)'!$A$2:$QQ$431,H20+105,FALSE),VLOOKUP($W$9,'TABCV(Female)'!$A$2:$QQ$431,H20+105,FALSE)),0) -> 0 | AE20: ETI Year 7 | AF20: ETA07 | AG20: =IFERROR(IF($W$6="M",VLOOKUP($W$9,'TABCV(Male)'!$A$2:$QQ$431,H20+206,FALSE),VLOOKUP($W$9,'TABCV(Female)'!$A$2:$QQ$431,H20+206,FALSE)),0) -> 0 | AI20: PEN Year 7 | AJ20: PEN07 | AK20: =IFERROR(IF($W$6="M",VLOOKUP($W$9,'TABCV(Male)'!$A$2:$QQ$431,H20+307,FALSE),VLOOKUP($W$9,'TABCV(Female)'!$A$2:$QQ$431,H20+307,FALSE)),0) -> 0
G21: =IF(G20="","",IF(กรอกข้อมูล!$C$5+H20>79,"",กรอกข้อมูล!$C$5+H20)) -> 51 | H21: =IF(G21="","",H20+1) -> 8 | I21: =IF(H21="","",(U21*$V$8)/1000) -> 0 | J21: =IF(H21="","",(V21*$V$8)/1000) -> 0 | K21: =IF(H21="","",IF(W21="","-",W21)) -> 0 | L21: =IF(I21="","",IF(X21=0,"-",X21)) -> - | M21: =IF(H21="","",(Y21*$V$8)/1000) -> 0 | N21: =IF(H21="","",(Z21*$V$8)/1000) -> 0 | U21: =IF(AC21-1000<0,0,AC21-1000) -> 0 | V21: =IF(AC21=0,0,IF(AC21>1000,1000,AC21)) -> 0 | W21: =IF(AG21=0,0,IF(LEN(AG21)<4,0,LEFT(AG21,(LEN(AG21)-3)))) -> 0 | X21: =IF(AG21=0,0,RIGHT(AG21,3)+0) -> 0 | Y21: =IF(AK21-1000<0,0,AK21-1000) -> 0 | Z21: =IF(AK21=0,0,IF(AK21>1000,1000,AK21)) -> 0 | AA21: RPU Year 8 | AB21: PVL08 | AC21: =IFERROR(IF($W$6="M",VLOOKUP($W$9,'TABCV(Male)'!$A$2:$QQ$431,H21+105,FALSE),VLOOKUP($W$9,'TABCV(Female)'!$A$2:$QQ$431,H21+105,FALSE)),0) -> 0 | AE21: ETI Year 8 | AF21: ETA08 | AG21: =IFERROR(IF($W$6="M",VLOOKUP($W$9,'TABCV(Male)'!$A$2:$QQ$431,H21+206,FALSE),VLOOKUP($W$9,'TABCV(Female)'!$A$2:$QQ$431,H21+206,FALSE)),0) -> 0 | AI21: PEN Year 8 | AJ21: PEN08 | AK21: =IFERROR(IF($W$6="M",VLOOKUP($W$9,'TABCV(Male)'!$A$2:$QQ$431,H21+307,FALSE),VLOOKUP($W$9,'TABCV(Female)'!$A$2:$QQ$431,H21+307,FALSE)),0) -> 0
G22: =IF(G21="","",IF(กรอกข้อมูล!$C$5+H21>79,"",กรอกข้อมูล!$C$5+H21)) -> 52 | H22: =IF(G22="","",H21+1) -> 9 | I22: =IF(H22="","",(U22*$V$8)/1000) -> 0 | J22: =IF(H22="","",(V22*$V$8)/1000) -> 0 | K22: =IF(H22="","",IF(W22="","-",W22)) -> 0 | L22: =IF(I22="","",IF(X22=0,"-",X22)) -> - | M22: =IF(H22="","",(Y22*$V$8)/1000) -> 0 | N22: =IF(H22="","",(Z22*$V$8)/1000) -> 0 | U22: =IF(AC22-1000<0,0,AC22-1000) -> 0 | V22: =IF(AC22=0,0,IF(AC22>1000,1000,AC22)) -> 0 | W22: =IF(AG22=0,0,IF(LEN(AG22)<4,0,LEFT(AG22,(LEN(AG22)-3)))) -> 0 | X22: =IF(AG22=0,0,RIGHT(AG22,3)+0) -> 0 | Y22: =IF(AK22-1000<0,0,AK22-1000) -> 0 | Z22: =IF(AK22=0,0,IF(AK22>1000,1000,AK22)) -> 0 | AA22: RPU Year 9 | AB22: PVL09 | AC22: =IFERROR(IF($W$6="M",VLOOKUP($W$9,'TABCV(Male)'!$A$2:$QQ$431,H22+105,FALSE),VLOOKUP($W$9,'TABCV(Female)'!$A$2:$QQ$431,H22+105,FALSE)),0) -> 0 | AE22: ETI Year 9 | AF22: ETA09 | AG22: =IFERROR(IF($W$6="M",VLOOKUP($W$9,'TABCV(Male)'!$A$2:$QQ$431,H22+206,FALSE),VLOOKUP($W$9,'TABCV(Female)'!$A$2:$QQ$431,H22+206,FALSE)),0) -> 0 | AI22: PEN Year 9 | AJ22: PEN09 | AK22: =IFERROR(IF($W$6="M",VLOOKUP($W$9,'TABCV(Male)'!$A$2:$QQ$431,H22+307,FALSE),VLOOKUP($W$9,'TABCV(Female)'!$A$2:$QQ$431,H22+307,FALSE)),0) -> 0
G23: =IF(G22="","",IF(กรอกข้อมูล!$C$5+H22>79,"",กรอกข้อมูล!$C$5+H22)) -> 53 | H23: =IF(G23="","",H22+1) -> 10 | I23: =IF(H23="","",(U23*$V$8)/1000) -> 0 | J23: =IF(H23="","",(V23*$V$8)/1000) -> 0 | K23: =IF(H23="","",IF(W23="","-",W23)) -> 0 | L23: =IF(I23="","",IF(X23=0,"-",X23)) -> - | M23: =IF(H23="","",(Y23*$V$8)/1000) -> 0 | N23: =IF(H23="","",(Z23*$V$8)/1000) -> 0 | U23: =IF(AC23-1000<0,0,AC23-1000) -> 0 | V23: =IF(AC23=0,0,IF(AC23>1000,1000,AC23)) -> 0 | W23: =IF(AG23=0,0,IF(LEN(AG23)<4,0,LEFT(AG23,(LEN(AG23)-3)))) -> 0 | X23: =IF(AG23=0,0,RIGHT(AG23,3)+0) -> 0 | Y23: =IF(AK23-1000<0,0,AK23-1000) -> 0 | Z23: =IF(AK23=0,0,IF(AK23>1000,1000,AK23)) -> 0 | AA23: RPU Year 10 | AB23: PVL10 | AC23: =IFERROR(IF($W$6="M",VLOOKUP($W$9,'TABCV(Male)'!$A$2:$QQ$431,H23+105,FALSE),VLOOKUP($W$9,'TABCV(Female)'!$A$2:$QQ$431,H23+105,FALSE)),0) -> 0 | AE23: ETI Year 10 | AF23: ETA10 | AG23: =IFERROR(IF($W$6="M",VLOOKUP($W$9,'TABCV(Male)'!$A$2:$QQ$431,H23+206,FALSE),VLOOKUP($W$9,'TABCV(Female)'!$A$2:$QQ$431,H23+206,FALSE)),0) -> 0 | AI23: PEN Year 10 | AJ23: PEN10 | AK23: =IFERROR(IF($W$6="M",VLOOKUP($W$9,'TABCV(Male)'!$A$2:$QQ$431,H23+307,FALSE),VLOOKUP($W$9,'TABCV(Female)'!$A$2:$QQ$431,H23+307,FALSE)),0) -> 0
G24: =IF(G23="","",IF(กรอกข้อมูล!$C$5+H23>79,"",กรอกข้อมูล!$C$5+H23)) -> 54 | H24: =IF(G24="","",H23+1) -> 11 | I24: =IF(H24="","",(U24*$V$8)/1000) -> 0 | J24: =IF(H24="","",(V24*$V$8)/1000) -> 0 | K24: =IF(H24="","",IF(W24="","-",W24)) -> 0 | L24: =IF(I24="","",IF(X24=0,"-",X24)) -> - | M24: =IF(H24="","",(Y24*$V$8)/1000) -> 0 | N24: =IF(H24="","",(Z24*$V$8)/1000) -> 0 | U24: =IF(AC24-1000<0,0,AC24-1000) -> 0 | V24: =IF(AC24=0,0,IF(AC24>1000,1000,AC24)) -> 0 | W24: =IF(AG24=0,0,IF(LEN(AG24)<4,0,LEFT(AG24,(LEN(AG24)-3)))) -> 0 | X24: =IF(AG24=0,0,RIGHT(AG24,3)+0) -> 0 | Y24: =IF(AK24-1000<0,0,AK24-1000) -> 0 | Z24: =IF(AK24=0,0,IF(AK24>1000,1000,AK24)) -> 0 | AA24: RPU Year 11 | AB24: PVL11 | AC24: =IFERROR(IF($W$6="M",VLOOKUP($W$9,'TABCV(Male)'!$A$2:$QQ$431,H24+105,FALSE),VLOOKUP($W$9,'TABCV(Female)'!$A$2:$QQ$431,H24+105,FALSE)),0) -> 0 | AE24: ETI Year 11 | AF24: ETA11 | AG24: =IFERROR(IF($W$6="M",VLOOKUP($W$9,'TABCV(Male)'!$A$2:$QQ$431,H24+206,FALSE),VLOOKUP($W$9,'TABCV(Female)'!$A$2:$QQ$431,H24+206,FALSE)),0) -> 0 | AI24: PEN Year 11 | AJ24: PEN11 | AK24: =IFERROR(IF($W$6="M",VLOOKUP($W$9,'TABCV(Male)'!$A$2:$QQ$431,H24+307,FALSE),VLOOKUP($W$9,'TABCV(Female)'!$A$2:$QQ$431,H24+307,FALSE)),0) -> 0
G25: =IF(G24="","",IF(กรอกข้อมูล!$C$5+H24>79,"",กรอกข้อมูล!$C$5+H24)) -> 55 | H25: =IF(G25="","",H24+1) -> 12 | I25: =IF(H25="","",(U25*$V$8)/1000) -> 0 | J25: =IF(H25="","",(V25*$V$8)/1000) -> 0 | K25: =IF(H25="","",IF(W25="","-",W25)) -> 0 | L25: =IF(I25="","",IF(X25=0,"-",X25)) -> - | M25: =IF(H25="","",(Y25*$V$8)/1000) -> 0 | N25: =IF(H25="","",(Z25*$V$8)/1000) -> 0 | U25: =IF(AC25-1000<0,0,AC25-1000) -> 0 | V25: =IF(AC25=0,0,IF(AC25>1000,1000,AC25)) -> 0 | W25: =IF(AG25=0,0,IF(LEN(AG25)<4,0,LEFT(AG25,(LEN(AG25)-3)))) -> 0 | X25: =IF(AG25=0,0,RIGHT(AG25,3)+0) -> 0 | Y25: =IF(AK25-1000<0,0,AK25-1000) -> 0 | Z25: =IF(AK25=0,0,IF(AK25>1000,1000,AK25)) -> 0 | AA25: RPU Year 12 | AB25: PVL12 | AC25: =IFERROR(IF($W$6="M",VLOOKUP($W$9,'TABCV(Male)'!$A$2:$QQ$431,H25+105,FALSE),VLOOKUP($W$9,'TABCV(Female)'!$A$2:$QQ$431,H25+105,FALSE)),0) -> 0 | AE25: ETI Year 12 | AF25: ETA12 | AG25: =IFERROR(IF($W$6="M",VLOOKUP($W$9,'TABCV(Male)'!$A$2:$QQ$431,H25+206,FALSE),VLOOKUP($W$9,'TABCV(Female)'!$A$2:$QQ$431,H25+206,FALSE)),0) -> 0 | AI25: PEN Year 12 | AJ25: PEN12 | AK25: =IFERROR(IF($W$6="M",VLOOKUP($W$9,'TABCV(Male)'!$A$2:$QQ$431,H25+307,FALSE),VLOOKUP($W$9,'TABCV(Female)'!$A$2:$QQ$431,H25+307,FALSE)),0) -> 0
G26: =IF(G25="","",IF(กรอกข้อมูล!$C$5+H25>79,"",กรอกข้อมูล!$C$5+H25)) -> 56 | H26: =IF(G26="","",H25+1) -> 13 | I26: =IF(H26="","",(U26*$V$8)/1000) -> 0 | J26: =IF(H26="","",(V26*$V$8)/1000) -> 0 | K26: =IF(H26="","",IF(W26="","-",W26)) -> 0 | L26: =IF(I26="","",IF(X26=0,"-",X26)) -> - | M26: =IF(H26="","",(Y26*$V$8)/1000) -> 0 | N26: =IF(H26="","",(Z26*$V$8)/1000) -> 0 | U26: =IF(AC26-1000<0,0,AC26-1000) -> 0 | V26: =IF(AC26=0,0,IF(AC26>1000,1000,AC26)) -> 0 | W26: =IF(AG26=0,0,IF(LEN(AG26)<4,0,LEFT(AG26,(LEN(AG26)-3)))) -> 0 | X26: =IF(AG26=0,0,RIGHT(AG26,3)+0) -> 0 | Y26: =IF(AK26-1000<0,0,AK26-1000) -> 0 | Z26: =IF(AK26=0,0,IF(AK26>1000,1000,AK26)) -> 0 | AA26: RPU Year 13 | AB26: PVL13 | AC26: =IFERROR(IF($W$6="M",VLOOKUP($W$9,'TABCV(Male)'!$A$2:$QQ$431,H26+105,FALSE),VLOOKUP($W$9,'TABCV(Female)'!$A$2:$QQ$431,H26+105,FALSE)),0) -> 0 | AE26: ETI Year 13 | AF26: ETA13 | AG26: =IFERROR(IF($W$6="M",VLOOKUP($W$9,'TABCV(Male)'!$A$2:$QQ$431,H26+206,FALSE),VLOOKUP($W$9,'TABCV(Female)'!$A$2:$QQ$431,H26+206,FALSE)),0) -> 0 | AI26: PEN Year 13 | AJ26: PEN13 | AK26: =IFERROR(IF($W$6="M",VLOOKUP($W$9,'TABCV(Male)'!$A$2:$QQ$431,H26+307,FALSE),VLOOKUP($W$9,'TABCV(Female)'!$A$2:$QQ$431,H26+307,FALSE)),0) -> 0
... G63: =IF(G62="","",IF(กรอกข้อมูล!$C$5+H62>79,"",กรอกข้อมูล!$C$5+H62)) | H63: =IF(G63="","",H62+1) | I63: =IF(H63="","",(U63*$V$8)/1000) | J63: =IF(H63="","",(V63*$V$8)/1000) | K63: =IF(H63="","",IF(W63="","-",W63)) | L63: =IF(I63="","",IF(X63=0,"-",X63)) | M63: =IF(H63="","",(Y63*$V$8)/1000) | N63: =IF(H63="","",(Z63*$V$8)/1000) | U63: =IF(AC63-1000<0,0,AC63-1000) -> 0 | V63: =IF(AC63=0,0,IF(AC63>1000,1000,AC63)) -> 0 | W63: =IF(AG63=0,0,IF(LEN(AG63)<4,0,LEFT(AG63,(LEN(AG63)-3)))) -> 0 | X63: =IF(AG63=0,0,RIGHT(AG63,3)+0) -> 0 | Y63: =IF(AK63-1000<0,0,AK63-1000) -> 0 | Z63: =IF(AK63=0,0,IF(AK63>1000,1000,AK63)) -> 0 | AA63: RPU Year 50 | AB63: PVL50 | AC63: =IFERROR(IF($W$6="M",VLOOKUP($W$9,'TABCV(Male)'!$A$2:$QQ$431,H63+105,FALSE),VLOOKUP($W$9,'TABCV(Female)'!$A$2:$QQ$431,H63+105,FALSE)),0) -> 0 | AE63: ETI Year 50 | AF63: ETA50 | AG63: =IFERROR(IF($W$6="M",VLOOKUP($W$9,'TABCV(Male)'!$A$2:$QQ$431,H63+206,FALSE),VLOOKUP($W$9,'TABCV(Female)'!$A$2:$QQ$431,H63+206,FALSE)),0) -> 0 | AI63: PEN Year 50 | AJ63: PEN50 | AK63: =IFERROR(IF($W$6="M",VLOOKUP($W$9,'TABCV(Male)'!$A$2:$QQ$431,H63+307,FALSE),VLOOKUP($W$9,'TABCV(Female)'!$A$2:$QQ$431,H63+307,FALSE)),0) -> 0
U64: =IF(AC64-1000<0,0,AC64-1000) -> 0 | V64: =IF(AC64=0,0,IF(AC64>1000,1000,AC64)) -> 0 | W64: =IF(AG64=0,0,IF(LEN(AG64)<4,0,LEFT(AG64,(LEN(AG64)-3)))) -> 0 | X64: =IF(AG64=0,0,RIGHT(AG64,3)+0) -> 0 | Y64: =IF(AK64-1000<0,0,AK64-1000) -> 0 | Z64: =IF(AK64=0,0,IF(AK64>1000,1000,AK64)) -> 0 | AA64: RPU Year 51 | AB64: PVL51 | AC64: =IFERROR(IF($W$6="M",VLOOKUP($W$9,'TABCV(Male)'!$A$2:$QQ$431,AO25+105,FALSE),VLOOKUP($W$9,'TABCV(Female)'!$A$2:$QQ$431,AO25+105,FALSE)),0) -> 0 | AE64: ETI Year 51 | AF64: ETA51 | AG64: =IFERROR(IF($W$6="M",VLOOKUP($W$9,'TABCV(Male)'!$A$2:$QQ$431,AO25+206,FALSE),VLOOKUP($W$9,'TABCV(Female)'!$A$2:$QQ$431,AO25+206,FALSE)),0) -> 0 | AI64: PEN Year 51 | AJ64: PEN51 | AK64: =IFERROR(IF($W$6="M",VLOOKUP($W$9,'TABCV(Male)'!$A$2:$QQ$431,AO25+307,FALSE),VLOOKUP($W$9,'TABCV(Female)'!$A$2:$QQ$431,AO25+307,FALSE)),0) -> 0
B65: เอกสารประกอบการเสนอขายนี้เป็นข้อมูลเบื้องต้นของแบบประกันภัย ผลประโยชน์ ความคุ้มครองและข้อยกเว้น เป็นไปตามที่กำหนดในกรมธรรม์ ผู้ซื้อควรทำความเข้าใจรายละเอียด ความคุ้มครองและเงื่อนไขก่อนตัดสินใจทำประกันภัยทุกครั้ง | U65: =IF(AC65-1000<0,0,AC65-1000) -> 0 | V65: =IF(AC65=0,0,IF(AC65>1000,1000,AC65)) -> 0 | W65: =IF(AG65=0,0,IF(LEN(AG65)<4,0,LEFT(AG65,(LEN(AG65)-3)))) -> 0 | X65: =IF(AG65=0,0,RIGHT(AG65,3)+0) -> 0 | Y65: =IF(AK65-1000<0,0,AK65-1000) -> 0 | Z65: =IF(AK65=0,0,IF(AK65>1000,1000,AK65)) -> 0 | AA65: RPU Year 52 | AB65: PVL52 | AC65: =IFERROR(IF($W$6="M",VLOOKUP($W$9,'TABCV(Male)'!$A$2:$QQ$431,AO26+105,FALSE),VLOOKUP($W$9,'TABCV(Female)'!$A$2:$QQ$431,AO26+105,FALSE)),0) -> 0 | AE65: ETI Year 52 | AF65: ETA52 | AG65: =IFERROR(IF($W$6="M",VLOOKUP($W$9,'TABCV(Male)'!$A$2:$QQ$431,AO26+206,FALSE),VLOOKUP($W$9,'TABCV(Female)'!$A$2:$QQ$431,AO26+206,FALSE)),0) -> 0 | AI65: PEN Year 52 | AJ65: PEN52 | AK65: =IFERROR(IF($W$6="M",VLOOKUP($W$9,'TABCV(Male)'!$A$2:$QQ$431,AO26+307,FALSE),VLOOKUP($W$9,'TABCV(Female)'!$A$2:$QQ$431,AO26+307,FALSE)),0) -> 0
B66: ="โปรแกรมใบข้อเสนอนี้ใช้สำหรับแบบประกัน "&กรอกข้อมูล!E65&" ที่เสนอขายตั้งแต่ "&กรอกข้อมูล!E63&" หรือตามประกาศยกเลิกการใช้จากบริษัทฯ (แล้วแต่ระยะเวลาใดจะเกิดขึ้นก่อน)" -> โปรแกรมใบข้อเสนอนี้ใช้สำหรับแบบประกัน ไอสมาร์ท 80/6 (ไม่มีเงินปันผล) ที่เสนอขายตั้งแต่ 1 มกราคม 2569 ถึง 31 มีนาคม 2570 หรือตามประกาศยกเลิกการใช้จากบริษัทฯ (แล้วแต่ระยะเวลาใดจะเกิดขึ้นก่อน) | U66: =IF(AC66-1000<0,0,AC66-1000) -> 0 | V66: =IF(AC66=0,0,IF(AC66>1000,1000,AC66)) -> 0 | W66: =IF(AG66=0,0,IF(LEN(AG66)<4,0,LEFT(AG66,(LEN(AG66)-3)))) -> 0 | X66: =IF(AG66=0,0,RIGHT(AG66,3)+0) -> 0 | Y66: =IF(AK66-1000<0,0,AK66-1000) -> 0 | Z66: =IF(AK66=0,0,IF(AK66>1000,1000,AK66)) -> 0 | AA66: RPU Year 53 | AB66: PVL53 | AC66: =IFERROR(IF($W$6="M",VLOOKUP($W$9,'TABCV(Male)'!$A$2:$QQ$431,AO27+105,FALSE),VLOOKUP($W$9,'TABCV(Female)'!$A$2:$QQ$431,AO27+105,FALSE)),0) -> 0 | AE66: ETI Year 53 | AF66: ETA53 | AG66: =IFERROR(IF($W$6="M",VLOOKUP($W$9,'TABCV(Male)'!$A$2:$QQ$431,AO27+206,FALSE),VLOOKUP($W$9,'TABCV(Female)'!$A$2:$QQ$431,AO27+206,FALSE)),0) -> 0 | AI66: PEN Year 53 | AJ66: PEN53 | AK66: =IFERROR(IF($W$6="M",VLOOKUP($W$9,'TABCV(Male)'!$A$2:$QQ$431,AO27+307,FALSE),VLOOKUP($W$9,'TABCV(Female)'!$A$2:$QQ$431,AO27+307,FALSE)),0) -> 0
R67: =กรอกข้อมูล!E65&" เวอร์ชั่น "&กรอกข้อมูล!E64 -> ไอสมาร์ท 80/6 (ไม่มีเงินปันผล) เวอร์ชั่น A2026-1 | U67: =IF(AC67-1000<0,0,AC67-1000) -> 0 | V67: =IF(AC67=0,0,IF(AC67>1000,1000,AC67)) -> 0 | W67: =IF(AG67=0,0,IF(LEN(AG67)<4,0,LEFT(AG67,(LEN(AG67)-3)))) -> 0 | X67: =IF(AG67=0,0,RIGHT(AG67,3)+0) -> 0 | Y67: =IF(AK67-1000<0,0,AK67-1000) -> 0 | Z67: =IF(AK67=0,0,IF(AK67>1000,1000,AK67)) -> 0 | AA67: RPU Year 54 | AB67: PVL54 | AC67: =IFERROR(IF($W$6="M",VLOOKUP($W$9,'TABCV(Male)'!$A$2:$QQ$431,AO28+105,FALSE),VLOOKUP($W$9,'TABCV(Female)'!$A$2:$QQ$431,AO28+105,FALSE)),0) -> 0 | AE67: ETI Year 54 | AF67: ETA54 | AG67: =IFERROR(IF($W$6="M",VLOOKUP($W$9,'TABCV(Male)'!$A$2:$QQ$431,AO28+206,FALSE),VLOOKUP($W$9,'TABCV(Female)'!$A$2:$QQ$431,AO28+206,FALSE)),0) -> 0 | AI67: PEN Year 54 | AJ67: PEN54 | AK67: =IFERROR(IF($W$6="M",VLOOKUP($W$9,'TABCV(Male)'!$A$2:$QQ$431,AO28+307,FALSE),VLOOKUP($W$9,'TABCV(Female)'!$A$2:$QQ$431,AO28+307,FALSE)),0) -> 0
U68: =IF(AC68-1000<0,0,AC68-1000) -> 0 | V68: =IF(AC68=0,0,IF(AC68>1000,1000,AC68)) -> 0 | W68: =IF(AG68=0,0,IF(LEN(AG68)<4,0,LEFT(AG68,(LEN(AG68)-3)))) -> 0 | X68: =IF(AG68=0,0,RIGHT(AG68,3)+0) -> 0 | Y68: =IF(AK68-1000<0,0,AK68-1000) -> 0 | Z68: =IF(AK68=0,0,IF(AK68>1000,1000,AK68)) -> 0 | AA68: RPU Year 55 | AB68: PVL55 | AC68: =IFERROR(IF($W$6="M",VLOOKUP($W$9,'TABCV(Male)'!$A$2:$QQ$431,AO29+105,FALSE),VLOOKUP($W$9,'TABCV(Female)'!$A$2:$QQ$431,AO29+105,FALSE)),0) -> 0 | AE68: ETI Year 55 | AF68: ETA55 | AG68: =IFERROR(IF($W$6="M",VLOOKUP($W$9,'TABCV(Male)'!$A$2:$QQ$431,AO29+206,FALSE),VLOOKUP($W$9,'TABCV(Female)'!$A$2:$QQ$431,AO29+206,FALSE)),0) -> 0 | AI68: PEN Year 55 | AJ68: PEN55 | AK68: =IFERROR(IF($W$6="M",VLOOKUP($W$9,'TABCV(Male)'!$A$2:$QQ$431,AO29+307,FALSE),VLOOKUP($W$9,'TABCV(Female)'!$A$2:$QQ$431,AO29+307,FALSE)),0) -> 0
U69: =IF(AC69-1000<0,0,AC69-1000) -> 0 | V69: =IF(AC69=0,0,IF(AC69>1000,1000,AC69)) -> 0 | W69: =IF(AG69=0,0,IF(LEN(AG69)<4,0,LEFT(AG69,(LEN(AG69)-3)))) -> 0 | X69: =IF(AG69=0,0,RIGHT(AG69,3)+0) -> 0 | Y69: =IF(AK69-1000<0,0,AK69-1000) -> 0 | Z69: =IF(AK69=0,0,IF(AK69>1000,1000,AK69)) -> 0 | AA69: RPU Year 56 | AB69: PVL56 | AC69: =IFERROR(IF($W$6="M",VLOOKUP($W$9,'TABCV(Male)'!$A$2:$QQ$431,AO30+105,FALSE),VLOOKUP($W$9,'TABCV(Female)'!$A$2:$QQ$431,AO30+105,FALSE)),0) -> 0 | AE69: ETI Year 56 | AF69: ETA56 | AG69: =IFERROR(IF($W$6="M",VLOOKUP($W$9,'TABCV(Male)'!$A$2:$QQ$431,AO30+206,FALSE),VLOOKUP($W$9,'TABCV(Female)'!$A$2:$QQ$431,AO30+206,FALSE)),0) -> 0 | AI69: PEN Year 56 | AJ69: PEN56 | AK69: =IFERROR(IF($W$6="M",VLOOKUP($W$9,'TABCV(Male)'!$A$2:$QQ$431,AO30+307,FALSE),VLOOKUP($W$9,'TABCV(Female)'!$A$2:$QQ$431,AO30+307,FALSE)),0) -> 0
U70: =IF(AC70-1000<0,0,AC70-1000) -> 0 | V70: =IF(AC70=0,0,IF(AC70>1000,1000,AC70)) -> 0 | W70: =IF(AG70=0,0,IF(LEN(AG70)<4,0,LEFT(AG70,(LEN(AG70)-3)))) -> 0 | X70: =IF(AG70=0,0,RIGHT(AG70,3)+0) -> 0 | Y70: =IF(AK70-1000<0,0,AK70-1000) -> 0 | Z70: =IF(AK70=0,0,IF(AK70>1000,1000,AK70)) -> 0 | AA70: RPU Year 57 | AB70: PVL57 | AC70: =IFERROR(IF($W$6="M",VLOOKUP($W$9,'TABCV(Male)'!$A$2:$QQ$431,AO31+105,FALSE),VLOOKUP($W$9,'TABCV(Female)'!$A$2:$QQ$431,AO31+105,FALSE)),0) -> 0 | AE70: ETI Year 57 | AF70: ETA57 | AG70: =IFERROR(IF($W$6="M",VLOOKUP($W$9,'TABCV(Male)'!$A$2:$QQ$431,AO31+206,FALSE),VLOOKUP($W$9,'TABCV(Female)'!$A$2:$QQ$431,AO31+206,FALSE)),0) -> 0 | AI70: PEN Year 57 | AJ70: PEN57 | AK70: =IFERROR(IF($W$6="M",VLOOKUP($W$9,'TABCV(Male)'!$A$2:$QQ$431,AO31+307,FALSE),VLOOKUP($W$9,'TABCV(Female)'!$A$2:$QQ$431,AO31+307,FALSE)),0) -> 0
U71: =IF(AC71-1000<0,0,AC71-1000) -> 0 | V71: =IF(AC71=0,0,IF(AC71>1000,1000,AC71)) -> 0 | W71: =IF(AG71=0,0,IF(LEN(AG71)<4,0,LEFT(AG71,(LEN(AG71)-3)))) -> 0 | X71: =IF(AG71=0,0,RIGHT(AG71,3)+0) -> 0 | Y71: =IF(AK71-1000<0,0,AK71-1000) -> 0 | Z71: =IF(AK71=0,0,IF(AK71>1000,1000,AK71)) -> 0 | AA71: RPU Year 58 | AB71: PVL58 | AC71: =IFERROR(IF($W$6="M",VLOOKUP($W$9,'TABCV(Male)'!$A$2:$QQ$431,AO32+105,FALSE),VLOOKUP($W$9,'TABCV(Female)'!$A$2:$QQ$431,AO32+105,FALSE)),0) -> 0 | AE71: ETI Year 58 | AF71: ETA58 | AG71: =IFERROR(IF($W$6="M",VLOOKUP($W$9,'TABCV(Male)'!$A$2:$QQ$431,AO32+206,FALSE),VLOOKUP($W$9,'TABCV(Female)'!$A$2:$QQ$431,AO32+206,FALSE)),0) -> 0 | AI71: PEN Year 58 | AJ71: PEN58 | AK71: =IFERROR(IF($W$6="M",VLOOKUP($W$9,'TABCV(Male)'!$A$2:$QQ$431,AO32+307,FALSE),VLOOKUP($W$9,'TABCV(Female)'!$A$2:$QQ$431,AO32+307,FALSE)),0) -> 0
U72: =IF(AC72-1000<0,0,AC72-1000) -> 0 | V72: =IF(AC72=0,0,IF(AC72>1000,1000,AC72)) -> 0 | W72: =IF(AG72=0,0,IF(LEN(AG72)<4,0,LEFT(AG72,(LEN(AG72)-3)))) -> 0 | X72: =IF(AG72=0,0,RIGHT(AG72,3)+0) -> 0 | Y72: =IF(AK72-1000<0,0,AK72-1000) -> 0 | Z72: =IF(AK72=0,0,IF(AK72>1000,1000,AK72)) -> 0 | AA72: RPU Year 59 | AB72: PVL59 | AC72: =IFERROR(IF($W$6="M",VLOOKUP($W$9,'TABCV(Male)'!$A$2:$QQ$431,AO33+105,FALSE),VLOOKUP($W$9,'TABCV(Female)'!$A$2:$QQ$431,AO33+105,FALSE)),0) -> 0 | AE72: ETI Year 59 | AF72: ETA59 | AG72: =IFERROR(IF($W$6="M",VLOOKUP($W$9,'TABCV(Male)'!$A$2:$QQ$431,AO33+206,FALSE),VLOOKUP($W$9,'TABCV(Female)'!$A$2:$QQ$431,AO33+206,FALSE)),0) -> 0 | AI72: PEN Year 59 | AJ72: PEN59 | AK72: =IFERROR(IF($W$6="M",VLOOKUP($W$9,'TABCV(Male)'!$A$2:$QQ$431,AO33+307,FALSE),VLOOKUP($W$9,'TABCV(Female)'!$A$2:$QQ$431,AO33+307,FALSE)),0) -> 0
U73: =IF(AC73-1000<0,0,AC73-1000) -> 0 | V73: =IF(AC73=0,0,IF(AC73>1000,1000,AC73)) -> 0 | W73: =IF(AG73=0,0,IF(LEN(AG73)<4,0,LEFT(AG73,(LEN(AG73)-3)))) -> 0 | X73: =IF(AG73=0,0,RIGHT(AG73,3)+0) -> 0 | Y73: =IF(AK73-1000<0,0,AK73-1000) -> 0 | Z73: =IF(AK73=0,0,IF(AK73>1000,1000,AK73)) -> 0 | AA73: RPU Year 60 | AB73: PVL60 | AC73: =IFERROR(IF($W$6="M",VLOOKUP($W$9,'TABCV(Male)'!$A$2:$QQ$431,AO34+105,FALSE),VLOOKUP($W$9,'TABCV(Female)'!$A$2:$QQ$431,AO34+105,FALSE)),0) -> 0 | AE73: ETI Year 60 | AF73: ETA60 | AG73: =IFERROR(IF($W$6="M",VLOOKUP($W$9,'TABCV(Male)'!$A$2:$QQ$431,AO34+206,FALSE),VLOOKUP($W$9,'TABCV(Female)'!$A$2:$QQ$431,AO34+206,FALSE)),0) -> 0 | AI73: PEN Year 60 | AJ73: PEN60 | AK73: =IFERROR(IF($W$6="M",VLOOKUP($W$9,'TABCV(Male)'!$A$2:$QQ$431,AO34+307,FALSE),VLOOKUP($W$9,'TABCV(Female)'!$A$2:$QQ$431,AO34+307,FALSE)),0) -> 0
U74: =IF(AC74-1000<0,0,AC74-1000) -> 0 | V74: =IF(AC74=0,0,IF(AC74>1000,1000,AC74)) -> 0 | W74: =IF(AG74=0,0,IF(LEN(AG74)<4,0,LEFT(AG74,(LEN(AG74)-3)))) -> 0 | X74: =IF(AG74=0,0,RIGHT(AG74,3)+0) -> 0 | Y74: =IF(AK74-1000<0,0,AK74-1000) -> 0 | Z74: =IF(AK74=0,0,IF(AK74>1000,1000,AK74)) -> 0 | AA74: RPU Year 61 | AB74: PVL61 | AC74: =IFERROR(IF($W$6="M",VLOOKUP($W$9,'TABCV(Male)'!$A$2:$QQ$431,AO35+105,FALSE),VLOOKUP($W$9,'TABCV(Female)'!$A$2:$QQ$431,AO35+105,FALSE)),0) -> 0 | AE74: ETI Year 61 | AF74: ETA61 | AG74: =IFERROR(IF($W$6="M",VLOOKUP($W$9,'TABCV(Male)'!$A$2:$QQ$431,AO35+206,FALSE),VLOOKUP($W$9,'TABCV(Female)'!$A$2:$QQ$431,AO35+206,FALSE)),0) -> 0 | AI74: PEN Year 61 | AJ74: PEN61 | AK74: =IFERROR(IF($W$6="M",VLOOKUP($W$9,'TABCV(Male)'!$A$2:$QQ$431,AO35+307,FALSE),VLOOKUP($W$9,'TABCV(Female)'!$A$2:$QQ$431,AO35+307,FALSE)),0) -> 0
U75: =IF(AC75-1000<0,0,AC75-1000) -> 0 | V75: =IF(AC75=0,0,IF(AC75>1000,1000,AC75)) -> 0 | W75: =IF(AG75=0,0,IF(LEN(AG75)<4,0,LEFT(AG75,(LEN(AG75)-3)))) -> 0 | X75: =IF(AG75=0,0,RIGHT(AG75,3)+0) -> 0 | Y75: =IF(AK75-1000<0,0,AK75-1000) -> 0 | Z75: =IF(AK75=0,0,IF(AK75>1000,1000,AK75)) -> 0 | AA75: RPU Year 62 | AB75: PVL62 | AC75: =IFERROR(IF($W$6="M",VLOOKUP($W$9,'TABCV(Male)'!$A$2:$QQ$431,AO36+105,FALSE),VLOOKUP($W$9,'TABCV(Female)'!$A$2:$QQ$431,AO36+105,FALSE)),0) -> 0 | AE75: ETI Year 62 | AF75: ETA62 | AG75: =IFERROR(IF($W$6="M",VLOOKUP($W$9,'TABCV(Male)'!$A$2:$QQ$431,AO36+206,FALSE),VLOOKUP($W$9,'TABCV(Female)'!$A$2:$QQ$431,AO36+206,FALSE)),0) -> 0 | AI75: PEN Year 62 | AJ75: PEN62 | AK75: =IFERROR(IF($W$6="M",VLOOKUP($W$9,'TABCV(Male)'!$A$2:$QQ$431,AO36+307,FALSE),VLOOKUP($W$9,'TABCV(Female)'!$A$2:$QQ$431,AO36+307,FALSE)),0) -> 0
U76: =IF(AC76-1000<0,0,AC76-1000) -> 0 | V76: =IF(AC76=0,0,IF(AC76>1000,1000,AC76)) -> 0 | W76: =IF(AG76=0,0,IF(LEN(AG76)<4,0,LEFT(AG76,(LEN(AG76)-3)))) -> 0 | X76: =IF(AG76=0,0,RIGHT(AG76,3)+0) -> 0 | Y76: =IF(AK76-1000<0,0,AK76-1000) -> 0 | Z76: =IF(AK76=0,0,IF(AK76>1000,1000,AK76)) -> 0 | AA76: RPU Year 63 | AB76: PVL63 | AC76: =IFERROR(IF($W$6="M",VLOOKUP($W$9,'TABCV(Male)'!$A$2:$QQ$431,AO37+105,FALSE),VLOOKUP($W$9,'TABCV(Female)'!$A$2:$QQ$431,AO37+105,FALSE)),0) -> 0 | AE76: ETI Year 63 | AF76: ETA63 | AG76: =IFERROR(IF($W$6="M",VLOOKUP($W$9,'TABCV(Male)'!$A$2:$QQ$431,AO37+206,FALSE),VLOOKUP($W$9,'TABCV(Female)'!$A$2:$QQ$431,AO37+206,FALSE)),0) -> 0 | AI76: PEN Year 63 | AJ76: PEN63 | AK76: =IFERROR(IF($W$6="M",VLOOKUP($W$9,'TABCV(Male)'!$A$2:$QQ$431,AO37+307,FALSE),VLOOKUP($W$9,'TABCV(Female)'!$A$2:$QQ$431,AO37+307,FALSE)),0) -> 0
U77: =IF(AC77-1000<0,0,AC77-1000) -> 0 | V77: =IF(AC77=0,0,IF(AC77>1000,1000,AC77)) -> 0 | W77: =IF(AG77=0,0,IF(LEN(AG77)<4,0,LEFT(AG77,(LEN(AG77)-3)))) -> 0 | X77: =IF(AG77=0,0,RIGHT(AG77,3)+0) -> 0 | Y77: =IF(AK77-1000<0,0,AK77-1000) -> 0 | Z77: =IF(AK77=0,0,IF(AK77>1000,1000,AK77)) -> 0 | AA77: RPU Year 64 | AB77: PVL64 | AC77: =IFERROR(IF($W$6="M",VLOOKUP($W$9,'TABCV(Male)'!$A$2:$QQ$431,AO38+105,FALSE),VLOOKUP($W$9,'TABCV(Female)'!$A$2:$QQ$431,AO38+105,FALSE)),0) -> 0 | AE77: ETI Year 64 | AF77: ETA64 | AG77: =IFERROR(IF($W$6="M",VLOOKUP($W$9,'TABCV(Male)'!$A$2:$QQ$431,AO38+206,FALSE),VLOOKUP($W$9,'TABCV(Female)'!$A$2:$QQ$431,AO38+206,FALSE)),0) -> 0 | AI77: PEN Year 64 | AJ77: PEN64 | AK77: =IFERROR(IF($W$6="M",VLOOKUP($W$9,'TABCV(Male)'!$A$2:$QQ$431,AO38+307,FALSE),VLOOKUP($W$9,'TABCV(Female)'!$A$2:$QQ$431,AO38+307,FALSE)),0) -> 0
U78: =IF(AC78-1000<0,0,AC78-1000) -> 0 | V78: =IF(AC78=0,0,IF(AC78>1000,1000,AC78)) -> 0 | W78: =IF(AG78=0,0,IF(LEN(AG78)<4,0,LEFT(AG78,(LEN(AG78)-3)))) -> 0 | X78: =IF(AG78=0,0,RIGHT(AG78,3)+0) -> 0 | Y78: =IF(AK78-1000<0,0,AK78-1000) -> 0 | Z78: =IF(AK78=0,0,IF(AK78>1000,1000,AK78)) -> 0 | AA78: RPU Year 65 | AB78: PVL65 | AC78: =IFERROR(IF($W$6="M",VLOOKUP($W$9,'TABCV(Male)'!$A$2:$QQ$431,AO39+105,FALSE),VLOOKUP($W$9,'TABCV(Female)'!$A$2:$QQ$431,AO39+105,FALSE)),0) -> 0 | AE78: ETI Year 65 | AF78: ETA65 | AG78: =IFERROR(IF($W$6="M",VLOOKUP($W$9,'TABCV(Male)'!$A$2:$QQ$431,AO39+206,FALSE),VLOOKUP($W$9,'TABCV(Female)'!$A$2:$QQ$431,AO39+206,FALSE)),0) -> 0 | AI78: PEN Year 65 | AJ78: PEN65 | AK78: =IFERROR(IF($W$6="M",VLOOKUP($W$9,'TABCV(Male)'!$A$2:$QQ$431,AO39+307,FALSE),VLOOKUP($W$9,'TABCV(Female)'!$A$2:$QQ$431,AO39+307,FALSE)),0) -> 0
U79: =IF(AC79-1000<0,0,AC79-1000) -> 0 | V79: =IF(AC79=0,0,IF(AC79>1000,1000,AC79)) -> 0 | W79: =IF(AG79=0,0,IF(LEN(AG79)<4,0,LEFT(AG79,(LEN(AG79)-3)))) -> 0 | X79: =IF(AG79=0,0,RIGHT(AG79,3)+0) -> 0 | Y79: =IF(AK79-1000<0,0,AK79-1000) -> 0 | Z79: =IF(AK79=0,0,IF(AK79>1000,1000,AK79)) -> 0 | AA79: RPU Year 66 | AB79: PVL66 | AC79: =IFERROR(IF($W$6="M",VLOOKUP($W$9,'TABCV(Male)'!$A$2:$QQ$431,AO40+105,FALSE),VLOOKUP($W$9,'TABCV(Female)'!$A$2:$QQ$431,AO40+105,FALSE)),0) -> 0 | AE79: ETI Year 66 | AF79: ETA66 | AG79: =IFERROR(IF($W$6="M",VLOOKUP($W$9,'TABCV(Male)'!$A$2:$QQ$431,AO40+206,FALSE),VLOOKUP($W$9,'TABCV(Female)'!$A$2:$QQ$431,AO40+206,FALSE)),0) -> 0 | AI79: PEN Year 66 | AJ79: PEN66 | AK79: =IFERROR(IF($W$6="M",VLOOKUP($W$9,'TABCV(Male)'!$A$2:$QQ$431,AO40+307,FALSE),VLOOKUP($W$9,'TABCV(Female)'!$A$2:$QQ$431,AO40+307,FALSE)),0) -> 0
... U113: =IF(AC113-1000<0,0,AC113-1000) -> 0 | V113: =IF(AC113=0,0,IF(AC113>1000,1000,AC113)) -> 0 | W113: =IF(AG113=0,0,IF(LEN(AG113)<4,0,LEFT(AG113,(LEN(AG113)-3)))) -> 0 | X113: =IF(AG113=0,0,RIGHT(AG113,3)+0) -> 0 | Y113: =IF(AK113-1000<0,0,AK113-1000) -> 0 | Z113: =IF(AK113=0,0,IF(AK113>1000,1000,AK113)) -> 0 | AA113: RPU Year 100 | AB113: PVL100 | AC113: =IFERROR(IF($W$6="M",VLOOKUP($W$9,'TABCV(Male)'!$A$2:$QQ$431,AO74+105,FALSE),VLOOKUP($W$9,'TABCV(Female)'!$A$2:$QQ$431,AO74+105,FALSE)),0) -> 0 | AE113: ETI Year 100 | AF113: ETA100 | AG113: =IFERROR(IF($W$6="M",VLOOKUP($W$9,'TABCV(Male)'!$A$2:$QQ$431,AO74+206,FALSE),VLOOKUP($W$9,'TABCV(Female)'!$A$2:$QQ$431,AO74+206,FALSE)),0) -> 0 | AI113: PEN Year 100 | AJ113: PEN100 | AK113: =IFERROR(IF($W$6="M",VLOOKUP($W$9,'TABCV(Male)'!$A$2:$QQ$431,AO74+307,FALSE),VLOOKUP($W$9,'TABCV(Female)'!$A$2:$QQ$431,AO74+307,FALSE)),0) -> 0

Sheet CI MED EX RATE
B1: Check | C1: OK
B2: Insure Age | C2: =กรอกข้อมูล!$C$5 -> 44 | D2: =IF(C2<11,"J","S") -> S | H2: เอเชีย | I2: A
B3: Gender | C3: =กรอกข้อมูล!$C$6 -> หญิง | D3: =IF(OR(C3="ชาย",C3="Male"),"M","F") -> F | H3: ทั่วโลก | I3: W
B4: แผนCI MED EX | D4: =กรอกข้อมูล!Z32 | H4: ประเทศไทย
B5: Coverage | C5: Full Coverage | D5: =IFERROR(IF(C5="Full Coverage","",IF(C5="Deductible","D",IF(C5="Co-Payment","C",""))),"")
B6: Cover | C6: ประเทศไทย | D6: =VLOOKUP($C6,H2:I4,2,FALSE)
B7: Key | D7: =TRIM("MCI"&D4) -> MCI | E7: =D7&"-"&D3 -> MCI-F | Z7: Copayment | AX7: Deductible
B8: Premium | D8: =IF(C1="OK",HLOOKUP(E7,$B$9:$I$111,C2+5,0),0) -> #N/A
A9: Key | B9: MCI1-M | C9: MCI1-F | D9: MCI2-M | E9: MCI2-F | F9: MCI3-M | G9: MCI3-F | H9: MCI4-M | I9: MCI4-F
A10: Plan code | B10: MCI1 | C10: MCI1 | D10: MCI2 | E10: MCI2 | F10: MCI3 | G10: MCI3 | H10: MCI4 | I10: MCI4
A11: Class | B11: 1 | C11: 1 | D11: 1 | E11: 1 | F11: 1 | G11: 1 | H11: 1 | I11: 1
A12: Gender | B12: M | C12: F | D12: M | E12: F | F12: M | G12: F | H12: M | I12: F
A13: 0 | B13: 1110 | C13: 912 | D13: 1279 | E13: 1014 | F13: 0 | G13: 0 | H13: 0 | I13: 0
A14: 1 | B14: 1051 | C14: 880 | D14: 1203 | E14: 975 | F14: 0 | G14: 0 | H14: 0 | I14: 0
A15: 2 | B15: 998 | C15: 847 | D15: 1136 | E15: 941 | F15: 0 | G15: 0 | H15: 0 | I15: 0
A16: 3 | B16: 951 | C16: 818 | D16: 1079 | E16: 906 | F16: 0 | G16: 0 | H16: 0 | I16: 0
A17: 4 | B17: 831 | C17: 747 | D17: 924 | E17: 814 | F17: 0 | G17: 0 | H17: 0 | I17: 0
A18: 5 | B18: 715 | C18: 674 | D18: 780 | E18: 725 | F18: 0 | G18: 0 | H18: 0 | I18: 0
A19: 6 | B19: 674 | C19: 647 | D19: 725 | E19: 692 | F19: 0 | G19: 0 | H19: 0 | I19: 0
A20: 7 | B20: 649 | C20: 633 | D20: 698 | E20: 674 | F20: 0 | G20: 0 | H20: 0 | I20: 0
A21: 8 | B21: 641 | C21: 629 | D21: 688 | E21: 670 | F21: 0 | G21: 0 | H21: 0 | I21: 0
A22: 9 | B22: 595 | C22: 588 | D22: 627 | E22: 617 | F22: 0 | G22: 0 | H22: 0 | I22: 0
A23: 10 | B23: 552 | C23: 550 | D23: 576 | E23: 572 | F23: 0 | G23: 0 | H23: 0 | I23: 0
A24: 11 | B24: 568 | C24: 566 | D24: 597 | E24: 592 | F24: 878 | G24: 869 | H24: 1012 | I24: 998
... A111: 98 | B111: 85836 | C111: 68087 | D111: 138046 | E111: 98054 | F111: 286767 | G111: 217946 | H111: 529903 | I111: 385570

Sheet Cal
M1: ขั้นอาชีพ | N1: AP | O1: ECARE
A2: Issue Age | B2: =กรอกข้อมูล!C5 -> 44 | F2: ชาย | G2: M | I2: รายปี | J2: 1 | K2: 1 | M2: 1 | N2: 3 | O2: 6.5
A3: Gender | B3: =กรอกข้อมูล!C6 -> หญิง | C3: =VLOOKUP(B3,$F$2:$G$3,2,FALSE) -> F | F3: หญิง | G3: F | I3: ราย 6 เดือน | J3: 0.52 | K3: 2 | M3: 2 | N3: 4.05 | O3: 7.5
A4: Mode | B4: =กรอกข้อมูล!C7 -> รายปี | C4: =VLOOKUP(B4,$I$2:$K$5,2,FALSE) -> 1 | D4: =VLOOKUP(B4,$I$2:$K$5,3,FALSE) -> 1 | I4: ราย 3 เดือน | J4: 0.27 | K4: 4 | M4: 3 | N4: 5.1 | O4: 8.5
I5: รายเดือน | J5: 0.09 | K5: 12 | M5: 4 | N5: 6 | O5: 10.5
A6: PPP of basic plan | B6: =กรอกข้อมูล!K14 -> 6
A8: Issue Age (payor) | B8: =กรอกข้อมูล!C11 -> 0 | N8: WPDD01 | O8: Max age of payor
A9: Gender (payor) | B9: =กรอกข้อมูล!C12 -> 0 | C9: =IFERROR(IF(B8>0,VLOOKUP(B9,$F$2:$G$3,2,FALSE),0),"") -> 0 | D9: Coverage period | E9: Payment payment term | F9: period to waive premium | N9: 10 | O9: =65-N9 -> 55
A10: ="PB "&IF(B2<=15,"Parent","Spouse")&" Payor" -> PB Spouse Payor | D10: =IF(B2<=15,MIN(B6,80-B8,25-B2),MIN(B6,80-B8)) -> 6 | E10: =D10 -> 6 | F10: =IF(B2<=15,MIN(B6,25-B2),B6) -> 6 | N10: 11 | O10: =65-N10 -> 54
A11: WP | D11: =MIN(B6,80-B2) -> 6 | E11: =D11 -> 6 | F11: =B6 -> 6 | N11: 12 | O11: =65-N11 -> 53
A12: Product | C12: SA | D12: Rate | E12: Occ Class | F12: High SA Discount | G12: Premium (Ann) | H12: Premium (Mode) | I12: Premium (Ann) for WP | N12: 13 | O12: =65-N12 -> 52
A13: =กรอกข้อมูล!$F$78 -> W80F06 | B13: =VLOOKUP($A13,$N$27:$O$34,2,FALSE)&C3 -> 06F | C13: =IF(กรอกข้อมูล!J22="no",0,กรอกข้อมูล!D19) -> 1000000 | D13: =HLOOKUP(B13,'Premium&Maturity'!$A$2:$C$86,B2+5,0) -> 287 | F13: 0 | G13: =ROUNDDOWN((D13-F13+E13)*ROUNDDOWN(C13/1000,3),2) -> 287000 | H13: =ROUNDDOWN(G13*$C$4,2) -> 287000 | I13: =ROUNDDOWN((D13-F13+E13)*ROUNDDOWN(IF(C13>30000000,30000000,C13)/1000,3),2) -> 287000 | N13: 14 | O13: =65-N13 -> 51
A14: =กรอกข้อมูล!J20 -> PBSDDCI | B14: =A14&C9&B8 -> PBSDDCI00 | C14: =IF(กรอกข้อมูล!D20="ซื้อ",Cal!I13,0) -> 0 | D14: =IF(OR(กรอกข้อมูล!D20="",กรอกข้อมูล!D20="ไม่ซื้อ",กรอกข้อมูล!B20="ไม่สามารถซื้อได้",กรอกข้อมูล!B20="กรอกอายุผู้ชำระเบี้ย",กรอกข้อมูล!B20="กรอกเพศผู้ชำระเบี้ย"),0,ROUND(IF($B$2<=15,VLOOKUP($B$14,'Rate PB'!$C$5:$AB$227,Cal!$F$10+1,FALSE),IF($B$2>=16,VLOOKUP($B$14,'Rate PB'!$C$231:$CH$437,Cal!$F$10+1,FALSE)))*IF(E14=0,1,E14),2)) -> 0 | E14: =กรอกข้อมูล!E20 -> 1 | G14: =TRUNC($D$14*TRUNC($C$14/100,3),2) -> 0 | H14: =TRUNC(TRUNC($D$14*TRUNC($C$14/100,3),2)*$C$4,2) -> 0 | N14: 15 | O14: =65-N14 -> 50
A15: =กรอกข้อมูล!J21 -> WPTPD | B15: =A15&C3&B2 -> WPTPDF44 | C15: =IF(กรอกข้อมูล!D21="ซื้อ",Cal!I13,0) -> 0 | D15: =IFERROR(ROUND(IF(C3="M",VLOOKUP($B$15,'Rate WP'!$A$5:$CF$119,$B$6+1,0),VLOOKUP($B$15,'Rate WP'!$CH$4:$FM$119,Cal!$B$6+1,0))*IF(E15=0,1,E15),2),0) -> 0.08 | E15: =กรอกข้อมูล!E21 -> 1 | G15: =TRUNC($D$15*TRUNC($C$15/100,3),2) -> 0 | H15: =TRUNC(TRUNC($D$15*TRUNC($C$15/100,3),2)*$C$4,2) -> 0 | N15: 16 | O15: =65-N15 -> 49
A16: =กรอกข้อมูล!A22 -> AP | C16: =กรอกข้อมูล!D22 -> 0 | D16: =IF(กรอกข้อมูล!B22="ไม่สามารถซื้อได้",0,IFERROR(VLOOKUP(E16,'Rate Rider'!$AB$3:$AD$6,2,FALSE),0)) -> 3 | E16: =กรอกข้อมูล!E22 -> 1 | G16: =ROUNDDOWN(D16*C16/1000,2) -> 0 | H16: =ROUNDDOWN(G16*$C$4,2) -> 0 | N16: 17 | O16: =65-N16 -> 48
A17: =กรอกข้อมูล!A23 -> ECARE | C17: =กรอกข้อมูล!D23 -> 0 | D17: =IF(กรอกข้อมูล!B23="ไม่สามารถซื้อได้",0,IFERROR(VLOOKUP(E17,'Rate Rider'!$AB$3:$AD$6,3,FALSE),0)) -> 6.5 | E17: =กรอกข้อมูล!E23 -> 1 | G17: =ROUNDDOWN(D17*C17/1000,2) -> 0 | H17: =ROUNDDOWN(G17*$C$4,2) -> 0 | N17: 18 | O17: =65-N17 -> 47
N18: 19 | O18: =65-N18 -> 46
A19: =กรอกข้อมูล!A25 -> MEB | C19: =กรอกข้อมูล!D25 -> 500 | D19: =IF(OR(กรอกข้อมูล!B25="ไม่สามารถซื้อได้",C19=0),0,INDEX('Rate Rider'!$A$4:$G$73,MATCH(B2,'Rate Rider'!$A$4:$A$73,),MATCH(C19,'Rate Rider'!$A$4:$G$4,)))*IF(E19=4,1.5,1) -> 750 | E19: =กรอกข้อมูล!E25 -> 1 | G19: =D19 -> 750 | H19: =ROUNDDOWN(G19*$C$4,2) -> 750 | N19: 20 | O19: =65-N19 -> 45
A20: =กรอกข้อมูล!A26 -> DCI | B20: =A20&"-"&$B$2 -> DCI-44 | C20: =กรอกข้อมูล!D26 -> 0 | D20: =IF(กรอกข้อมูล!B26="ไม่สามารถซื้อได้",0,(INDEX('Rate Rider'!$X$2:$Z$257,MATCH(Cal!B20,'Rate Rider'!$X$2:$X$257,),MATCH(Cal!$C$3,'Rate Rider'!$X$2:$Z$2,)))) -> 5.8 | G20: =ROUNDDOWN((D20-F20)*C20/1000,2) -> 0 | H20: =ROUNDDOWN(G20*$C$4,2) -> 0 | N20: 21 | O20: =65-N20 -> 44
A21: =กรอกข้อมูล!A27 -> PLS10 | B21: =A21&"-"&$B$2 -> PLS10-44 | C21: =กรอกข้อมูล!D27 -> 0 | D21: =IF(กรอกข้อมูล!B27="ไม่สามารถซื้อได้",0,IFERROR(INDEX('Rate Rider'!$X$2:$Z$257,MATCH(Cal!B21,'Rate Rider'!$X$2:$X$257,),MATCH(Cal!$C$3,'Rate Rider'!$X$2:$Z$2,)),0)) -> 4.1 | F21: =IF(D21=0,0,IF(C21>=1000000,1,IF(C21>=500000,0.5,0))) -> 0 | G21: =ROUNDDOWN((D21-F21)*C21/1000,2) -> 0 | H21: =ROUNDDOWN(G21*$C$4,2) -> 0 | J21: =VALUE(MID(A21,4,2)) -> 10 | N21: 22 | O21: =65-N21 -> 43
A22: MEX | B22: =IF(C22>0,C3&"-"&C22,0) -> 0 | C22: =IF(กรอกข้อมูล!H24="ไม่คุ้มครอง",0,กรอกข้อมูล!D24) -> 0 | D22: =IF(OR(กรอกข้อมูล!B24="ไม่สามารถซื้อได้",C22=0),0,INDEX('Rate rider_MEX'!$A$5:$K$95,MATCH($B$2,'Rate rider_MEX'!$A$5:$A$95,),MATCH($B$22,'Rate rider_MEX'!$A$5:$K$5,)))*IF(E22=4,1.5,1) -> 0 | E22: =กรอกข้อมูล!E24 -> 1 | G22: =D22 -> 0 | H22: =ROUNDDOWN(G22*$C$4,2) -> 0 | N22: 23 | O22: =65-N22 -> 42
A23: MHP | E23: =กรอกข้อมูล!E30 -> 1 | G23: ='iHealthy Ultra Rate'!$D$8*IF(E23=4,1.5,1) -> 0 | H23: =ROUNDDOWN(G23*$C$4,2) -> 0 | N23: 24 | O23: =65-N23 -> 41
A24: MCI | E24: =กรอกข้อมูล!F43 -> 0 | G24: ='CI MED EX RATE'!D8*IF(E24=4,1.5,1) -> #N/A | H24: =ROUNDDOWN(G24*$C$4,2) -> #N/A | N24: 25 | O24: =65-N24 -> 40
A25: CIES | H25: =กรอกข้อมูล!AH28 -> 44789.5
N26: Plan Code | O26: Payment Term
B27: 06 | C27: 12 | D27: 18 | E27: 99 | N27: W80F06 | O27: 06
A28: 300000 | B28: 0 | C28: 0 | D28: 0.5 | E28: 0.5 | N28: W99FU12 | O28: 12
A29: 500000 | B29: 2 | C29: 2 | D29: 0.5 | E29: 0.5 | N29: W99FU18 | O29: 18
A30: 700000 | B30: 2 | C30: 2 | D30: 0.5 | E30: 0.5 | N30: W99FH18 | O30: 18
A31: 1000000 | B31: 3 | C31: 3 | D31: 1 | E31: 1 | N31: W99FU99 | O31: 99
A32: 3000000 | B32: 4 | C32: 4 | D32: 1.5 | E32: 1.5 | N32: W99FH99 | O32: 99
A33: 5000000 | B33: 4 | C33: 4 | D33: 1.5 | E33: 1.5 | N33: W99F99H | O33: 99H
A34: High SA Discount | B34: =IF($C$13>=$A$33,B33,IF($C$13>=$A$32,B32,IF($C$13>=$A$31,B31,IF($C$13>=$A$30,B30,IF($C$13>=$A$29,B29,IF($C$13>=$A$28,B28,0)))))) -> 3 | C34: =IF($C$13>=$A$33,C33,IF($C$13>=$A$32,C32,IF($C$13>=$A$31,C31,IF($C$13>=$A$30,C30,IF($C$13>=$A$29,C29,IF($C$13>=$A$28,C28,0)))))) -> 3 | D34: =IF($C$13>=$A$33,D33,IF($C$13>=$A$32,D32,IF($C$13>=$A$31,D31,IF($C$13>=$A$30,D30,IF($C$13>=$A$29,D29,IF($C$13>=$A$28,D28,0)))))) -> 1 | E34: =IF($C$13>=$A$33,E33,IF($C$13>=$A$32,E32,IF($C$13>=$A$31,E31,IF($C$13>=$A$30,E30,IF($C$13>=$A$29,E29,IF($C$13>=$A$28,E28,0)))))) -> 1 | N34: W99F99M | O34: 99M
A36: Product | C36: SA | D36: Rate | E36: Occ Class | F36: discount | G36: Premium (Ann) | H36: Premium (Mode) | I36: Premium Tax per year | K36: Total Tax Deduct | N36: from product Spec : WP
A37: =กรอกข้อมูล!A28 -> CPR | B37: =A37&"-"&$B$2 -> CPR-44 | C37: =กรอกข้อมูล!D28 -> 0 | D37: =IF(OR(กรอกข้อมูล!B28="ไม่สามารถซื้อได้",กรอกข้อมูล!B28="ไม่สามารถซื้อคู่กับ DCI ได้"),0,INDEX('Rate Rider'!$Y$258:$Z$342,MATCH(Cal!$B37,'Rate Rider'!$X$258:$X$342,),MATCH(Cal!$C$3,'Rate Rider'!$Y$2:$Z$2,))) -> 3.91 | E37: None | G37: =ROUNDDOWN(D37*C37/1000,2) -> 0 | H37: =ROUNDDOWN(G37*$C$4,2) -> 0
A38: =กรอกข้อมูล!A29 -> HIC | B38: =A38&"-"&$B$2 -> HIC-44 | C38: =IF(กรอกข้อมูล!H29="ไม่คุ้มครอง",0,กรอกข้อมูล!D29) -> 0 | D38: =IF(OR(กรอกข้อมูล!B29="ไม่สามารถซื้อได้",กรอกข้อมูล!B29="ไม่สามารถซื้อคู่กับ DCI ได้",กรอกข้อมูล!B29="ต้องซื้อคู่กับ CPR",กรอกข้อมูล!B29="ไม่สามารถซื้อคู่กับ MEA+หรือ MEB"),0,INDEX('Rate Rider'!$Y$343:$Z$427,MATCH(Cal!$B38,'Rate Rider'!$X$343:$X$427,),MATCH(Cal!$C$3,'Rate Rider'!$Y$2:$Z$2,))) -> 41.77 | E38: None | G38: =ROUND((D38*C38)/1000,2) -> 0 | H38: =ROUNDDOWN(G38*$C$4,2) -> 0
A43: Confirm final formula for new WP / PB
N48: PB Parent
A57: Final Formular แก้เพื่อให้ตรงกับ RLS
N66: PB Spouse
B104: 10WL
B144: LifeReady (Non-Participating)'2022
B145: Large Sum Assured Discount ( LSAD ) per 1000 SA | C145: 6 Pay | D145: 12 Pay | E145: 18 Pay | F145: 99 Pay
C146: 500k – 999k : 2.00 | E146: 300k - 999k : 0.50
C147: 1M - 2.99M : 3.00 | E147: 1M - 2.99M : 1.00
C148: 3M & above: 4.00 | E148: 3M & above: 1.50
B153: 9. Premium amount
B154: = ROUNDDOWN (ROUNDDOWN ( ( ( ( STD PREMIUM – LSAD) x (1-%STAFF DISCOUNT ) ) + SUB STD PREMIUM + TEMP LOADING ) x SA/1,000 ,2 decimal places) x Modal factor, 2 decimal places)
B155: = ROUNDDOWN (ROUNDDOWN ( ( ( ( 76 – 3) x (1-0% ) ) + 7.14 + 0 ) x SA/1,000 , 2 decimal places) x Modal factor, 2 decimal places)
B156: = ROUNDDOWN ( ROUNDDOWN (( 76 – 3 + 7.14 + 0 ) x 1,000,000/1,000 , 2 decimal places) x 1 , 2 decimal places)
B157: = ROUNDDOWN ( ROUNDDOWN (( 80.14 ) x 1,000,000/1,000, 2 decimal places) x 1 , 2 decimal places)
B158: = 80,140 THB
B160: Require Product Implementation team to confirm system formula to cap max Staff discount at 30% following OIC rule.
B161: We can go by have communication with OIC to provide the Total Commission over Total Premium paid during the premium payment terms are not over 30% . > No need to cap max at 30% and provide staff discount following as Commission which calculated from Standard premium after High Sum Assured Discount.
B162: Require Product Implementation team to confirm system formula to cap max Staff discount at 30% following OIC rule.

Sheet Premium&Maturity
A2: Key | B2: 06M | C2: 06F
A3: Plan Code | B3: W80F06 | C3: W80F06
A4: Class | B4: S | C4: S
A5: Gender | B5: M | C5: F
A6: 0 | B6: - | C6: -
A7: 1 | B7: - | C7: -
A8: 2 | B8: - | C8: -
A9: 3 | B9: - | C9: -
A10: 4 | B10: - | C10: -
A11: 5 | B11: - | C11: -
A12: 6 | B12: - | C12: -
A13: 7 | B13: - | C13: -
A14: 8 | B14: - | C14: -
A15: 9 | B15: - | C15: -
A16: 10 | B16: - | C16: -
A17: 11 | B17: - | C17: -
... A21: 15 | B21: - | C21: -
A22: 16 | B22: - | C22: - | G22: f | H22: 244 | I22: 245 | J22: 247 | K22: 249 | L22: 251 | M22: 253 | N22: 254 | O22: 256 | P22: 259 | Q22: 261 | R22: 263 | S22: 265 | T22: 267 | U22: 270 | V22: 273 | W22: 276 | X22: 278 | Y22: 281 | Z22: 284 | AA22: 287 | AB22: 289 | AC22: 292 | AD22: 295 | AE22: 299 | AF22: 303 | AG22: 307 | AH22: 311 | AI22: 315 | AJ22: 319 | AK22: 323 | AL22: 327 | AM22: 332 | AN22: 338 | AO22: 345 | AP22: 355 | AQ22: 375 | AR22: 405 | AS22: 440 | AT22: 475 | AU22: 510 | AV22: 545
A23: 17 | B23: - | C23: - | G23: m | H23: 256 | I23: 257 | J23: 259 | K23: 261 | L23: 263 | M23: 265 | N23: 267 | O23: 269 | P23: 272 | Q23: 275 | R23: 277 | S23: 280 | T23: 282 | U23: 285 | V23: 288 | W23: 290 | X23: 293 | Y23: 296 | Z23: 299 | AA23: 302 | AB23: 305 | AC23: 309 | AD23: 313 | AE23: 316 | AF23: 319 | AG23: 323 | AH23: 327 | AI23: 330 | AJ23: 334 | AK23: 338 | AL23: 347 | AM23: 365 | AN23: 389 | AO23: 414 | AP23: 439 | AQ23: 469 | AR23: 504 | AS23: 539 | AT23: 574 | AU23: 609 | AV23: 644
A24: 18 | B24: - | C24: -
A25: 19 | B25: - | C25: -
A26: 20 | B26: - | C26: -
A27: 21 | B27: - | C27: -
A28: 22 | B28: - | C28: -
A29: 23 | B29: - | C29: -
A30: 24 | B30: - | C30: -
A31: 25 | B31: 256 | C31: 244
A32: 26 | B32: 257 | C32: 245
A33: 27 | B33: 259 | C33: 247
A34: 28 | B34: 261 | C34: 249
A35: 29 | B35: 263 | C35: 251
A36: 30 | B36: 265 | C36: 253
A37: 31 | B37: 267 | C37: 254
A38: 32 | B38: 269 | C38: 256
A39: 33 | B39: 272 | C39: 259
A40: 34 | B40: 275 | C40: 261
A41: 35 | B41: 277 | C41: 263
A42: 36 | B42: 280 | C42: 265
... A71: 65 | B71: 644 | C71: 545
A72: 66 | B72: - | C72: -
A73: 67 | B73: - | C73: -
A74: 68 | B74: - | C74: -
A75: 69 | B75: - | C75: -
A76: 70 | B76: - | C76: -
A77: 71 | B77: - | C77: -
A78: 72 | B78: - | C78: -
A79: 73 | B79: - | C79: -
A80: 74 | B80: - | C80: -
A81: 75 | B81: - | C81: -
A82: 76 | B82: - | C82: -
A83: 77 | B83: - | C83: -
... A86: 80 | B86: - | C86: -

Sheet Product Category Tax Deduct
I1: Deductible Amount
C2: Premium per mode | D2: Premium per year | E2: Tax Code | F2: Deductible Ratio | I2: Life/Retirement | J2: Health | K2: Non TAX | L2: Total | M2: Premium from Fill Info | N2: check Diff | Z2: L | AA2: H | AB2: NT
A3: Product Code | B3: Type | F3: Life | G3: Health | H3: Non Tax | I3: =IF(N28="no",0,SUM(I4:I29)) -> 287000 | J3: =IF(N28="no",0,SUM(J4:J29)) -> 44789.5 | K3: =IF(N28="no",0,SUM(K4:K29)) -> 750 | L3: =SUM(I3:K3) -> 332539.5 | M3: =IF(N28="no",0,กรอกข้อมูล!$F$37*N7) -> 332539.5 | N3: =+M3-L3 -> 0 | R3: key | S3: Plan Code | T3: Min Age | U3: Max Age | V3: Sex | W3: Std / EM | X3: Min Occ.Class | Y3: Max Occ.Class | Z3: % Life Tax | AA3: % Health | AB3: % Non-Tax
A4: =Cal!$A$13 -> W80F06 | B4: Basic | C4: =IFERROR(VLOOKUP(A4,Cal!$A$13:$H$42,8,FALSE),0) -> 287000 | D4: =+C4*$N$7 -> 287000 | E4: L | F4: 1 | G4: 0 | H4: 0 | I4: =IFERROR(ROUND(F4*D4,2),0) -> 287000 | J4: =IFERROR(ROUND(G4*D4,2),0) -> 0 | K4: =IFERROR(ROUND(H4*D4,2),0) -> 0 | L4: =+D4-I4-J4-K4 -> 0 | M4: Insure Issue Age | N4: =กรอกข้อมูล!$C$5 -> 44 | R4: 12PL | S4: 12PL | Z4: 1 | AA4: 0 | AB4: 0
A5: =Cal!A14 -> PBSDDCI | B5: Rider | C5: =IF(กรอกข้อมูล!$H$20="ไม่คุ้มครอง",0,IFERROR(VLOOKUP(A5,Cal!$A$13:$H$42,8,FALSE),0)) -> 0 | D5: =+C5*$N$7 -> 0 | E5: N/A | F5: 0 | G5: 0 | H5: 1 | I5: =IFERROR(ROUND(F5*D5,2),0) -> 0 | J5: =IFERROR(ROUND(G5*D5,2),0) -> 0 | K5: =IFERROR(ROUND(H5*D5,2),0) -> 0 | L5: =+D5-I5-J5-K5 -> 0 | M5: Insure Gender | N5: =IF(OR(กรอกข้อมูล!$C$6="ชาย",กรอกข้อมูล!$C$6="Male"),"M","F") -> F | R5: 25PG | S5: 25PG | Z5: 1 | AA5: 0 | AB5: 0
A6: =Cal!A15 -> WPTPD | B6: Rider | C6: =IF(กรอกข้อมูล!$H$21="ไม่คุ้มครอง",0,IFERROR(VLOOKUP(A6,Cal!$A$13:$H$42,8,FALSE),0)) -> 0 | D6: =+C6*$N$7 -> 0 | E6: N/A | F6: 0 | G6: 0 | H6: 1 | I6: =IFERROR(ROUND(F6*D6,2),0) -> 0 | J6: =IFERROR(ROUND(G6*D6,2),0) -> 0 | K6: =IFERROR(ROUND(H6*D6,2),0) -> 0 | L6: =+D6-I6-J6-K6 -> 0 | M6: Mode | N6: =กรอกข้อมูล!$C$7 -> รายปี | O6: =VLOOKUP($N6,$M$23:$N$26,2,FALSE) -> A | R6: PR60 | S6: PR60 | Z6: 1 | AA6: 0 | AB6: 0
M7: Times per year | N7: =VLOOKUP($O6,$N$23:$P$26,3,FALSE) -> 1 | R7: PLB05 | S7: PLB05 | Z7: 0 | AA7: 0 | AB7: 1
A8: AP | B8: Rider | C8: =IF(กรอกข้อมูล!$H$22="ไม่คุ้มครอง",0,IFERROR(VLOOKUP(A8,Cal!$A$13:$H$42,8,FALSE),0)) -> 0 | D8: =+C8*$N$7 -> 0 | E8: H | F8: 0 | G8: =IF($A8="20SS",VLOOKUP($A8&$N$4&$N$5,$R:$AB,10,FALSE),VLOOKUP($A8,$R:$AB,10,FALSE)) -> 0.1818 | H8: =IF(OR($A8="20SS",LEFT($A8,4)="WLCI"),VLOOKUP($A8&$N$4&$N$5,$R:$AB,11,FALSE),VLOOKUP($A8,$R:$AB,11,FALSE)) -> 0.8182 | I8: =IFERROR(ROUND(F8*D8,2),0) -> 0 | J8: =IFERROR(ROUND(G8*D8,2),0) -> 0 | K8: =IFERROR(ROUND(H8*D8,2),0) -> 0 | L8: =+D8-I8-J8-K8 -> 0 | M8: Basic can Deductible Life | R8: PLB10 | S8: PLB10 | Z8: 1 | AA8: 0 | AB8: 0
A9: ECARE | B9: Rider | C9: =IF(กรอกข้อมูล!$H$23="ไม่คุ้มครอง",0,IFERROR(VLOOKUP(A9,Cal!$A$13:$H$42,8,FALSE),0)) -> 0 | D9: =+C9*$N$7 -> 0 | E9: H | F9: 0 | G9: =IF($A9="20SS",VLOOKUP($A9&$N$4&$N$5,$R:$AB,10,FALSE),VLOOKUP($A9,$R:$AB,10,FALSE)) -> 0.6982 | H9: =IF(OR($A9="20SS",LEFT($A9,4)="WLCI"),VLOOKUP($A9&$N$4&$N$5,$R:$AB,11,FALSE),VLOOKUP($A9,$R:$AB,11,FALSE)) -> 0.3018 | I9: =IFERROR(ROUND(F9*D9,2),0) -> 0 | J9: =IFERROR(ROUND(G9*D9,2),0) -> 0 | K9: =IFERROR(ROUND(H9*D9,2),0) -> 0 | L9: =+D9-I9-J9-K9 -> 0 | R9: PLB15 | S9: PLB15 | Z9: 1 | AA9: 0 | AB9: 0
A10: MEA+ | B10: Rider | C10: =IFERROR(VLOOKUP(A10,Cal!$A$13:$H$42,8,FALSE),0) -> 0 | D10: =+C10*$N$7 -> 0 | E10: H | F10: 0 | G10: 1 | H10: 0 | I10: =IFERROR(ROUND(F10*D10,2),0) -> 0 | J10: =IFERROR(ROUND(G10*D10,2),0) -> 0 | K10: =IFERROR(ROUND(H10*D10,2),0) -> 0 | L10: =+D10-I10-J10-K10 -> 0 | M10: Max Life Tax | N10: 100000 | R10: PLB20 | S10: PLB20 | Z10: 1 | AA10: 0 | AB10: 0
A11: MEB | B11: Rider | C11: =IF(กรอกข้อมูล!$H$25="ไม่คุ้มครอง",0,IFERROR(VLOOKUP(A11,Cal!$A$13:$H$42,8,FALSE),0)) -> 750 | D11: =+C11*$N$7 -> 750 | E11: N/A | F11: 0 | G11: 0 | H11: 1 | I11: =IFERROR(ROUND(F11*D11,2),0) -> 0 | J11: =IFERROR(ROUND(G11*D11,2),0) -> 0 | K11: =IFERROR(ROUND(H11*D11,2),0) -> 750 | L11: =+D11-I11-J11-K11 -> 0 | M11: Max Health Tax | N11: 25000 | R11: WLNP85 | S11: WLNP85 | Z11: 1 | AA11: 0 | AB11: 0
A12: PLS05 | B12: Rider | C12: =IF(กรอกข้อมูล!$H$27="ไม่คุ้มครอง",0,IFERROR(VLOOKUP(A12,Cal!$A$13:$H$42,8,FALSE),0)) -> 0 | D12: =+C12*$N$7 -> 0 | E12: N/A | F12: 0 | G12: 0 | H12: 1 | I12: =IFERROR(ROUND(F12*D12,2),0) -> 0 | J12: =IFERROR(ROUND(G12*D12,2),0) -> 0 | K12: =IFERROR(ROUND(H12*D12,2),0) -> 0 | L12: =+D12-I12-J12-K12 -> 0 | M12: Health Tax is under Life Limit | N12: 1 | O12: 1 = Health รวมใน Life | R12: WL88J | S12: WL88J | Z12: 1 | AA12: 0 | AB12: 0
A13: PLS10 | B13: Rider | C13: =IF(กรอกข้อมูล!$H$27="ไม่คุ้มครอง",0,IFERROR(VLOOKUP(A13,Cal!$A$13:$H$42,8,FALSE),0)) -> 0 | D13: =+C13*$N$7 -> 0 | E13: L | F13: 1 | G13: 0 | H13: 0 | I13: =IFERROR(ROUND(F13*D13,2),0) -> 0 | J13: =IFERROR(ROUND(G13*D13,2),0) -> 0 | K13: =IFERROR(ROUND(H13*D13,2),0) -> 0 | L13: =+D13-I13-J13-K13 -> 0 | M13: Max Retirement Tax Deductible | N13: 200000 | R13: WL88S | S13: WL88S | Z13: 1 | AA13: 0 | AB13: 0
A14: PLS12 | B14: Rider | C14: =IF(กรอกข้อมูล!$H$27="ไม่คุ้มครอง",0,IFERROR(VLOOKUP(A14,Cal!$A$13:$H$42,8,FALSE),0)) -> 0 | D14: =+C14*$N$7 -> 0 | E14: L | F14: 1 | G14: 0 | H14: 0 | I14: =IFERROR(ROUND(F14*D14,2),0) -> 0 | J14: =IFERROR(ROUND(G14*D14,2),0) -> 0 | K14: =IFERROR(ROUND(H14*D14,2),0) -> 0 | L14: =+D14-I14-J14-K14 -> 0 | R14: PWLNP60 | S14: PWLNP60 | Z14: 1 | AA14: 0 | AB14: 0
A15: PLS15 | B15: Rider | C15: =IF(กรอกข้อมูล!$H$27="ไม่คุ้มครอง",0,IFERROR(VLOOKUP(A15,Cal!$A$13:$H$42,8,FALSE),0)) -> 0 | D15: =+C15*$N$7 -> 0 | E15: L | F15: 1 | G15: 0 | H15: 0 | I15: =IFERROR(ROUND(F15*D15,2),0) -> 0 | J15: =IFERROR(ROUND(G15*D15,2),0) -> 0 | K15: =IFERROR(ROUND(H15*D15,2),0) -> 0 | L15: =+D15-I15-J15-K15 -> 0 | M15: Life Tax Deductible | N15: =IF(N10>I3,I3,N10) -> 100000 | P15: =N10-(N15+N16) -> 0 | R15: PWLNP85 | S15: PWLNP85 | Z15: 1 | AA15: 0 | AB15: 0
A16: CPR | B16: Rider | C16: =IF(กรอกข้อมูล!$H$28="ไม่คุ้มครอง",0,IFERROR(VLOOKUP(A16,Cal!$A$13:$H$42,8,FALSE),0)) -> 0 | D16: =+C16*$N$7 -> 0 | E16: N/A | F16: 0 | G16: 1 | H16: 0 | I16: =IFERROR(ROUND(F16*D16,2),0) -> 0 | J16: =IFERROR(ROUND(G16*D16,2),0) -> 0 | K16: =IFERROR(ROUND(H16*D16,2),0) -> 0 | L16: =+D16-I16-J16-K16 -> 0 | M16: Retirement Tax Deductible (> 200,000) | N16: =MIN(N10-N15,K3-N20) -> 0 | R16: FWLNP85 | S16: FWLNP85 | Z16: 1 | AA16: 0 | AB16: 0
A17: HIC | B17: Rider | C17: =IF(กรอกข้อมูล!$H$29="ไม่คุ้มครอง",0,IFERROR(VLOOKUP(A17,Cal!$A$13:$H$42,8,FALSE),0)) -> 0 | D17: =+C17*$N$7 -> 0 | E17: N/A | F17: 0 | G17: 0 | H17: 1 | I17: =IFERROR(ROUND(F17*D17,2),0) -> 0 | J17: =IFERROR(ROUND(G17*D17,2),0) -> 0 | K17: =IFERROR(ROUND(H17*D17,2),0) -> 0 | L17: =+D17-I17-J17-K17 -> 0 | R17: WLNP60L | S17: WLNP60L | Z17: 1 | AA17: 0 | AB17: 0
A18: WPC | B18: Rider | C18: =IFERROR(VLOOKUP(A18,Cal!$A$13:$H$42,8,FALSE),0) -> 0 | D18: =+C18*$N$7 -> 0 | E18: N/A | F18: 0 | G18: 0 | H18: 1 | I18: =IFERROR(ROUND(F18*D18,2),0) -> 0 | J18: =IFERROR(ROUND(G18*D18,2),0) -> 0 | K18: =IFERROR(ROUND(H18*D18,2),0) -> 0 | L18: =+D18-I18-J18-K18 -> 0 | M18: Total Life Tax Deductible | N18: =N15+N16 -> 100000 | R18: WLNP99L | S18: WLNP99L | Z18: 1 | AA18: 0 | AB18: 0
A19: DCI | B19: Rider | C19: =IF(กรอกข้อมูล!$H$26="ไม่คุ้มครอง",0,IFERROR(VLOOKUP(A19,Cal!$A$13:$H$42,8,FALSE),0)) -> 0 | D19: =+C19*$N$7 -> 0 | E19: H | F19: =IFERROR(VLOOKUP($A19&$N$4&$N$5,$R:$AB,9,FALSE),0) -> 0 | G19: =IFERROR(VLOOKUP($A19&$N$4&$N$5,$R:$AB,10,FALSE),0) -> 0.8685 | H19: =IFERROR(VLOOKUP($A19&$N$4&$N$5,$R:$AB,11,FALSE),0) -> 0.1315 | I19: =IFERROR(ROUND(F19*D19,2),0) -> 0 | J19: =IFERROR(ROUND(G19*D19,2),0) -> 0 | K19: =IFERROR(ROUND(H19*D19,2),0) -> 0 | L19: =+D19-I19-J19-K19 -> 0 | M19: Total Health Tax Deductible | N19: =IF(N12>0,MIN(N10-(N15+N16),J3,N11),MIN(N11,J3)) -> 0 | R19: CR60 | S19: CR60 | Z19: 1 | AA19: 0 | AB19: 0
A20: ESCI | B20: Rider | F20: 0 | G20: 1 | H20: 0 | I20: =IFERROR(ROUND(F20*D20,2),0) -> 0 | J20: =IFERROR(ROUND(G20*D20,2),0) -> 0 | K20: =IFERROR(ROUND(H20*D20,2),0) -> 0 | L20: =+D20-I20-J20-K20 -> 0 | M20: Total Retirement Tax Deductible | N20: =IF(N13>K3,K3,N13) -> 750 | R20: 20P10 | S20: 20P10 | Z20: 1 | AA20: 0 | AB20: 0
A21: WPE | B21: Rider | F21: 0 | G21: 0 | H21: 1 | I21: =IFERROR(ROUND(F21*D21,2),0) -> 0 | J21: =IFERROR(ROUND(G21*D21,2),0) -> 0 | K21: =IFERROR(ROUND(H21*D21,2),0) -> 0 | L21: =+D21-I21-J21-K21 -> 0 | R21: 20P10S | S21: 20P10S | Z21: 1 | AA21: 0 | AB21: 0
A22: Flexi Health | B22: Rider | F22: 0 | G22: 1 | H22: 0 | I22: =IFERROR(ROUND(F22*D22,2),0) -> 0 | J22: =IFERROR(ROUND(G22*D22,2),0) -> 0 | K22: =IFERROR(ROUND(H22*D22,2),0) -> 0 | L22: =+D22-I22-J22-K22 -> 0 | N22: Mode | O22: Factor | P22: Times per year | R22: 25P15 | S22: 25P15 | Z22: 1 | AA22: 0 | AB22: 0
A23: MEH | B23: Rider | F23: 0 | G23: 1 | H23: 0 | I23: =IFERROR(ROUND(F23*D23,2),0) -> 0 | J23: =IFERROR(ROUND(G23*D23,2),0) -> 0 | K23: =IFERROR(ROUND(H23*D23,2),0) -> 0 | L23: =+D23-I23-J23-K23 -> 0 | M23: รายปี | N23: A | O23: 1 | P23: 1 | R23: 25P15S | S23: 25P15S | Z23: 1 | AA23: 0 | AB23: 0
A24: MEK | B24: Rider | F24: 0 | G24: 1 | H24: 0 | I24: =IFERROR(ROUND(F24*D24,2),0) -> 0 | J24: =IFERROR(ROUND(G24*D24,2),0) -> 0 | K24: =IFERROR(ROUND(H24*D24,2),0) -> 0 | L24: =+D24-I24-J24-K24 -> 0 | M24: ราย 6 เดือน | N24: S | O24: 0.52 | P24: 2 | R24: S10P4 | S24: S10P4 | Z24: 1 | AA24: 0 | AB24: 0
A25: MEX | B25: Rider | C25: =IF(กรอกข้อมูล!$H$24="ไม่คุ้มครอง",0,IFERROR(VLOOKUP(A25,Cal!$A$13:$H$42,8,FALSE),0)) -> 0 | D25: =+C25*$N$7 -> 0 | E25: H | F25: 0 | G25: 1 | H25: 0 | I25: =IFERROR(ROUND(F25*D25,2),0) -> 0 | J25: =IFERROR(ROUND(G25*D25,2),0) -> 0 | K25: =IFERROR(ROUND(H25*D25,2),0) -> 0 | L25: =+D25-I25-J25-K25 -> 0 | M25: ราย 3 เดือน | N25: Q | O25: 0.27 | P25: 4 | R25: W85P10J | S25: W85P10J | Z25: 1 | AA25: 0 | AB25: 0
A26: MHP | B26: Rider | C26: =IF(กรอกข้อมูล!$H$30="ไม่คุ้มครอง",0,IFERROR(VLOOKUP(A26,Cal!$A$13:$H$42,8,FALSE),0)) -> 0 | D26: =+C26*$N$7 -> 0 | E26: H | F26: 0 | G26: 1 | H26: 0 | I26: =IFERROR(ROUND(F26*D26,2),0) -> 0 | J26: =IFERROR(ROUND(G26*D26,2),0) -> 0 | K26: =IFERROR(ROUND(H26*D26,2),0) -> 0 | L26: =+D26-I26-J26-K26 -> 0 | M26: รายเดือน | N26: M | O26: 0.09 | P26: 12 | R26: W85P10S | S26: W85P10S | Z26: 1 | AA26: 0 | AB26: 0
A27: MCI | B27: Rider | C27: =IF(กรอกข้อมูล!$H$32="ไม่คุ้มครอง",0,IFERROR(VLOOKUP(A27,Cal!$A$13:$H$42,8,FALSE),0)) -> 0 | D27: =+C27*$N$7 -> 0 | E27: H | F27: 0 | G27: 1 | H27: 0 | I27: =IFERROR(ROUND(F27*D27,2),0) -> 0 | J27: =IFERROR(ROUND(G27*D27,2),0) -> 0 | K27: =IFERROR(ROUND(H27*D27,2),0) -> 0 | L27: =+D27-I27-J27-K27 -> 0 | R27: AP | S27: AP | T27: 0 | U27: 64 | V27: M | W27: Std | X27: 1 | Y27: 1 | Z27: 0 | AA27: 0.1818 | AB27: 0.8182
A28: CIES | B28: Rider | C28: =IFERROR(VLOOKUP(A28,Cal!$A$13:$H$42,8,FALSE),0) -> 44789.5 | D28: =+C28*$N$7 -> 44789.5 | E28: H | F28: 0 | G28: 1 | H28: 0 | I28: =IFERROR(ROUND(F28*D28,2),0) -> 0 | J28: =IFERROR(ROUND(G28*D28,2),0) -> 44789.5 | K28: =IFERROR(ROUND(H28*D28,2),0) -> 0 | L28: =+D28-I28-J28-K28 -> 0 | M28: checkเบี้ยรายเดือนน้อยกว่า 1,000 & เลือกแผนไม่ถูก จะแสดง no | N28: =กรอกข้อมูล!E70 -> yes | R28: AP | S28: AP | T28: 0 | U28: 64 | V28: M | W28: Std | X28: 2 | Y28: 2 | Z28: 0 | AA28: 0.1818 | AB28: 0.8182
R29: AP | S29: AP | T29: 0 | U29: 64 | V29: M | W29: Std | X29: 3 | Y29: 3 | Z29: 0 | AA29: 0.1818 | AB29: 0.8182
R30: AP | S30: AP | T30: 0 | U30: 64 | V30: M | W30: Std | X30: 4 | Y30: 4 | Z30: 0 | AA30: 0.1818 | AB30: 0.8182
R31: AP | S31: AP | T31: 0 | U31: 64 | V31: F | W31: Std | X31: 1 | Y31: 1 | Z31: 0 | AA31: 0.1818 | AB31: 0.8182
R32: AP | S32: AP | T32: 0 | U32: 64 | V32: F | W32: Std | X32: 2 | Y32: 2 | Z32: 0 | AA32: 0.1818 | AB32: 0.8182
R33: AP | S33: AP | T33: 0 | U33: 64 | V33: F | W33: Std | X33: 3 | Y33: 3 | Z33: 0 | AA33: 0.1818 | AB33: 0.8182
R34: AP | S34: AP | T34: 0 | U34: 64 | V34: F | W34: Std | X34: 4 | Y34: 4 | Z34: 0 | AA34: 0.1818 | AB34: 0.8182
R35: ECARE | S35: ECARE | T35: 0 | U35: 64 | V35: M | W35: Std | X35: 1 | Y35: 1 | Z35: 0 | AA35: 0.6982 | AB35: 0.3018
R36: ECARE | S36: ECARE | T36: 0 | U36: 64 | V36: M | W36: Std | X36: 2 | Y36: 2 | Z36: 0 | AA36: 0.6982 | AB36: 0.3018
R37: ECARE | S37: ECARE | T37: 0 | U37: 64 | V37: M | W37: Std | X37: 3 | Y37: 3 | Z37: 0 | AA37: 0.6982 | AB37: 0.3018
R38: ECARE | S38: ECARE | T38: 0 | U38: 64 | V38: M | W38: Std | X38: 4 | Y38: 4 | Z38: 0 | AA38: 0.6982 | AB38: 0.3018
R39: ECARE | S39: ECARE | T39: 0 | U39: 64 | V39: F | W39: Std | X39: 1 | Y39: 1 | Z39: 0 | AA39: 0.6982 | AB39: 0.3018
R40: ECARE | S40: ECARE | T40: 0 | U40: 64 | V40: F | W40: Std | X40: 2 | Y40: 2 | Z40: 0 | AA40: 0.6982 | AB40: 0.3018
... R42: ECARE | S42: ECARE | T42: 0 | U42: 64 | V42: F | W42: Std | X42: 4 | Y42: 4 | Z42: 0 | AA42: 0.6982 | AB42: 0.3018
R43: =S43&T43&V43 -> DCI20M | S43: DCI | T43: 20 | U43: 20 | V43: M | W43: Std | X43: 1 | Y43: 4 | Z43: 0 | AA43: 0.6881 | AB43: 0.3119
R44: =S44&T44&V44 -> DCI21M | S44: DCI | T44: 21 | U44: 21 | V44: M | W44: Std | X44: 1 | Y44: 4 | Z44: 0 | AA44: 0.6894 | AB44: 0.3106
R45: =S45&T45&V45 -> DCI22M | S45: DCI | T45: 22 | U45: 22 | V45: M | W45: Std | X45: 1 | Y45: 4 | Z45: 0 | AA45: 0.6913 | AB45: 0.3087
R46: =S46&T46&V46 -> DCI23M | S46: DCI | T46: 23 | U46: 23 | V46: M | W46: Std | X46: 1 | Y46: 4 | Z46: 0 | AA46: 0.6937 | AB46: 0.3063
R47: =S47&T47&V47 -> DCI24M | S47: DCI | T47: 24 | U47: 24 | V47: M | W47: Std | X47: 1 | Y47: 4 | Z47: 0 | AA47: 0.6938 | AB47: 0.3062
R48: =S48&T48&V48 -> DCI25M | S48: DCI | T48: 25 | U48: 25 | V48: M | W48: Std | X48: 1 | Y48: 4 | Z48: 0 | AA48: 0.6955 | AB48: 0.3045
R49: =S49&T49&V49 -> DCI26M | S49: DCI | T49: 26 | U49: 26 | V49: M | W49: Std | X49: 1 | Y49: 4 | Z49: 0 | AA49: 0.6981 | AB49: 0.3019
R50: =S50&T50&V50 -> DCI27M | S50: DCI | T50: 27 | U50: 27 | V50: M | W50: Std | X50: 1 | Y50: 4 | Z50: 0 | AA50: 0.7016 | AB50: 0.2984
R51: =S51&T51&V51 -> DCI28M | S51: DCI | T51: 28 | U51: 28 | V51: M | W51: Std | X51: 1 | Y51: 4 | Z51: 0 | AA51: 0.7075 | AB51: 0.2925
R52: =S52&T52&V52 -> DCI29M | S52: DCI | T52: 29 | U52: 29 | V52: M | W52: Std | X52: 1 | Y52: 4 | Z52: 0 | AA52: 0.7127 | AB52: 0.2873
R53: =S53&T53&V53 -> DCI30M | S53: DCI | T53: 30 | U53: 30 | V53: M | W53: Std | X53: 1 | Y53: 4 | Z53: 0 | AA53: 0.715 | AB53: 0.285
R54: =S54&T54&V54 -> DCI31M | S54: DCI | T54: 31 | U54: 31 | V54: M | W54: Std | X54: 1 | Y54: 4 | Z54: 0 | AA54: 0.7148 | AB54: 0.2852
... R582: =S582&T582&V582 -> WLCI2052F | S582: WLCI20 | T582: 52 | U582: 52 | V582: F | W582: Std | X582: 1 | Y582: 4 | Z582: 0.9179 | AA582: 0.0821 | AB582: 0
R583: =S583&T583&V583 -> 20SS0M | S583: 20SS | T583: 0 | U583: 0 | V583: M | W583: Std | X583: 1 | Y583: 1 | Z583: 0 | AA583: 0.0013 | AB583: 0.9987
R584: =S584&T584&V584 -> 20SS1M | S584: 20SS | T584: 1 | U584: 1 | V584: M | W584: Std | X584: 1 | Y584: 1 | Z584: 0 | AA584: 0.0016 | AB584: 0.9984
R585: =S585&T585&V585 -> 20SS2M | S585: 20SS | T585: 2 | U585: 2 | V585: M | W585: Std | X585: 1 | Y585: 1 | Z585: 0 | AA585: 0.002 | AB585: 0.998
R586: =S586&T586&V586 -> 20SS3M | S586: 20SS | T586: 3 | U586: 3 | V586: M | W586: Std | X586: 1 | Y586: 1 | Z586: 0 | AA586: 0.0023 | AB586: 0.9977
R587: =S587&T587&V587 -> 20SS4M | S587: 20SS | T587: 4 | U587: 4 | V587: M | W587: Std | X587: 1 | Y587: 1 | Z587: 0 | AA587: 0.0027 | AB587: 0.9973
R588: =S588&T588&V588 -> 20SS5M | S588: 20SS | T588: 5 | U588: 5 | V588: M | W588: Std | X588: 1 | Y588: 1 | Z588: 0 | AA588: 0.0031 | AB588: 0.9969
R589: =S589&T589&V589 -> 20SS6M | S589: 20SS | T589: 6 | U589: 6 | V589: M | W589: Std | X589: 1 | Y589: 1 | Z589: 0 | AA589: 0.0035 | AB589: 0.9965
R590: =S590&T590&V590 -> 20SS7M | S590: 20SS | T590: 7 | U590: 7 | V590: M | W590: Std | X590: 1 | Y590: 1 | Z590: 0 | AA590: 0.004 | AB590: 0.996
R591: =S591&T591&V591 -> 20SS8M | S591: 20SS | T591: 8 | U591: 8 | V591: M | W591: Std | X591: 1 | Y591: 1 | Z591: 0 | AA591: 0.0045 | AB591: 0.9955
R592: =S592&T592&V592 -> 20SS9M | S592: 20SS | T592: 9 | U592: 9 | V592: M | W592: Std | X592: 1 | Y592: 1 | Z592: 0 | AA592: 0.005 | AB592: 0.995
R593: =S593&T593&V593 -> 20SS10M | S593: 20SS | T593: 10 | U593: 10 | V593: M | W593: Std | X593: 1 | Y593: 1 | Z593: 0 | AA593: 0.0056 | AB593: 0.9944
R594: =S594&T594&V594 -> 20SS11M | S594: 20SS | T594: 11 | U594: 11 | V594: M | W594: Std | X594: 1 | Y594: 1 | Z594: 0 | AA594: 0.0063 | AB594: 0.9937
... R714: =S714&T714&V714 -> 20SS65F | S714: 20SS | T714: 65 | U714: 65 | V714: F | W714: Std | X714: 1 | Y714: 1 | Z714: 0 | AA714: 0 | AB714: 1
R715: W99FU06 | Z715: 1 | AA715: 0 | AB715: 0
R716: W99FU12 | Z716: 1 | AA716: 0 | AB716: 0
R717: W99FU18 | Z717: 1 | AA717: 0 | AB717: 0
R718: W99FU99 | Z718: 1 | AA718: 0 | AB718: 0
R719: W99F99H | Z719: 1 | AA719: 0 | AB719: 0
R720: W99F99M | Z720: 1 | AA720: 0 | AB720: 0
R721: W99FH18 | Z721: 1 | AA721: 0 | AB721: 0
R722: W99FH99 | Z722: 1 | AA722: 0 | AB722: 0

Sheet TABCV(Female)
A1: Key | B1: CVPLAN | C1: CVSEX | D1: CVAGE | E1: 1 | F1: 2 | G1: 3 | H1: 4 | I1: 5 | J1: 6 | K1: 7 | L1: 8 | M1: 9 | N1: 10 | O1: 11 | P1: 12 | Q1: 13 | R1: 14 | S1: 15 | T1: 16 | U1: 17 | V1: 18 | W1: 19 | X1: 20 | Y1: 21 | Z1: 22 | AA1: 23 | AB1: 24 | AC1: 25 | AD1: 26 | AE1: 27 | AF1: 28 | AG1: 29 | AH1: 30 | AI1: 31 | AJ1: 32 | AK1: 33 | AL1: 34 | AM1: 35 | AN1: 36 | AO1: 37 | AP1: 38 | AQ1: 39 | AR1: 40 | AS1: 41 | AT1: 42 | AU1: 43 | AV1: 44 | AW1: 45 | AX1: 46 | AY1: 47 | AZ1: 48 | BA1: 49 | BB1: 50 | BC1: 51 | BD1: 52 | BE1: 53 | BF1: 54 | BG1: 55 | BH1: 56 | BI1: 57 | BJ1: 58 | BK1: 59 | BL1: 60 | BM1: 61 | BN1: 62 | BO1: 63 | BP1: 64 | BQ1: 65 | BR1: 66 | BS1: 67 | BT1: 68 | BU1: 69 | BV1: 70 | BW1: 71 | BX1: 72 | BY1: 73 | BZ1: 74 | CA1: 75 | CB1: 76 | CC1: 77 | CD1: 78 | CE1: 79 | CF1: 80 | CG1: 81 | CH1: 82 | CI1: 83 | CJ1: 84 | CK1: 85 | CL1: 86 | CM1: 87 | CN1: 88 | CO1: 89 | CP1: 90 | CQ1: 91 | CR1: 92 | CS1: 93 | CT1: 94 | CU1: 95 | CV1: 96 | CW1: 97 | CX1: 98 | CY1: 99 | CZ1: 100 | DA1: PVL00 | DB1: PVL01 | DC1: PVL02 | DD1: PVL03 | DE1: PVL04 | DF1: PVL05 | DG1: PVL06 | DH1: PVL07 | DI1: PVL08 | DJ1: PVL09 | DK1: PVL10 | DL1: PVL11 | DM1: PVL12 | DN1: PVL13 | DO1: PVL14 | DP1: PVL15 | DQ1: PVL16 | DR1: PVL17 | DS1: PVL18 | DT1: PVL19 | DU1: PVL20 | DV1: PVL21 | DW1: PVL22 | DX1: PVL23 | DY1: PVL24 | DZ1: PVL25 | EA1: PVL26 | EB1: PVL27 | EC1: PVL28 | ED1: PVL29 | EE1: PVL30 | EF1: PVL31 | EG1: PVL32 | EH1: PVL33 | EI1: PVL34 | EJ1: PVL35 | EK1: PVL36 | EL1: PVL37 | EM1: PVL38 | EN1: PVL39 | EO1: PVL40 | EP1: PVL41 | EQ1: PVL42 | ER1: PVL43 | ES1: PVL44 | ET1: PVL45 | EU1: PVL46 | EV1: PVL47 | EW1: PVL48 | EX1: PVL49 | EY1: PVL50 | EZ1: PVL51 | FA1: PVL52 | FB1: PVL53 | FC1: PVL54 | FD1: PVL55 | FE1: PVL56 | FF1: PVL57 | FG1: PVL58 | FH1: PVL59 | FI1: PVL60 | FJ1: PVL61 | FK1: PVL62 | FL1: PVL63 | FM1: PVL64 | FN1: PVL65 | FO1: PVL66 | FP1: PVL67 | FQ1: PVL68 | FR1: PVL69 | FS1: PVL70 | FT1: PVL71 | FU1: PVL72 | FV1: PVL73 | FW1: PVL74 | FX1: PVL75 | FY1: PVL76 | FZ1: PVL77 | GA1: PVL78 | GB1: PVL79 | GC1: PVL80 | GD1: PVL81 | GE1: PVL82 | GF1: PVL83 | GG1: PVL84 | GH1: PVL85 | GI1: PVL86 | GJ1: PVL87 | GK1: PVL88 | GL1: PVL89 | GM1: PVL90 | GN1: PVL91 | GO1: PVL92 | GP1: PVL93 | GQ1: PVL94 | GR1: PVL95 | GS1: PVL96 | GT1: PVL97 | GU1: PVL98 | GV1: PVL99 | GW1: PVL100 | GX1: ETA00 | GY1: ETA01 | GZ1: ETA02 | HA1: ETA03 | HB1: ETA04 | HC1: ETA05 | HD1: ETA06 | HE1: ETA07 | HF1: ETA08 | HG1: ETA09 | HH1: ETA10 | HI1: ETA11 | HJ1: ETA12 | HK1: ETA13 | HL1: ETA14 | HM1: ETA15 | HN1: ETA16 | HO1: ETA17 | HP1: ETA18 | HQ1: ETA19 | HR1: ETA20 | HS1: ETA21 | HT1: ETA22 | HU1: ETA23 | HV1: ETA24 | HW1: ETA25 | HX1: ETA26 | HY1: ETA27 | HZ1: ETA28 | IA1: ETA29 | IB1: ETA30 | IC1: ETA31 | ID1: ETA32 | IE1: ETA33 | IF1: ETA34 | IG1: ETA35 | IH1: ETA36 | II1: ETA37 | IJ1: ETA38 | IK1: ETA39 | IL1: ETA40 | IM1: ETA41 | IN1: ETA42 | IO1: ETA43 | IP1: ETA44 | IQ1: ETA45 | IR1: ETA46 | IS1: ETA47 | IT1: ETA48 | IU1: ETA49 | IV1: ETA50 | IW1: ETA51 | IX1: ETA52 | IY1: ETA53 | IZ1: ETA54 | JA1: ETA55 | JB1: ETA56 | JC1: ETA57 | JD1: ETA58 | JE1: ETA59 | JF1: ETA60 | JG1: ETA61 | JH1: ETA62 | JI1: ETA63 | JJ1: ETA64 | JK1: ETA65 | JL1: ETA66 | JM1: ETA67 | JN1: ETA68 | JO1: ETA69 | JP1: ETA70 | JQ1: ETA71 | JR1: ETA72 | JS1: ETA73 | JT1: ETA74 | JU1: ETA75 | JV1: ETA76 | JW1: ETA77 | JX1: ETA78 | JY1: ETA79 | JZ1: ETA80 | KA1: ETA81 | KB1: ETA82 | KC1: ETA83 | KD1: ETA84 | KE1: ETA85 | KF1: ETA86 | KG1: ETA87 | KH1: ETA88 | KI1: ETA89 | KJ1: ETA90 | KK1: ETA91 | KL1: ETA92 | KM1: ETA93 | KN1: ETA94 | KO1: ETA95 | KP1: ETA96 | KQ1: ETA97 | KR1: ETA98 | KS1: ETA99 | KT1: ETA100 | KU1: PEN00 | KV1: PEN01 | KW1: PEN02 | KX1: PEN03 | KY1: PEN04 | KZ1: PEN05 | LA1: PEN06 | LB1: PEN07 | LC1: PEN08 | LD1: PEN09 | LE1: PEN10 | LF1: PEN11 | LG1: PEN12 | LH1: PEN13 | LI1: PEN14 | LJ1: PEN15 | LK1: PEN16 | LL1: PEN17 | LM1: PEN18 | LN1: PEN19 | LO1: PEN20 | LP1: PEN21 | LQ1: PEN22 | LR1: PEN23 | LS1: PEN24 | LT1: PEN25 | LU1: PEN26 | LV1: PEN27 | LW1: PEN28 | LX1: PEN29 | LY1: PEN30 | LZ1: PEN31 | MA1: PEN32 | MB1: PEN33 | MC1: PEN34 | MD1: PEN35 | ME1: PEN36 | MF1: PEN37 | MG1: PEN38 | MH1: PEN39 | MI1: PEN40 | MJ1: PEN41 | MK1: PEN42 | ML1: PEN43 | MM1: PEN44 | MN1: PEN45 | MO1: PEN46 | MP1: PEN47 | MQ1: PEN48 | MR1: PEN49 | MS1: PEN50 | MT1: PEN51 | MU1: PEN52 | MV1: PEN53 | MW1: PEN54 | MX1: PEN55 | MY1: PEN56 | MZ1: PEN57 | NA1: PEN58 | NB1: PEN59 | NC1: PEN60 | ND1: PEN61 | NE1: PEN62 | NF1: PEN63 | NG1: PEN64 | NH1: PEN65 | NI1: PEN66 | NJ1: PEN67 | NK1: PEN68 | NL1: PEN69 | NM1: PEN70 | NN1: PEN71 | NO1: PEN72 | NP1: PEN73 | NQ1: PEN74 | NR1: PEN75 | NS1: PEN76 | NT1: PEN77 | NU1: PEN78 | NV1: PEN79 | NW1: PEN80 | NX1: PEN81 | NY1: PEN82 | NZ1: PEN83 | OA1: PEN84 | OB1: PEN85 | OC1: PEN86 | OD1: PEN87 | OE1: PEN88 | OF1: PEN89 | OG1: PEN90 | OH1: PEN91 | OI1: PEN92 | OJ1: PEN93 | OK1: PEN94 | OL1: PEN95 | OM1: PEN96 | ON1: PEN97 | OO1: PEN98 | OP1: PEN99 | OQ1: PEN100
A2: 06F25 | B2: W80F06 | C2: F | D2: 25 | E2: 34 | F2: 143 | G2: 372 | H2: 585 | I2: 839 | J2: 1025 | K2: 1035 | L2: 1046 | M2: 1056 | N2: 1067 | O2: 1079 | P2: 1090 | Q2: 1102 | R2: 1115 | S2: 1127 | T2: 1140 | U2: 1154 | V2: 1167 | W2: 1181 | X2: 1196 | Y2: 1210 | Z2: 1226 | AA2: 1241 | AB2: 1257 | AC2: 1273 | AD2: 1290 | AE2: 1307 | AF2: 1324 | AG2: 1342 | AH2: 1360 | AI2: 1379 | AJ2: 1398 | AK2: 1418 | AL2: 1438 | AM2: 1458 | AN2: 1479 | AO2: 1500 | AP2: 1522 | AQ2: 1544 | AR2: 1566 | AS2: 1589 | AT2: 1612 | AU2: 1636 | AV2: 1660 | AW2: 1684 | AX2: 1709 | AY2: 1735 | AZ2: 1761 | BA2: 1787 | BB2: 1815 | BC2: 1844 | BD2: 1874 | BE2: 1907 | BF2: 1942 | BG2: 2000 | BH2: 0 | BI2: 0 | BJ2: 0 | BK2: 0 | BL2: 0 | BM2: 0 | BN2: 0 | BO2: 0 | BP2: 0 | BQ2: 0 | BR2: 0 | BS2: 0 | BT2: 0 | BU2: 0 | BV2: 0 | BW2: 0 | BX2: 0 | BY2: 0 | BZ2: 0 | CA2: 0 | CB2: 0 | CC2: 0 | CD2: 0 | CE2: 0 | CF2: 0 | CG2: 0 | CH2: 0 | CI2: 0 | CJ2: 0 | CK2: 0 | CL2: 0 | CM2: 0 | CN2: 0 | CO2: 0 | CP2: 0 | CQ2: 0 | CR2: 0 | CS2: 0 | CT2: 0 | CU2: 0 | CV2: 0 | CW2: 0 | CX2: 0 | CY2: 0 | CZ2: 0 | DA2: 0 | DB2: 143 | DC2: 586 | DD2: 1121 | DE2: 1327 | DF2: 1574 | DG2: 0 | DH2: 0 | DI2: 0 | DJ2: 0 | DK2: 0 | DL2: 0 | DM2: 0 | DN2: 0 | DO2: 0 | DP2: 0 | DQ2: 0 | DR2: 0 | DS2: 0 | DT2: 0 | DU2: 0 | DV2: 0 | DW2: 0 | DX2: 0 | DY2: 0 | DZ2: 0 | EA2: 0 | EB2: 0 | EC2: 0 | ED2: 0 | EE2: 0 | EF2: 0 | EG2: 0 | EH2: 0 | EI2: 0 | EJ2: 0 | EK2: 0 | EL2: 0 | EM2: 0 | EN2: 0 | EO2: 0 | EP2: 0 | EQ2: 0 | ER2: 0 | ES2: 0 | ET2: 0 | EU2: 0 | EV2: 0 | EW2: 0 | EX2: 0 | EY2: 0 | EZ2: 0 | FA2: 0 | FB2: 0 | FC2: 0 | FD2: 0 | FE2: 0 | FF2: 0 | FG2: 0 | FH2: 0 | FI2: 0 | FJ2: 0 | FK2: 0 | FL2: 0 | FM2: 0 | FN2: 0 | FO2: 0 | FP2: 0 | FQ2: 0 | FR2: 0 | FS2: 0 | FT2: 0 | FU2: 0 | FV2: 0 | FW2: 0 | FX2: 0 | FY2: 0 | FZ2: 0 | GA2: 0 | GB2: 0 | GC2: 0 | GD2: 0 | GE2: 0 | GF2: 0 | GG2: 0 | GH2: 0 | GI2: 0 | GJ2: 0 | GK2: 0 | GL2: 0 | GM2: 0 | GN2: 0 | GO2: 0 | GP2: 0 | GQ2: 0 | GR2: 0 | GS2: 0 | GT2: 0 | GU2: 0 | GV2: 0 | GW2: 0 | GX2: 0 | GY2: 32125 | GZ2: 51235 | HA2: 52000 | HB2: 51000 | HC2: 50000 | HD2: 0 | HE2: 0 | HF2: 0 | HG2: 0 | HH2: 0 | HI2: 0 | HJ2: 0 | HK2: 0 | HL2: 0 | HM2: 0 | HN2: 0 | HO2: 0 | HP2: 0 | HQ2: 0 | HR2: 0 | HS2: 0 | HT2: 0 | HU2: 0 | HV2: 0 | HW2: 0 | HX2: 0 | HY2: 0 | HZ2: 0 | IA2: 0 | IB2: 0 | IC2: 0 | ID2: 0 | IE2: 0 | IF2: 0 | IG2: 0 | IH2: 0 | II2: 0 | IJ2: 0 | IK2: 0 | IL2: 0 | IM2: 0 | IN2: 0 | IO2: 0 | IP2: 0 | IQ2: 0 | IR2: 0 | IS2: 0 | IT2: 0 | IU2: 0 | IV2: 0 | IW2: 0 | IX2: 0 | IY2: 0 | IZ2: 0 | JA2: 0 | JB2: 0 | JC2: 0 | JD2: 0 | JE2: 0 | JF2: 0 | JG2: 0 | JH2: 0 | JI2: 0 | JJ2: 0 | JK2: 0 | JL2: 0 | JM2: 0 | JN2: 0 | JO2: 0 | JP2: 0 | JQ2: 0 | JR2: 0 | JS2: 0 | JT2: 0 | JU2: 0 | JV2: 0 | JW2: 0 | JX2: 0 | JY2: 0 | JZ2: 0 | KA2: 0 | KB2: 0 | KC2: 0 | KD2: 0 | KE2: 0 | KF2: 0 | KG2: 0 | KH2: 0 | KI2: 0 | KJ2: 0 | KK2: 0 | KL2: 0 | KM2: 0 | KN2: 0 | KO2: 0 | KP2: 0 | KQ2: 0 | KR2: 0 | KS2: 0 | KT2: 0 | KU2: 0 | KV2: 0 | KW2: 0 | KX2: 1112 | KY2: 1317 | KZ2: 1564 | LA2: 0 | LB2: 0 | LC2: 0 | LD2: 0 | LE2: 0 | LF2: 0 | LG2: 0 | LH2: 0 | LI2: 0 | LJ2: 0 | LK2: 0 | LL2: 0 | LM2: 0 | LN2: 0 | LO2: 0 | LP2: 0 | LQ2: 0 | LR2: 0 | LS2: 0 | LT2: 0 | LU2: 0 | LV2: 0 | LW2: 0 | LX2: 0 | LY2: 0 | LZ2: 0 | MA2: 0 | MB2: 0 | MC2: 0 | MD2: 0 | ME2: 0 | MF2: 0 | MG2: 0 | MH2: 0 | MI2: 0 | MJ2: 0 | MK2: 0 | ML2: 0 | MM2: 0 | MN2: 0 | MO2: 0 | MP2: 0 | MQ2: 0 | MR2: 0 | MS2: 0 | MT2: 0 | MU2: 0 | MV2: 0 | MW2: 0 | MX2: 0 | MY2: 0 | MZ2: 0 | NA2: 0 | NB2: 0 | NC2: 0 | ND2: 0 | NE2: 0 | NF2: 0 | NG2: 0 | NH2: 0 | NI2: 0 | NJ2: 0 | NK2: 0 | NL2: 0 | NM2: 0 | NN2: 0 | NO2: 0 | NP2: 0 | NQ2: 0 | NR2: 0 | NS2: 0 | NT2: 0 | NU2: 0 | NV2: 0 | NW2: 0 | NX2: 0 | NY2: 0 | NZ2: 0 | OA2: 0 | OB2: 0 | OC2: 0 | OD2: 0 | OE2: 0 | OF2: 0 | OG2: 0 | OH2: 0 | OI2: 0 | OJ2: 0 | OK2: 0 | OL2: 0 | OM2: 0 | ON2: 0 | OO2: 0 | OP2: 0 | OQ2: 0
A3: 06F26 | B3: W80F06 | C3: F | D3: 26 | E3: 34 | F3: 145 | G3: 376 | H3: 591 | I3: 848 | J3: 1035 | K3: 1046 | L3: 1056 | M3: 1067 | N3: 1079 | O3: 1090 | P3: 1102 | Q3: 1115 | R3: 1127 | S3: 1140 | T3: 1154 | U3: 1167 | V3: 1181 | W3: 1196 | X3: 1210 | Y3: 1226 | Z3: 1241 | AA3: 1257 | AB3: 1273 | AC3: 1290 | AD3: 1307 | AE3: 1324 | AF3: 1342 | AG3: 1360 | AH3: 1379 | AI3: 1398 | AJ3: 1418 | AK3: 1438 | AL3: 1458 | AM3: 1479 | AN3: 1500 | AO3: 1522 | AP3: 1544 | AQ3: 1566 | AR3: 1589 | AS3: 1612 | AT3: 1636 | AU3: 1660 | AV3: 1684 | AW3: 1709 | AX3: 1735 | AY3: 1761 | AZ3: 1787 | BA3: 1815 | BB3: 1844 | BC3: 1874 | BD3: 1907 | BE3: 1942 | BF3: 2000 | BG3: 0 | BH3: 0 | BI3: 0 | BJ3: 0 | BK3: 0 | BL3: 0 | BM3: 0 | BN3: 0 | BO3: 0 | BP3: 0 | BQ3: 0 | BR3: 0 | BS3: 0 | BT3: 0 | BU3: 0 | BV3: 0 | BW3: 0 | BX3: 0 | BY3: 0 | BZ3: 0 | CA3: 0 | CB3: 0 | CC3: 0 | CD3: 0 | CE3: 0 | CF3: 0 | CG3: 0 | CH3: 0 | CI3: 0 | CJ3: 0 | CK3: 0 | CL3: 0 | CM3: 0 | CN3: 0 | CO3: 0 | CP3: 0 | CQ3: 0 | CR3: 0 | CS3: 0 | CT3: 0 | CU3: 0 | CV3: 0 | CW3: 0 | CX3: 0 | CY3: 0 | CZ3: 0 | DA3: 0 | DB3: 139 | DC3: 578 | DD3: 1118 | DE3: 1326 | DF3: 1575 | DG3: 0 | DH3: 0 | DI3: 0 | DJ3: 0 | DK3: 0 | DL3: 0 | DM3: 0 | DN3: 0 | DO3: 0 | DP3: 0 | DQ3: 0 | DR3: 0 | DS3: 0 | DT3: 0 | DU3: 0 | DV3: 0 | DW3: 0 | DX3: 0 | DY3: 0 | DZ3: 0 | EA3: 0 | EB3: 0 | EC3: 0 | ED3: 0 | EE3: 0 | EF3: 0 | EG3: 0 | EH3: 0 | EI3: 0 | EJ3: 0 | EK3: 0 | EL3: 0 | EM3: 0 | EN3: 0 | EO3: 0 | EP3: 0 | EQ3: 0 | ER3: 0 | ES3: 0 | ET3: 0 | EU3: 0 | EV3: 0 | EW3: 0 | EX3: 0 | EY3: 0 | EZ3: 0 | FA3: 0 | FB3: 0 | FC3: 0 | FD3: 0 | FE3: 0 | FF3: 0 | FG3: 0 | FH3: 0 | FI3: 0 | FJ3: 0 | FK3: 0 | FL3: 0 | FM3: 0 | FN3: 0 | FO3: 0 | FP3: 0 | FQ3: 0 | FR3: 0 | FS3: 0 | FT3: 0 | FU3: 0 | FV3: 0 | FW3: 0 | FX3: 0 | FY3: 0 | FZ3: 0 | GA3: 0 | GB3: 0 | GC3: 0 | GD3: 0 | GE3: 0 | GF3: 0 | GG3: 0 | GH3: 0 | GI3: 0 | GJ3: 0 | GK3: 0 | GL3: 0 | GM3: 0 | GN3: 0 | GO3: 0 | GP3: 0 | GQ3: 0 | GR3: 0 | GS3: 0 | GT3: 0 | GU3: 0 | GV3: 0 | GW3: 0 | GX3: 0 | GY3: 31068 | GZ3: 50168 | HA3: 51000 | HB3: 50000 | HC3: 49000 | HD3: 0 | HE3: 0 | HF3: 0 | HG3: 0 | HH3: 0 | HI3: 0 | HJ3: 0 | HK3: 0 | HL3: 0 | HM3: 0 | HN3: 0 | HO3: 0 | HP3: 0 | HQ3: 0 | HR3: 0 | HS3: 0 | HT3: 0 | HU3: 0 | HV3: 0 | HW3: 0 | HX3: 0 | HY3: 0 | HZ3: 0 | IA3: 0 | IB3: 0 | IC3: 0 | ID3: 0 | IE3: 0 | IF3: 0 | IG3: 0 | IH3: 0 | II3: 0 | IJ3: 0 | IK3: 0 | IL3: 0 | IM3: 0 | IN3: 0 | IO3: 0 | IP3: 0 | IQ3: 0 | IR3: 0 | IS3: 0 | IT3: 0 | IU3: 0 | IV3: 0 | IW3: 0 | IX3: 0 | IY3: 0 | IZ3: 0 | JA3: 0 | JB3: 0 | JC3: 0 | JD3: 0 | JE3: 0 | JF3: 0 | JG3: 0 | JH3: 0 | JI3: 0 | JJ3: 0 | JK3: 0 | JL3: 0 | JM3: 0 | JN3: 0 | JO3: 0 | JP3: 0 | JQ3: 0 | JR3: 0 | JS3: 0 | JT3: 0 | JU3: 0 | JV3: 0 | JW3: 0 | JX3: 0 | JY3: 0 | JZ3: 0 | KA3: 0 | KB3: 0 | KC3: 0 | KD3: 0 | KE3: 0 | KF3: 0 | KG3: 0 | KH3: 0 | KI3: 0 | KJ3: 0 | KK3: 0 | KL3: 0 | KM3: 0 | KN3: 0 | KO3: 0 | KP3: 0 | KQ3: 0 | KR3: 0 | KS3: 0 | KT3: 0 | KU3: 0 | KV3: 0 | KW3: 0 | KX3: 1108 | KY3: 1316 | KZ3: 1565 | LA3: 0 | LB3: 0 | LC3: 0 | LD3: 0 | LE3: 0 | LF3: 0 | LG3: 0 | LH3: 0 | LI3: 0 | LJ3: 0 | LK3: 0 | LL3: 0 | LM3: 0 | LN3: 0 | LO3: 0 | LP3: 0 | LQ3: 0 | LR3: 0 | LS3: 0 | LT3: 0 | LU3: 0 | LV3: 0 | LW3: 0 | LX3: 0 | LY3: 0 | LZ3: 0 | MA3: 0 | MB3: 0 | MC3: 0 | MD3: 0 | ME3: 0 | MF3: 0 | MG3: 0 | MH3: 0 | MI3: 0 | MJ3: 0 | MK3: 0 | ML3: 0 | MM3: 0 | MN3: 0 | MO3: 0 | MP3: 0 | MQ3: 0 | MR3: 0 | MS3: 0 | MT3: 0 | MU3: 0 | MV3: 0 | MW3: 0 | MX3: 0 | MY3: 0 | MZ3: 0 | NA3: 0 | NB3: 0 | NC3: 0 | ND3: 0 | NE3: 0 | NF3: 0 | NG3: 0 | NH3: 0 | NI3: 0 | NJ3: 0 | NK3: 0 | NL3: 0 | NM3: 0 | NN3: 0 | NO3: 0 | NP3: 0 | NQ3: 0 | NR3: 0 | NS3: 0 | NT3: 0 | NU3: 0 | NV3: 0 | NW3: 0 | NX3: 0 | NY3: 0 | NZ3: 0 | OA3: 0 | OB3: 0 | OC3: 0 | OD3: 0 | OE3: 0 | OF3: 0 | OG3: 0 | OH3: 0 | OI3: 0 | OJ3: 0 | OK3: 0 | OL3: 0 | OM3: 0 | ON3: 0 | OO3: 0 | OP3: 0 | OQ3: 0
A4: 06F27 | B4: W80F06 | C4: F | D4: 27 | E4: 35 | F4: 147 | G4: 380 | H4: 597 | I4: 856 | J4: 1046 | K4: 1056 | L4: 1067 | M4: 1079 | N4: 1090 | O4: 1102 | P4: 1115 | Q4: 1127 | R4: 1140 | S4: 1154 | T4: 1167 | U4: 1181 | V4: 1196 | W4: 1210 | X4: 1226 | Y4: 1241 | Z4: 1257 | AA4: 1273 | AB4: 1290 | AC4: 1307 | AD4: 1324 | AE4: 1342 | AF4: 1360 | AG4: 1379 | AH4: 1398 | AI4: 1418 | AJ4: 1438 | AK4: 1458 | AL4: 1479 | AM4: 1500 | AN4: 1522 | AO4: 1544 | AP4: 1566 | AQ4: 1589 | AR4: 1612 | AS4: 1636 | AT4: 1660 | AU4: 1684 | AV4: 1709 | AW4: 1735 | AX4: 1761 | AY4: 1787 | AZ4: 1815 | BA4: 1844 | BB4: 1874 | BC4: 1907 | BD4: 1942 | BE4: 2000 | BF4: 0 | BG4: 0 | BH4: 0 | BI4: 0 | BJ4: 0 | BK4: 0 | BL4: 0 | BM4: 0 | BN4: 0 | BO4: 0 | BP4: 0 | BQ4: 0 | BR4: 0 | BS4: 0 | BT4: 0 | BU4: 0 | BV4: 0 | BW4: 0 | BX4: 0 | BY4: 0 | BZ4: 0 | CA4: 0 | CB4: 0 | CC4: 0 | CD4: 0 | CE4: 0 | CF4: 0 | CG4: 0 | CH4: 0 | CI4: 0 | CJ4: 0 | CK4: 0 | CL4: 0 | CM4: 0 | CN4: 0 | CO4: 0 | CP4: 0 | CQ4: 0 | CR4: 0 | CS4: 0 | CT4: 0 | CU4: 0 | CV4: 0 | CW4: 0 | CX4: 0 | CY4: 0 | CZ4: 0 | DA4: 0 | DB4: 140 | DC4: 570 | DD4: 1115 | DE4: 1324 | DF4: 1576 | DG4: 0 | DH4: 0 | DI4: 0 | DJ4: 0 | DK4: 0 | DL4: 0 | DM4: 0 | DN4: 0 | DO4: 0 | DP4: 0 | DQ4: 0 | DR4: 0 | DS4: 0 | DT4: 0 | DU4: 0 | DV4: 0 | DW4: 0 | DX4: 0 | DY4: 0 | DZ4: 0 | EA4: 0 | EB4: 0 | EC4: 0 | ED4: 0 | EE4: 0 | EF4: 0 | EG4: 0 | EH4: 0 | EI4: 0 | EJ4: 0 | EK4: 0 | EL4: 0 | EM4: 0 | EN4: 0 | EO4: 0 | EP4: 0 | EQ4: 0 | ER4: 0 | ES4: 0 | ET4: 0 | EU4: 0 | EV4: 0 | EW4: 0 | EX4: 0 | EY4: 0 | EZ4: 0 | FA4: 0 | FB4: 0 | FC4: 0 | FD4: 0 | FE4: 0 | FF4: 0 | FG4: 0 | FH4: 0 | FI4: 0 | FJ4: 0 | FK4: 0 | FL4: 0 | FM4: 0 | FN4: 0 | FO4: 0 | FP4: 0 | FQ4: 0 | FR4: 0 | FS4: 0 | FT4: 0 | FU4: 0 | FV4: 0 | FW4: 0 | FX4: 0 | FY4: 0 | FZ4: 0 | GA4: 0 | GB4: 0 | GC4: 0 | GD4: 0 | GE4: 0 | GF4: 0 | GG4: 0 | GH4: 0 | GI4: 0 | GJ4: 0 | GK4: 0 | GL4: 0 | GM4: 0 | GN4: 0 | GO4: 0 | GP4: 0 | GQ4: 0 | GR4: 0 | GS4: 0 | GT4: 0 | GU4: 0 | GV4: 0 | GW4: 0 | GX4: 0 | GY4: 30171 | GZ4: 49102 | HA4: 50000 | HB4: 49000 | HC4: 48000 | HD4: 0 | HE4: 0 | HF4: 0 | HG4: 0 | HH4: 0 | HI4: 0 | HJ4: 0 | HK4: 0 | HL4: 0 | HM4: 0 | HN4: 0 | HO4: 0 | HP4: 0 | HQ4: 0 | HR4: 0 | HS4: 0 | HT4: 0 | HU4: 0 | HV4: 0 | HW4: 0 | HX4: 0 | HY4: 0 | HZ4: 0 | IA4: 0 | IB4: 0 | IC4: 0 | ID4: 0 | IE4: 0 | IF4: 0 | IG4: 0 | IH4: 0 | II4: 0 | IJ4: 0 | IK4: 0 | IL4: 0 | IM4: 0 | IN4: 0 | IO4: 0 | IP4: 0 | IQ4: 0 | IR4: 0 | IS4: 0 | IT4: 0 | IU4: 0 | IV4: 0 | IW4: 0 | IX4: 0 | IY4: 0 | IZ4: 0 | JA4: 0 | JB4: 0 | JC4: 0 | JD4: 0 | JE4: 0 | JF4: 0 | JG4: 0 | JH4: 0 | JI4: 0 | JJ4: 0 | JK4: 0 | JL4: 0 | JM4: 0 | JN4: 0 | JO4: 0 | JP4: 0 | JQ4: 0 | JR4: 0 | JS4: 0 | JT4: 0 | JU4: 0 | JV4: 0 | JW4: 0 | JX4: 0 | JY4: 0 | JZ4: 0 | KA4: 0 | KB4: 0 | KC4: 0 | KD4: 0 | KE4: 0 | KF4: 0 | KG4: 0 | KH4: 0 | KI4: 0 | KJ4: 0 | KK4: 0 | KL4: 0 | KM4: 0 | KN4: 0 | KO4: 0 | KP4: 0 | KQ4: 0 | KR4: 0 | KS4: 0 | KT4: 0 | KU4: 0 | KV4: 0 | KW4: 0 | KX4: 1105 | KY4: 1314 | KZ4: 1565 | LA4: 0 | LB4: 0 | LC4: 0 | LD4: 0 | LE4: 0 | LF4: 0 | LG4: 0 | LH4: 0 | LI4: 0 | LJ4: 0 | LK4: 0 | LL4: 0 | LM4: 0 | LN4: 0 | LO4: 0 | LP4: 0 | LQ4: 0 | LR4: 0 | LS4: 0 | LT4: 0 | LU4: 0 | LV4: 0 | LW4: 0 | LX4: 0 | LY4: 0 | LZ4: 0 | MA4: 0 | MB4: 0 | MC4: 0 | MD4: 0 | ME4: 0 | MF4: 0 | MG4: 0 | MH4: 0 | MI4: 0 | MJ4: 0 | MK4: 0 | ML4: 0 | MM4: 0 | MN4: 0 | MO4: 0 | MP4: 0 | MQ4: 0 | MR4: 0 | MS4: 0 | MT4: 0 | MU4: 0 | MV4: 0 | MW4: 0 | MX4: 0 | MY4: 0 | MZ4: 0 | NA4: 0 | NB4: 0 | NC4: 0 | ND4: 0 | NE4: 0 | NF4: 0 | NG4: 0 | NH4: 0 | NI4: 0 | NJ4: 0 | NK4: 0 | NL4: 0 | NM4: 0 | NN4: 0 | NO4: 0 | NP4: 0 | NQ4: 0 | NR4: 0 | NS4: 0 | NT4: 0 | NU4: 0 | NV4: 0 | NW4: 0 | NX4: 0 | NY4: 0 | NZ4: 0 | OA4: 0 | OB4: 0 | OC4: 0 | OD4: 0 | OE4: 0 | OF4: 0 | OG4: 0 | OH4: 0 | OI4: 0 | OJ4: 0 | OK4: 0 | OL4: 0 | OM4: 0 | ON4: 0 | OO4: 0 | OP4: 0 | OQ4: 0
